Workbook

Sheet EOI
A1: start | B1: end | C1: Implementing_Partner_Support_Organization | D1: What is the name of your business/Enterprise? | E1: Please provide a brief description of what your business / enterprise provides. | F1: Is your business/enterprise formally registered with URSB? | G1: If yes, which kind of registration | H1: Does your business/enterprise have a Tax Identification Number? | I1: If yes, provide the Tin Number | J1: Upload a copy of your Business/Company's URA Certificate of Registration. | K1: Upload a copy of your Business/Company's URA Certificate of Registration._URL | L1: Does the business have a NSSF Business / Employer Number? | M1: Please provide your Company/Business NSSF number | N1: In which Region is your Enterprise located? | O1: In which district is your Enterprise/Business located? | P1: In which Subcounty of the district is your Enterprise/Business located? | Q1: In which Parish of the Subcounty is your Enterprise/Business located? | R1: what sector is your Enterprise/Business operating? | S1: Please specify the sector | T1: How many founders does your Enterprise/Business have? | U1: How many of the Enterprise/Business founders are female? | V1: How many full-time staff do you have? | W1: How many part-time employees do you have? | X1: Provide a list and a brief description about theproduct(s) or service(s) that your business provide | Y1: What problem is your business trying to solve? | Z1: How many suppliers or supplier categories do you have? | AA1: How many people do your suppliers employ? | AB1: _id | AC1: Please explain your business model. | AD1: How much revenue (in UGX) has your Business generated in the last two years (24 months)? | AE1: Have you taken any investments or subsidies yet? | AF1: How many investments or subsidies have you (business) taken? | AG1: Have you participated in any incubator, accelerator or enterprise development program before? | AH1: Please tell us more about it. We would like to know who was running it, what it was offering, what you received, the impact you created, etc | AI1: How much funding (in UGX) would you need to facilitate your business growth plan over the next 1 year? | AJ1: With the financing and technical support provided from the 10X Digital Economy, what growth milestones do you seek to achieve? | AK1: Why do you believe that your business is well positioned to grow and reach more customers? | AL1: Is there any other information about your company that you feel we should know about? | AM1: Which other information about your Enterprise/business should we know about? | AN1: Are you affiliated to anyone working at UNCDF, Refactory, WITU and Outbox? | AO1: Please describe the nature of your relationship with the person at UNCDF, Refactory, WITU and Outbox? | AP1: Do you have a personal,professional or family relationship to anyone working at the following Hubs and organisations; Mkazipreneur, Challenges Uganda, DFCU Foundation, Excel Hort, Finfing XY, MUBS EIIC, PEDN, Stanbic Incubator, Mastercard Foundation, UNCDF, Women In Technology, Refactory & Outbox Uganda Limited.? | AQ1: Please describe the nature of your relationship with the person in any of the above Hubs and organisation? | AR1: Are you or anyone in your business a politically exposed person? | AS1: What is (are) the name of the person(s), the public office (s) held and the role(s) of the staff in your business who are politically exposed? | AT1: What convinced you to apply to the 10X Digital Economy Program? | AU1: How did you hear about to the 10X Digital Economy Program? | AV1: On a scale of 1 - 5, how difficult/easy did you find the expression of interest form? | AW1: Please enter the reason for selecting the option above. | AX1: Do you accept the terms and conditions for participating in the 10X Digital Economy Program? | AY1: Thank you so much for you time and for filling this 10X Digital Economy Expression of Interest Form. | AZ1: Please include all your feedback of the tool here | BA1: Consent/Data Release Form | BB1: Please enter your name | BC1: What is your position / title / role in the company? | BD1: Please provide your primary mobile number (the person filling in the application). | BE1: Please provide the email address of the person filling in the application | BF1: Does ${business_name} have any parent company or subsidiaries? | BG1: Does ${business_name} have any parent company or subsidiaries?/Yes, the company has a parent company. | BH1: Does ${business_name} have any parent company or subsidiaries?/Yes, the company has a subsidiary (subsidiaries). | BI1: Does ${business_name} have any parent company or subsidiaries?/No | BJ1: Please list the parent company below. | BK1: How many subsidiaries does your company have? | BL1: When was your company legally registered with URSB? | BM1: Please upload your certificate of registration | BN1: Please upload your certificate of registration_URL | BO1: Upload a copy of your Company's Memorandum and Articles of Association. | BP1: Upload a copy of your Company's Memorandum and Articles of Association._URL | BQ1: What is your company's Tax Identification Number? | BR1: Please upload Form 20 / Form 7 of your Company Registration Form that evidences the Company Directors | BS1: Please upload Form 20 / Form 7 of your Company Registration Form that evidences the Company Directors_URL | BT1: _id | BU1: _uuid | BV1: _submission_time | BW1: _validation_status | BX1: _notes | BY1: _status | BZ1: _submitted_by | CA1: __version__ | CB1: _tags | CC1: _index | CD1: Breakdown | CE1: Test | CF1: ESO | CG1: What is the name of your business/Enterprise?_f | CH1: _submission__id | CI1: founder_number | CJ1: Please enter the first name of Founder #${founder_number}. | CK1: Please enter ${first_name_f}'s last name. | CL1: Please enter ${first_name_f}'s date of birth. | CM1: Age | CN1: Please select ${first_name_f}'s gender. | CO1: What percentage of shares does ${first_name_f} hold? | CP1: What is ${first_name_f}'s Nationality. | CQ1: Is ${first_name_f} a person with disabilities? | CR1: Please select the disability that ${first_name_f} has from the options below. | CS1: Please select the disability that ${first_name_f} has from the options below./Visual disability | CT1: Please select the disability that ${first_name_f} has from the options below./Mental disability | CU1: Please specify the disability. | CV1: What is ${first_name_f}'s citizenship? | CW1: If Refugee, which country? | CX1: What is ${first_name_f}'s district of residence? | CY1: What is ${first_name_f}'s Subcounty of residence? | CZ1: What is ${first_name_f}'s parish of residence? | DA1: What is ${first_name_f}'s village of residence? | DB1: What is ${first_name_f}'s Mobile number? | DC1: Please enter ${first_name_f}'s valid email address. | DD1: Is ${first_name_f} actively working in the business? | DE1: What is ${first_name_f}'s monthly gross salary? (In Uganda Shillings) | DF1: Please upload a copy of the National ID front page for ${first_name_f}. | DG1: Please upload a copy of the National ID front page for ${first_name_f}._URL | DH1: _index_f | DI1: _parent_table_name | DJ1: _parent_index | DK1: _submission__id.1 | DL1: _submission__uuid | DM1: _submission__submission_time | DN1: _submission__validation_status | DO1: _submission__notes | DP1: _submission__status | DQ1: _submission__submitted_by | DR1: _submission___version__ | DS1: _submission__tags | DT1: ESO_ft | DU1: What is the name of your business/Enterprise?_ft | DV1: _submission__id_ft | DW1: fte_number | DX1: Please enter the first name of Full Time Employee #${fte_number}. | DY1: Is ${first_name_fte} a founder? | DZ1: Please enter ${first_name_fte}'s last name. | EA1: Please enter ${first_name_fte}'s Date of Birth. | EB1: Please select ${first_name_fte}'s Gender. | EC1: What is the role of ${first_name_fte} in the Business/Enterprise? | ED1: What is the monthly gross salary or stipend (In Uganda Shillings) for ${first_name_fte}. | EE1: Is ${first_name_fte} a person with disabilities? | EF1: Please specify the disability._ft | EG1: What is ${first_name_fte}'s citizenship? | EH1: If refugee, name the country | EI1: What is ${first_name_fte}'s home district? | EJ1: What is ${first_name_fte}'s subcounty? | EK1: What is ${first_name_fte}'s Parish? | EL1: What is ${first_name_fte}'s Village? | EM1: What is ${first_name_fte}'s primary phone number? | EN1: What is ${first_name_fte}'s primary email address? | EO1: What is ${first_name_fte}'s highest level of education? | EP1: What is ${first_name_fte}'s National Identification Number (NIN) as shown on the National ID? | EQ1: What is ${first_name_fte}'s subcounty?.1 | ER1: What is ${first_name_fte}'s Parish?.1 | ES1: _index_ft | ET1: _parent_table_name_ft | EU1: _parent_index_ft | EV1: _submission__id.1_ft | EW1: _submission__uuid_ft | EX1: _submission__submission_time_ft | EY1: _submission__validation_status_ft | EZ1: _submission__notes_ft | FA1: _submission__status_ft | FB1: _submission__submitted_by_ft | FC1: _submission___version___ft | FD1: _submission__tags_ft | FE1: ESO_pt | FF1: What is the name of your business/Enterprise?_pt | FG1: _submission__id_pt | FH1: pte_number | FI1: Please enter the first name of Part Time Employee #${pte_number}. | FJ1: Please enter ${first_name_pte}'s last name. | FK1: Please enter ${first_name_pte}'s Date of Birth. | FL1: Please select ${first_name_pte}'s Gender. | FM1: What is the role of ${first_name_pte} in the company? | FN1: What is the monthly gross salary or stipend (In Uganda Shillings) for ${first_name_pte}. | FO1: Is ${first_name_pte} a person with disabilities? | FP1: Please specify the disability._pt | FQ1: What is ${first_name_pte}'s citizenship? | FR1: If Refugee, which country?_pt | FS1: What is ${first_name_pte}'s home district? | FT1: What is ${first_name_pte}'s subcounty? | FU1: What is ${first_name_pte}'s Parish? | FV1: What is ${first_name_pte}'s Village? | FW1: What is ${first_name_pte}'s primary phone number? | FX1: What is ${first_name_pte}'s primary email address? | FY1: What is ${first_name_pte}'s National Identification Number (NIN) as shown on the National ID? | FZ1: _index_pt | GA1: _parent_table_name_pt | GB1: _parent_index_pt | GC1: _submission__id.1_pt | GD1: _submission__uuid_pt | GE1: _submission__submission_time_pt | GF1: _submission__validation_status_pt | GG1: _submission__notes_pt | GH1: _submission__status_pt | GI1: _submission__submitted_by_pt | GJ1: _submission___version___pt | GK1: category | GL1: Age | GM1: Age
A2: 0.021476852 | B2: 45965 | C2: Stanbic Bank Incubator | D2: Prime Classy Perfumes and Beauty Inn | E2: Authentic perfumes, scent oil, automatic air freshener, watches and smart watches, tab speakershand bags, tabs and kids tabs, Victoria secret and bath and body products branded Lotions and creamsand pedicure | F2: No | H2: Yes | I2: 1010807824 | L2: No | N2: Central | O2: Mubende | P2: West division | Q2: Katogo ward | R2: fashion and design | T2: 1 | U2: 1 | V2: 1 | W2: 0 | X2: Authentic perfumes, branded products like Victoria secret and bath and body works, branded Lotions and creams, all types of air freshener, scent oils, branded bags like hand books, kids bags, rechargeable bags, table speaker, smart watches and non smart watches, tabs and kids tabs, shoes , pedicure etc | Y2: It's helps me to development | Z2: 3 | AA2: 20 | AB2: 597810443 | AC2: Charges depends on the product sold but ranges from 5000- 1000000 because the highest expensive product is at that00 | AD2: 4500000 | AE2: No | AG2: No | AI2: 10000000 | AJ2: Enlarging my business | AK2: My business is in the middle of town so the targeted customers are available and prices are friendly and it has a full time attendant | AL2: No | AN2: No | AP2: No | AR2: No | AT2: Learning champion convinced me | AU2: Through learning champion | AV2: 4 - Easy | AW2: Because I was able to interpret the questions asked and replied them | AX2: Yes | AZ2: For sure am loving more more 10x DIGITAL EXPRESSION the tool was easy to fill and the questions were easy to understand. Thanks | BT2: 597810443 | BU2: e95a4725-3b3b-4838-8c7c-7cc00f8e23f4 | BV2: 45965.404 | BY2: submitted_via_web | CA2: vCJgLk2yV8oivMfbcbCpCF | CC2: 431 | CF2: Stanbic Bank Incubator | CG2: Prime Classy Perfumes and Beauty Inn | CH2: 597810443 | CI2: 1 | CJ2: Angella | CK2: Nakatimbo | CL2: 34104 | CN2: Female | CO2: 100 | CP2: Ugandan | CQ2: No | CV2: Ugandan | CX2: Mubende | CY2: West dividion | CZ2: Katogo ward | DA2: Main Street LCI | DB2: 703966762 | DC2: angellanakatimbo1@mail.com | DD2: Yes | DE2: 100000 | DF2: IMG_20251104_113944_522-11_42_13.jpg | DG2: https://kf.kobotoolbox.org/api/v2/assets/a9dTHTe72X7zPceKxVtSxV/data/597810443/attachments/attYsfoQQUzrXmtQ95W4sU9t/ | DH2: 545 | DI2: 10X Digital Economy Expression of interest Form | DJ2: 431 | DK2: 597810443 | DL2: e95a4725-3b3b-4838-8c7c-7cc00f8e23f4 | DM2: 45965.404 | DP2: submitted_via_web | DR2: vCJgLk2yV8oivMfbcbCpCF | DT2: Stanbic Bank Incubator | DU2: Prime Classy Perfumes and Beauty Inn | DV2: 597810443 | DW2: 1 | DX2: Rose | DY2: No | DZ2: Nakiwala | EA2: 38349 | EB2: Female | EC2: Attendant | ED2: 100000 | EE2: No | EG2: Ugandan | EI2: Mubende | EJ2: Kiyuni | EK2: Katente | EL2: Katente | EM2: 747420860 | EO2: S.6 | EP2: CFO403110K3JPE | ES2: 986 | ET2: 10X Digital Economy Expression of interest Form | EU2: 431 | EV2: 597810443 | EW2: e95a4725-3b3b-4838-8c7c-7cc00f8e23f4 | EX2: 45965.404 | FA2: submitted_via_web | FC2: vCJgLk2yV8oivMfbcbCpCF | GK2: Unique | GL2: 0 | GM2: 32
A3: 0.041204861 | B3: 45973 | C3: Stanbic Bank Incubator | D3: Poul | E3: My business provides eggs to the community and durks for those interested in.furk keeping | F3: No | H3: No | L3: No | N3: Central | O3: Wakiso | P3: Wakiso subcouty | Q3: Bukasa parish | R3: Agriculture | T3: 2 | U3: 2 | V3: 1 | W3: 1 | X3: My poutry business is a small scale of 15 durks and 10 layers chicken I employee my self on my small business as I plan to grow bigger than this | Y3: My business is trying to solve a problem of space and healthy of my birds | Z3: 2 | AA3: 2 | AB3: 603755911 | AC3: I make money buy selling off the young ones of durks and selling of eggs from the chicken | AD3: 0 | AE3: No | AG3: Yes | AH3: Stanbic incubatormadam penthroughh various ways like record keeping asand financial literacy nit was offering training on how to look after small scale business asand how to grow in businessinah was running it | AI3: 1000000 | AJ3: I want to see myself having a big farm of over 100 birds and hoodrecords | AK3: Because of the knowledge I have got from the 10 x program training | AL3: Yes | AM3: Expansion interms of space | AN3: Yes | AO3: She is one of my menter from our disability flatanity | AP3: Yes | AQ3: She is apwa as my self | AR3: No | AT3: The traings they offerare quite important | AU3: Through my fellow person with disability | AV3: 3 - Neutral | AW3: Reason being am short sighted and some of the fillings like my nini has not been easy and feeling my birthday date | AX3: Yes | AZ3: Am so greatfull for this program thank you Stanbic icubatoe | BT3: 603755911 | BU3: ba22e98b-bc2c-4fcc-9044-15e33a1658bb | BV3: 45973.279 | BY3: submitted_via_web | CA3: vCJgLk2yV8oivMfbcbCpCF | CC3: 516 | CF3: Stanbic Bank Incubator | CG3: Poul | CH3: 603755911 | CI3: 1 | CJ3: Kasagga | CK3: Faith | CL3: 29020 | CN3: Female | CO3: 80 | CP3: Uganda | CQ3: Yes | CR3: Others | CS3: 0 | CT3: 0 | CU3: Albinism | CV3: Ugandan | CX3: Wakiso | CY3: Wakiso subcounty | CZ3: Bukasa | DA3: Muyomba | DB3: 704744329 | DC3: bwanikafath2016@gmail.com | DD3: Yes | DE3: 50000 | DF3: IMG_20251112_090304_484-9_5_58.jpg | DG3: https://kf.kobotoolbox.org/api/v2/assets/a9dTHTe72X7zPceKxVtSxV/data/603755911/attachments/attGzr3pGm4JzMKTTuqa2Rz3/ | DH3: 638 | DI3: 10X Digital Economy Expression of interest Form | DJ3: 516 | DK3: 603755911 | DL3: ba22e98b-bc2c-4fcc-9044-15e33a1658bb | DM3: 45973.279 | DP3: submitted_via_web | DR3: vCJgLk2yV8oivMfbcbCpCF | DT3: Stanbic Bank Incubator | DU3: Poul | DV3: 603755911 | DW3: 1 | DX3: Kasagga | DY3: Yes | EL3: Muyomba | ES3: 1130 | ET3: 10X Digital Economy Expression of interest Form | EU3: 516 | EV3: 603755911 | EW3: ba22e98b-bc2c-4fcc-9044-15e33a1658bb | EX3: 45973.279 | FA3: submitted_via_web | FC3: vCJgLk2yV8oivMfbcbCpCF | FE3: Stanbic Bank Incubator | FF3: Poul | FG3: 603755911 | FH3: 1 | FI3: Kasagga | FJ3: Faith | FK3: 29171 | FL3: Female | FM3: To take care of the nirds | FN3: 50000 | FO3: Yes | FP3: Albinism | FQ3: Ugandan | FS3: Wakiso | FT3: Wakiso subcouty | FU3: Bukasa | FV3: Muyomba | FW3: 704744329 | FX3: bwanikafaith2016@gmail.com | FY3: Cf790521081cll | FZ3: 376 | GA3: 10X Digital Economy Expression of interest Form | GB3: 516 | GC3: 603755911 | GD3: ba22e98b-bc2c-4fcc-9044-15e33a1658bb | GE3: 45973.279 | GH3: submitted_via_web | GJ3: vCJgLk2yV8oivMfbcbCpCF | GK3: Unique | GL3: 46 | GM3: 46
A4: 0.021215278 | B4: 45973 | C4: Stanbic Bank Incubator | D4: Tamutamu weaving and bag collection | E4: My business provides weaved cupmats , millet basket , and I also sell bags for ladies | F4: No | H4: No | L4: No | N4: Central | O4: Kampala | P4: Makerere | Q4: Makerere | R4: fashion and design | T4: 1 | U4: 1 | V4: 1 | W4: 1 | X4: As aiming to equip and develope yourth with disabilities create opportunities using our local cheap materials to change ,we sell cupmats , table mats, baskets by weaving using our local materials of payrus,we buy ladies bag from wholesale and sell them on retail | Y4: Capital to employe many yourth to development their talents , place where to put my business in stable place , accomodation | Z4: 3 | AA4: 8 | AB4: 603928923 | AC4: Small retail business | AD4: 2000000 | AE4: No | AG4: No | AI4: 2500000 | AJ4: Employee more people with impairments, expand the business to local areas to train more young growing yourth who are unemployed | AK4: Because it targets the yourth who are interested in fashion and also old families that want their houses designed with millet baskets, cup marts, | AL4: Yes | AM4: My business specifically employees the young disabled talented youth to be job creators rather than job seekers, looking forward to export our products even abroad | AN4: No | AP4: No | AR4: Yes | AS4: I myself am the guild representative and minister for pwds at Makerere university | AT4: Need to learn more skills in world of business and financial support | AU4: Got a link from a friend and filled it , he told me that it has been empowering pwds to start up Businesses | AV4: 4 - Easy | AW4: It asks what you really want to be , seeks your general knowledge in the business which is my passion | AX4: Yes | AZ4: It's Abit hectic to fill as for a person with visual impairments , also some places doesn't give option of self expression | BT4: 603928923 | BU4: 88bcafa1-8ca4-41c2-b144-aa9c4eb00e4b | BV4: 45973.415 | BY4: submitted_via_web | CA4: vCJgLk2yV8oivMfbcbCpCF | CC4: 525 | CF4: Stanbic Bank Incubator | CG4: Tamutamu weaving and bag collection | CH4: 603928923 | CI4: 1 | CJ4: Akankunda | CK4: Donitah | CL4: 37249 | CN4: Female | CO4: 100 | CP4: Ugandan | CQ4: Yes | CR4: Visual disability | CS4: 1 | CT4: 0 | CV4: Ugandan | CX4: Kampala | CY4: Makerere | CZ4: Makerere | DA4: Makerere | DB4: 791064779 | DC4: donitahakankunda48@gmail.com | DD4: Yes | DE4: 100000 | DH4: 648 | DI4: 10X Digital Economy Expression of interest Form | DJ4: 525 | DK4: 603928923 | DL4: 88bcafa1-8ca4-41c2-b144-aa9c4eb00e4b | DM4: 45973.415 | DP4: submitted_via_web | DR4: vCJgLk2yV8oivMfbcbCpCF | DT4: Stanbic Bank Incubator | DU4: Tamutamu weaving and bag collection | DV4: 603928923 | DW4: 1 | DX4: Akankunda | DY4: Yes | EL4: Kitoma | ES4: 1142 | ET4: 10X Digital Economy Expression of interest Form | EU4: 525 | EV4: 603928923 | EW4: 88bcafa1-8ca4-41c2-b144-aa9c4eb00e4b | EX4: 45973.415 | FA4: submitted_via_web | FC4: vCJgLk2yV8oivMfbcbCpCF | FE4: Stanbic Bank Incubator | FF4: Tamutamu weaving and bag collection | FG4: 603928923 | FH4: 1 | FI4: Joy | FJ4: Ndayishimye | FK4: 37605 | FL4: Female | FM4: Selling products | FN4: 100000 | FO4: No | FQ4: Ugandan | FS4: Kisoro | FT4: Nyarusiza | FU4: Gitenderi | FV4: Kabande | FW4: 779188559 | FX4: jndayishimye2@gmail.com | FY4: CF0201810EFFGE | FZ4: 377 | GA4: 10X Digital Economy Expression of interest Form | GB4: 525 | GC4: 603928923 | GD4: 88bcafa1-8ca4-41c2-b144-aa9c4eb00e4b | GE4: 45973.415 | GH4: submitted_via_web | GJ4: vCJgLk2yV8oivMfbcbCpCF | GK4: Unique | GL4: 28 | GM4: 24
A5: 0.012311343 | B5: 45973 | C5: Stanbic Bank Incubator | D5: Gabriel fast foods 7 | E5: Provides pasties and fast foods to the community | F5: No | H5: No | L5: No | N5: Central | O5: Wakiso | P5: Nsangi | Q5: Kasenge ward | R5: Others | S5: Bakery | T5: 1 | U5: 1 | V5: 1 | W5: 0 | X5: Daddies, Cookies, Doughnuts, Bread and bans,scones, samosas, chapati and many pastries in all types | Y5: Working from home and limited capital | Z5: 1 | AA5: 2 | AB5: 603971564 | AC5: I make money through supplying cakes to friends on parties, satisfying customers orders like bread. I make different types of pastries to attract more customers at an affordable price to also finish up my daily production and have profit at the end without making loses that I cannot weigh in my micro business | AD5: 0 | AE5: No | AG5: Yes | AH5: Stanbic incubator, teaching about business skills to grow micro businesses to another level of growth which taught me more of business success | AI5: 30000000 | AJ5: Financial support | AK5: Because I will employ many youth and reduce on unemployment problems in my community and also pay revenue to support government services for my country's development | AL5: Yes | AM5: I want to start working on a medium scale and know how to register my business | AN5: Yes | AO5: Business expert lecturer | AP5: Yes | AQ5: Teacher | AR5: No | AT5: I listened to business growth Ideas and also wanted to grow mine | AU5: From Amodo Doreen | AV5: 5 - Very easy | AW5: Because all the questions were clear and understandable, related to my business journey for growth | AX5: Yes | AZ5: Am so grateful for having been granted such an opportunity | BT5: 603971564 | BU5: 64c0ea74-94cc-492c-b5e8-6af324b897d5 | BV5: 45973.444 | BY5: submitted_via_web | CA5: vCJgLk2yV8oivMfbcbCpCF | CC5: 528 | CF5: Stanbic Bank Incubator | CG5: Gabriel fast foods 7 | CH5: 603971564 | CI5: 1 | CJ5: Nakkazi | CK5: Gloria | CL5: 37876 | CN5: Female | CO5: 70 | CP5: Uganda | CQ5: No | CV5: Ugandan | CX5: Wakiso | CY5: Nsangi | CZ5: Kasenge | DA5: Mugongo A | DB5: 771936183 | DC5: gloriavocal9@gmail.com | DD5: No | DH5: 651 | DI5: 10X Digital Economy Expression of interest Form | DJ5: 528 | DK5: 603971564 | DL5: 64c0ea74-94cc-492c-b5e8-6af324b897d5 | DM5: 45973.444 | DP5: submitted_via_web | DR5: vCJgLk2yV8oivMfbcbCpCF | DT5: Stanbic Bank Incubator | DU5: Gabriel fast foods 7 | DV5: 603971564 | DW5: 1 | DX5: Nakkazi Gloria | DY5: Yes | EL5: Mugongo A | ES5: 1145 | ET5: 10X Digital Economy Expression of interest Form | EU5: 528 | EV5: 603971564 | EW5: 64c0ea74-94cc-492c-b5e8-6af324b897d5 | EX5: 45973.444 | FA5: submitted_via_web | FC5: vCJgLk2yV8oivMfbcbCpCF | GK5: Unique | GL5: 31 | GM5: 22
A6: 0.018792824 | B6: 45973 | C6: Stanbic Bank Incubator | D6: Hannah's bakery and sweet snacks | E6: Cakes | F6: No | H6: No | L6: No | N6: Central | O6: Wakiso | P6: Nakabugo | Q6: Nakuwadde | R6: trade and services | T6: 2 | U6: 2 | V6: 1 | W6: 1 | X6: Cakes,chapatis,piza,cookies | Y6: Reducing on the loss | Z6: 5 | AA6: 5 | AB6: 604130561 | AC6: I make cakes from 70k | AD6: 10000 | AE6: No | AG6: Yes | AH6: Managing my business finances and savings for growth | AI6: 10000000 | AJ6: To grow my business bigger | AK6: Because business incubator has taught us more about digital marketing credit | AL6: No | AN6: No | AP6: Yes | AQ6: Liven | AR6: No | AT6: Growing my business and savings for growth and marketing my business online | AU6: Through business incubator | AV6: 3 - Neutral | AW6: It needed mindset | AX6: Yes | AZ6: Thanks for growing my business | BT6: 604130561 | BU6: d2a7a0b5-2591-482d-b0c0-5b3c39489c7d | BV6: 45973.562 | BY6: submitted_via_web | CA6: vCJgLk2yV8oivMfbcbCpCF | CC6: 534 | CF6: Stanbic Bank Incubator | CG6: Hannah's bakery and sweet snacks | CH6: 604130561 | CI6: 2 | CJ6: Nabunnya | CK6: Annnet | CL6: 36615 | CN6: Female | CO6: 50 | CP6: Ugandan | CQ6: No | CV6: Ugandan | CX6: Wakiso | CY6: Nakabugo | CZ6: Nakuwadde | DA6: Nakuwadde | DB6: 741769493 | DC6: annetnabunnya649@gmail.com | DD6: No | DF6: 20251112_160557-16_10_24.heic | DG6: https://kf.kobotoolbox.org/api/v2/assets/a9dTHTe72X7zPceKxVtSxV/data/604130561/attachments/attsxRGdb5ETLgM2kDvHXpFg/ | DH6: 660 | DI6: 10X Digital Economy Expression of interest Form | DJ6: 534 | DK6: 604130561 | DL6: d2a7a0b5-2591-482d-b0c0-5b3c39489c7d | DM6: 45973.562 | DP6: submitted_via_web | DR6: vCJgLk2yV8oivMfbcbCpCF | DT6: Stanbic Bank Incubator | DU6: Hannah's bakery and sweet snacks | DV6: 604130561 | DW6: 1 | DX6: Nabunnya Annet | DY6: Yes | EL6: Nakuwadde | ES6: 1161 | ET6: 10X Digital Economy Expression of interest Form | EU6: 534 | EV6: 604130561 | EW6: d2a7a0b5-2591-482d-b0c0-5b3c39489c7d | EX6: 45973.562 | FA6: submitted_via_web | FC6: vCJgLk2yV8oivMfbcbCpCF | FE6: Stanbic Bank Incubator | FF6: Hannah's bakery and sweet snacks | FG6: 604130561 | FH6: 1 | FI6: Nabunnya | FJ6: Annet | FK6: 36615 | FL6: Female | FM6: Baking cakes | FN6: 200000 | FO6: No | FQ6: Ugandan | FS6: Wakiso | FT6: Nakabugo | FU6: Nakuwadde | FV6: Nakuwadde | FW6: 741769493 | FX6: annetnabunnya649@gmail.com | FY6: CF00012107LL7L | FZ6: 379 | GA6: 10X Digital Economy Expression of interest Form | GB6: 534 | GC6: 604130561 | GD6: d2a7a0b5-2591-482d-b0c0-5b3c39489c7d | GE6: 45973.562 | GH6: submitted_via_web | GJ6: vCJgLk2yV8oivMfbcbCpCF | GK6: Unique | GL6: 23 | GM6: 23
A7: 0.029237269 | B7: 45973 | C7: Stanbic Bank Incubator | D7: Gabriella's beauty saloon | E7: Hairstyling and cosmetics | F7: No | H7: No | L7: No | N7: Central | O7: Wakiso | P7: Nsangi | Q7: Kyengera | R7: fashion and design | T7: 1 | U7: 1 | V7: 1 | W7: 0 | X7: Hairstyling, makeup, wig installation,nail technician | Y7: Low Market | Z7: 1 | AA7: 0 | AB7: 604297815 | AC7: Hairstyling and cosmetics | AD7: 0 | AE7: No | AG7: No | AI7: 4000000 | AJ7: Increase my income and profit. Get more customers and make my business known. Make another branch to earn more | AK7: It is in a good location | AL7: No | AN7: No | AP7: Yes | AQ7: Friend | AR7: No | AT7: To get more business knowledge | AU7: Via Dreams program | AV7: 3 - Neutral | AW7: Too many questions | AX7: Yes | AZ7: Thanks for everything | BT7: 604297815 | BU7: 81e373d2-14b3-4c09-ace4-1d30b8979dc5 | BV7: 45973.697 | BY7: submitted_via_web | CA7: vCJgLk2yV8oivMfbcbCpCF | CC7: 547 | CF7: Stanbic Bank Incubator | CG7: Gabriella's beauty saloon | CH7: 604297815 | CI7: 1 | CJ7: AINEMBABAZI | CK7: SANDRA | CL7: 38658 | CN7: Female | CO7: 100 | CP7: Ugandan | CQ7: No | CV7: Ugandan | CX7: Wakiso | CY7: Nsangi | CZ7: Kyengera | DA7: Masanda | DB7: 769812414 | DC7: camraiseelainesandie@gmail.com | DD7: No | DF7: IMG-20251011-WA0246-18_51_13.jpg | DG7: https://kf.kobotoolbox.org/api/v2/assets/a9dTHTe72X7zPceKxVtSxV/data/604297815/attachments/atthpFwjWVikDEqUBynrbmMv/ | DH7: 673 | DI7: 10X Digital Economy Expression of interest Form | DJ7: 547 | DK7: 604297815 | DL7: 81e373d2-14b3-4c09-ace4-1d30b8979dc5 | DM7: 45973.697 | DP7: submitted_via_web | DR7: vCJgLk2yV8oivMfbcbCpCF | DT7: Stanbic Bank Incubator | DU7: Gabriella's beauty saloon | DV7: 604297815 | DW7: 1 | DX7: Ainembabazi Sandra | DY7: Yes | EL7: Masanda | ES7: 1174 | ET7: 10X Digital Economy Expression of interest Form | EU7: 547 | EV7: 604297815 | EW7: 81e373d2-14b3-4c09-ace4-1d30b8979dc5 | EX7: 45973.697 | FA7: submitted_via_web | FC7: vCJgLk2yV8oivMfbcbCpCF | GK7: Unique | GL7: 21 | GM7: 21
A8: 0.03537963 | B8: 45973 | C8: Stanbic Bank Incubator | D8: Harrietcrafts | E8: Harrietcrafts is a social interprise dealing in making crafts like functional baskets mats verses hut netivities and many others | F8: No | H8: No | L8: No | N8: Central | O8: Wakiso | P8: Busiro | Q8: Wakiso | R8: fashion and design | T8: 1 | U8: 1 | V8: 1 | W8: 0 | X8: It provides mats verses hut netivities and baskets for home use | Y8: It solves diseases from poor sanitation | Z8: 3 | AA8: 5 | AB8: 604370172 | AC8: These are the resources needed to run this social interprise rent for at list 2months 200000total400000 phone for internet and communication at700000 sowing needles at 50000 sisol at100000 bananastem at 100000 bananafibires at 50000 vernish woodglue at1000005litres transport 100000total 1600000 | AD8: 400000 | AE8: No | AG8: Yes | AH8: The stanbic incubator program was runned by mr waguma it was offering capacity building irecieved how to develop financially and to solve unemployment | AI8: 2000000 | AJ8: I expect to employ more workers to make more quality products to expand the business to grow and to increase on the costs of the products | AK8: Due to good quality products made and use of internt for marketing | AL8: No | AN8: No | AP8: No | AR8: No | AT8: I wanted to develop financially to solve unemployment | AU8: Thrugh madam peninah | AV8: 3 - Neutral | AW8: Some questions have been simple and others difficult | AX8: Yes | AZ8: Thank you for your support and for introducing capacity building | BT8: 604370172 | BU8: cc141231-43f2-4fff-b593-2d30d8788b70 | BV8: 45973.769 | BY8: submitted_via_web | CA8: vCJgLk2yV8oivMfbcbCpCF | CC8: 550 | CF8: Stanbic Bank Incubator | CG8: Harrietcrafts | CH8: 604370172 | CI8: 1 | CJ8: Nakijjoba | CK8: Harriet | CL8: 35069 | CN8: Female | CO8: 50 | CP8: Ugandan | CQ8: Yes | CR8: Physical Disability | CS8: 0 | CT8: 0 | CV8: Ugandan | CX8: Wakiso | CY8: Busiro | CZ8: Wakiso | DA8: Gombe A | DB8: 756653782 | DC8: nakijjobaharriet09@gmail.com | DD8: Yes | DE8: 100000 | DF8: IMG-20251112-WA0176-20_8_57.jpg | DG8: https://kf.kobotoolbox.org/api/v2/assets/a9dTHTe72X7zPceKxVtSxV/data/604370172/attachments/attR7YUZkRieSBhS3758ucGu/ | DH8: 676 | DI8: 10X Digital Economy Expression of interest Form | DJ8: 550 | DK8: 604370172 | DL8: cc141231-43f2-4fff-b593-2d30d8788b70 | DM8: 45973.769 | DP8: submitted_via_web | DR8: vCJgLk2yV8oivMfbcbCpCF | DT8: Stanbic Bank Incubator | DU8: Harrietcrafts | DV8: 604370172 | DW8: 1 | DX8: Nakijjoba | DY8: Yes | EL8: Gombe A | ES8: 1177 | ET8: 10X Digital Economy Expression of interest Form | EU8: 550 | EV8: 604370172 | EW8: cc141231-43f2-4fff-b593-2d30d8788b70 | EX8: 45973.769 | FA8: submitted_via_web | FC8: vCJgLk2yV8oivMfbcbCpCF | GK8: Unique | GL8: 29 | GM8: 29
A9: 0.0079074074 | B9: 45974 | C9: Stanbic Bank Incubator | D9: Salon | E9: We plaint hair | F9: No | H9: No | L9: No | N9: Central | O9: Wakiso | P9: Nsangi | Q9: Kikajjo | R9: fashion and design | T9: 1 | U9: 1 | V9: 1 | W9: 1 | X9: Crafts | Y9: Decorations | Z9: 11 | AA9: 25 | AB9: 604569648 | AC9: I use my own hands then after I sell them to get money | AD9: 60000 | AE9: No | AG9: No | AI9: 1000000 | AJ9: I want to be a business lady I want also to register my business so that its in are good path | AK9: Couse am confident | AL9: No | AN9: No | AP9: No | AR9: No | AT9: I need your help so that my business glow and wide | AU9: By announcement in our village | AV9: 5 - Very easy | AW9: Couse they was reasonble | AX9: Yes | BT9: 604569648 | BU9: 17e4008f-d739-4171-a069-fb9922c9af76 | BV9: 45974.199 | BY9: submitted_via_web | CA9: vCJgLk2yV8oivMfbcbCpCF | CC9: 556 | CF9: Stanbic Bank Incubator | CG9: Salon | CH9: 604569648 | CI9: 1 | CJ9: Gladys | CK9: Nalukenge | CL9: 38835 | CN9: Female | CO9: 100 | CP9: Ugandan | CQ9: No | CV9: Ugandan | CX9: Kampala | CY9: Nsangi | CZ9: Kikajjo | DA9: Katale | DB9: 747715389 | DC9: nalukengegladys42@gmail.cok | DD9: Yes | DE9: 500000 | DH9: 682 | DI9: 10X Digital Economy Expression of interest Form | DJ9: 556 | DK9: 604569648 | DL9: 17e4008f-d739-4171-a069-fb9922c9af76 | DM9: 45974.199 | DP9: submitted_via_web | DR9: vCJgLk2yV8oivMfbcbCpCF | DT9: Stanbic Bank Incubator | DU9: Salon | DV9: 604569648 | DW9: 1 | DX9: Nalukenge | DY9: No | DZ9: Gladys | EA9: 38835 | EB9: Female | EC9: Business owner | ED9: 500000 | EE9: No | EG9: Ugandan | EI9: Wakiso | EJ9: Nsangi | EK9: Kikajjo | EL9: Katale | EM9: 747715389 | EN9: nalukengegladys42@gmail.cok | EO9: S3 | EP9: CF06091107VCSL | ES9: 1183 | ET9: 10X Digital Economy Expression of interest Form | EU9: 556 | EV9: 604569648 | EW9: 17e4008f-d739-4171-a069-fb9922c9af76 | EX9: 45974.199 | FA9: submitted_via_web | FC9: vCJgLk2yV8oivMfbcbCpCF | FE9: Stanbic Bank Incubator | FF9: Salon | FG9: 604569648 | FH9: 1 | FI9: Gladys | FJ9: Nalukenge | FK9: 38835 | FL9: Female | FM9: Business owner | FN9: 200000 | FO9: No | FQ9: Ugandan | FS9: Wakiso | FT9: Nsangi | FU9: Kikajjo | FV9: Katale | FW9: 747715389 | FX9: nalukengegladys42l@gmail.cok | FY9: CF06091107VCSL | FZ9: 398 | GA9: 10X Digital Economy Expression of interest Form | GB9: 556 | GC9: 604569648 | GD9: 17e4008f-d739-4171-a069-fb9922c9af76 | GE9: 45974.199 | GH9: submitted_via_web | GJ9: vCJgLk2yV8oivMfbcbCpCF | GK9: Unique | GL9: 0 | GM9: 19
A10: 0.003775463 | B10: 45974 | C10: Stanbic Bank Incubator | D10: Simmy's nyam nyam snacks | E10: Cakes and cookies | F10: No | H10: No | L10: No | N10: Central | O10: Wakiso | P10: Nsangi | Q10: Nsangi | R10: trade and services | T10: 1 | U10: 1 | V10: 1 | W10: 0 | X10: Cakes: I sell the ones of 500 and the birthday cakes and cookies are for 500 | Y10: My business is solving the problem of reducing on the journey of people traveling to look for cakes in another environment | Z10: 1 | AA10: 0 | AB10: 604570098 | AC10: I sell the cakes to the shops and available customers and 1 dozen is for 5000 because each cake is for 500 | AD10: 0 | AE10: No | AG10: No | AI10: 5000000 | AJ10: To access digital tools in order to access more customers online | AK10: Because I give quality and sweet products and ensure customer's wants | AL10: No | AN10: No | AP10: No | AR10: No | AT10: I was much interested to learn more about running my business and using digital tools to run it | AU10: Program champion | AV10: 4 - Easy | AW10: Because I managed to answer all questions according to wat I do in real life | AX10: Yes | AZ10: They will help me to grow my business | BT10: 604570098 | BU10: 12cf702c-1c1f-4f42-9d3f-39d26abbff23 | BV10: 45974.2 | BY10: submitted_via_web | CA10: vCJgLk2yV8oivMfbcbCpCF | CC10: 557 | CF10: Stanbic Bank Incubator | CG10: Simmy's nyam nyam snacks | CH10: 604570098 | CI10: 1 | CJ10: Nakalawa | CK10: Patience | CL10: 38789 | CN10: Female | CO10: 100 | CP10: Ugandan | CQ10: No | CV10: Ugandan | CX10: Wakiso | CY10: Nsangi | CZ10: Nsangi | DA10: Nakasozi | DB10: 757227098 | DC10: patiencemujjuzi@gmail.com | DD10: Yes | DE10: 100000 | DH10: 683 | DI10: 10X Digital Economy Expression of interest Form | DJ10: 557 | DK10: 604570098 | DL10: 12cf702c-1c1f-4f42-9d3f-39d26abbff23 | DM10: 45974.2 | DP10: submitted_via_web | DR10: vCJgLk2yV8oivMfbcbCpCF | DT10: Stanbic Bank Incubator | DU10: Simmy's nyam nyam snacks | DV10: 604570098 | DW10: 1 | DX10: Nakalawa | DY10: Yes | EL10: Nakasozi | ES10: 1184 | ET10: 10X Digital Economy Expression of interest Form | EU10: 557 | EV10: 604570098 | EW10: 12cf702c-1c1f-4f42-9d3f-39d26abbff23 | EX10: 45974.2 | FA10: submitted_via_web | FC10: vCJgLk2yV8oivMfbcbCpCF | GK10: Unique | GL10: 19 | GM10: 19
A11: 0.013831019 | B11: 45974 | C11: Stanbic Bank Incubator | D11: Not yet | E11: Hairdressing | F11: No | H11: No | L11: No | N11: West | O11: Wakiso | P11: Kyengera | Q11: Kasenge | R11: Others | S11: Hairdressing | T11: 1 | U11: 1 | V11: 3 | W11: 0 | X11: Not yet | Y11: Keeping girl child away from poverty | Z11: 1 | AA11: 0 | AB11: 604833865 | AC11: Not yet | AD11: 50 | AE11: No | AG11: No | AI11: 2000000 | AJ11: Yes | AK11: I respect anyone | AL11: No | AN11: No | AP11: No | AR11: No | AT11: Nothing | AU11: It helps to uplift business | AV11: 4 - Easy | AW11: It's rare | AX11: Yes | AZ11: Ok | BT11: 604833865 | BU11: 09bbaaf3-e594-4323-9ee5-422dea85770f | BV11: 45974.448 | BY11: submitted_via_web | CA11: vCJgLk2yV8oivMfbcbCpCF | CC11: 575 | CF11: Stanbic Bank Incubator | CG11: Not yet | CH11: 604833865 | CI11: 1 | CJ11: Nansereko | CK11: Shamusa | CL11: 38947 | CN11: Female | CO11: 0 | CP11: Ugandan | CQ11: No | CV11: Ugandan | CX11: Wakiso | CY11: Nsangi | CZ11: Kasenge | DA11: Kikajjo | DB11: 746278715 | DC11: shamusanansereko@gmail.com | DD11: No | DH11: 703 | DI11: 10X Digital Economy Expression of interest Form | DJ11: 575 | DK11: 604833865 | DL11: 09bbaaf3-e594-4323-9ee5-422dea85770f | DM11: 45974.448 | DP11: submitted_via_web | DR11: vCJgLk2yV8oivMfbcbCpCF | DT11: Stanbic Bank Incubator | DU11: Not yet | DV11: 604833865 | DW11: 1 | DX11: Nansereko Shamusa | DY11: Yes | EL11: Kikajjo | ES11: 1204 | ET11: 10X Digital Economy Expression of interest Form | EU11: 575 | EV11: 604833865 | EW11: 09bbaaf3-e594-4323-9ee5-422dea85770f | EX11: 45974.448 | FA11: submitted_via_web | FC11: vCJgLk2yV8oivMfbcbCpCF | GK11: Unique | GL11: 19 | GM11: 19
A12: 0.014703704 | B12: 45974 | C12: Stanbic Bank Incubator | D12: Aggie's Best Cakes, Juice and Takeaway | E12: Cakes, daddies,Cookies, Doughnuts, Bread and bans and other bakery products | F12: No | H12: No | L12: No | N12: Central | O12: Wakiso | P12: Nsangi | Q12: Kasenge ward | R12: Others | S12: Bakery | T12: 1 | U12: 1 | V12: 1 | W12: 0 | X12: We provide Soft drinks, Juice in all types,cakes doughnuts, cookies, daddies, bread and bans, samosas and other bakery products | Y12: Limited customers because I work from home so I want to expand my business | Z12: 1 | AA12: 1 | AB12: 605258607 | AC12: It works supplying snacks for tea in the morning mostly. I fry and bake my foods and snacks, I walk looking for customers with my foods in buckets | AD12: 0 | AE12: No | AG12: No | AI12: 10000000 | AJ12: Financial skills and support | AK12: I have learnt more about business in the 10x program foundation course | AL12: Yes | AM12: My business can also give other young people employment under me | AN12: Yes | AO12: Teachers | AP12: Yes | AQ12: Teacher for business growth skills | AR12: No | AT12: I wanted to learn how to expand my business and build new ideas | AU12: Through Amodo Doreen | AV12: 5 - Very easy | AW12: Questions have all been about me and my business that I understood most | AX12: Yes | AZ12: Very fine | BT12: 605258607 | BU12: 7b2dbb0b-b45e-4712-a1fc-a23426c6d18f | BV12: 45974.771 | BY12: submitted_via_web | CA12: vCJgLk2yV8oivMfbcbCpCF | CC12: 589 | CF12: Stanbic Bank Incubator | CG12: Aggie's Best Cakes, Juice and Takeaway | CH12: 605258607 | CI12: 1 | CJ12: Tibiwa | CK12: Agnes | CL12: 37962 | CN12: Female | CO12: 90 | CP12: Uganda | CQ12: No | CV12: Ugandan | CX12: Wakiso | CY12: Nsangi | CZ12: Kasenge | DA12: Kinaawa | DB12: 746363643 | DC12: aggiemishello@gmail.com | DD12: Yes | DE12: 200000 | DH12: 717 | DI12: 10X Digital Economy Expression of interest Form | DJ12: 589 | DK12: 605258607 | DL12: 7b2dbb0b-b45e-4712-a1fc-a23426c6d18f | DM12: 45974.771 | DP12: submitted_via_web | DR12: vCJgLk2yV8oivMfbcbCpCF | DT12: Stanbic Bank Incubator | DU12: Aggie's Best Cakes, Juice and Takeaway | DV12: 605258607 | DW12: 1 | DX12: Tibiwa Agnes | DY12: Yes | EL12: Kinaawa | ES12: 1226 | ET12: 10X Digital Economy Expression of interest Form | EU12: 589 | EV12: 605258607 | EW12: 7b2dbb0b-b45e-4712-a1fc-a23426c6d18f | EX12: 45974.771 | FA12: submitted_via_web | FC12: vCJgLk2yV8oivMfbcbCpCF | GK12: Unique | GL12: 22 | GM12: 22
A13: 0.026737269 | B13: 45975 | C13: Stanbic Bank Incubator | D13: doesnt have | E13: baking and mobile money | F13: No | H13: No | L13: No | N13: Central | O13: Wakiso | P13: wakiso | Q13: Bukasa | R13: Light manufacturing | T13: 1 | U13: 1 | V13: 1 | W13: 1 | X13: cakes,breads ,cookies and mobile money | Y13: capital | Z13: 1 | AA13: 20 | AB13: 605484503 | AC13: it is working good | AD13: 0 | AE13: Yes | AF13: 1 | AG13: Yes | AH13: its good | AI13: 2000000 | AJ13: To serve uganda | AK13: its well with skills and quality | AL13: No | AN13: No | AP13: No | AR13: No | AT13: i was interested bse it teaches on bussines | AU13: from my friend | AV13: 2 - Difficult | AW13: Answering | AX13: Yes | BT13: 605484503 | BU13: 42cb7100-9107-456c-90e3-eff1c7ca0dac | BV13: 45975.251 | BY13: submitted_via_web | CA13: vCJgLk2yV8oivMfbcbCpCF | CC13: 599 | CF13: Stanbic Bank Incubator | CG13: doesnt have | CH13: 605484503 | CI13: 1 | CJ13: Mukyala | CK13: winfred | CL13: 36192 | CN13: Female | CO13: 100 | CP13: ugandan | CQ13: No | CV13: Ugandan | CX13: Wakiso | CY13: wakiso | CZ13: Bukasa | DA13: kigoma | DB13: 755387203 | DC13: twixwinnie21@gmail.com | DD13: Yes | DE13: 150000 | DH13: 727 | DI13: 10X Digital Economy Expression of interest Form | DJ13: 599 | DK13: 605484503 | DL13: 42cb7100-9107-456c-90e3-eff1c7ca0dac | DM13: 45975.251 | DP13: submitted_via_web | DR13: vCJgLk2yV8oivMfbcbCpCF | DT13: Stanbic Bank Incubator | DU13: doesnt have | DV13: 605484503 | DW13: 1 | DX13: Mukyala | DY13: Yes | EL13: kigoma | ES13: 1248 | ET13: 10X Digital Economy Expression of interest Form | EU13: 599 | EV13: 605484503 | EW13: 42cb7100-9107-456c-90e3-eff1c7ca0dac | EX13: 45975.251 | FA13: submitted_via_web | FC13: vCJgLk2yV8oivMfbcbCpCF | FE13: Stanbic Bank Incubator | FF13: doesnt have | FG13: 605484503 | FH13: 1 | FI13: mukyala | FJ13: winfred | FK13: 36192 | FL13: Female | FM13: selling to the customers | FN13: 150000 | FO13: No | FQ13: Ugandan | FS13: Wakiso | FT13: wakiso | FU13: Bukasa | FV13: kigoma | FW13: 755387203 | FX13: twixwinnie21@gmail.com | FY13: CF9900810EH9GA | FZ13: 408 | GA13: 10X Digital Economy Expression of interest Form | GB13: 599 | GC13: 605484503 | GD13: 42cb7100-9107-456c-90e3-eff1c7ca0dac | GE13: 45975.251 | GH13: submitted_via_web | GJ13: vCJgLk2yV8oivMfbcbCpCF | GK13: Unique | GL13: 27 | GM13: 27
A14: 0.021078704 | B14: 45976 | C14: Stanbic Bank Incubator | D14: Suma Mobile Money Services | E14: Easyload, deposit of cash, withdraw and phone accessories | F14: No | H14: No | J14: IMG-20251113-WA0073-16_44_12.jpg | K14: https://kf.kobotoolbox.org/api/v2/assets/a9dTHTe72X7zPceKxVtSxV/data/606622367/attachments/attJeAbFNwMWYpSuwCDEASqQ/ | L14: No | N14: Central | O14: Wakiso | P14: Nsangi | Q14: Kasenge ward | R14: trade and services | T14: 1 | U14: 1 | V14: 1 | W14: 0 | X14: We make it easy for people in the community to have their money in hard form instantly and even Making mobile services easier | Y14: Small scale that hinders potential customers | Z14: 1 | AA14: 1 | AB14: 606622367 | AC14: We withdraw and deposit money, sell easyload and making mobile services easier | AD14: 0 | AE14: No | AG14: Yes | AH14: It was about business skills and I gained mostly financial skills. I can now run my business successfully | AI14: 5000000 | AJ14: Giving out quality services | AK14: Because I have been taught more about business and understood the topics, and the high demand for mobile services in my community | AL14: Yes | AM14: I can employ other people | AN14: Yes | AO14: Teacher | AP14: Yes | AQ14: Teacher | AR14: No | AT14: I wanted to learn how to have a successful business | AU14: Howard Muhwezi | AV14: 4 - Easy | AW14: Most of them were questions about my business | AX14: Yes | AZ14: Thanks | BT14: 606622367 | BU14: 2f514c1d-cd44-4fa8-a95c-6022bf1d2d4e | BV14: 45976.672 | BY14: submitted_via_web | CA14: vCJgLk2yV8oivMfbcbCpCF | CC14: 708 | CF14: Stanbic Bank Incubator | CG14: Suma Mobile Money Services | CH14: 606622367 | CI14: 1 | CJ14: Nanyunja | CK14: Sumayiyah | CL14: 35616 | CN14: Female | CO14: 98 | CP14: Ugandan | CQ14: No | CV14: Ugandan | CX14: Wakiso | CY14: Nsangi | CZ14: Kasenge ward | DA14: Kyengera | DB14: 740522879 | DC14: sumayiyah58@gmail.com | DD14: Yes | DE14: 100000 | DF14: IMG-20251113-WA0073-18_10_32.jpg | DG14: https://kf.kobotoolbox.org/api/v2/assets/a9dTHTe72X7zPceKxVtSxV/data/606622367/attachments/attkTayWCHUd6sHZn7mwPpNA/ | DH14: 836 | DI14: 10X Digital Economy Expression of interest Form | DJ14: 708 | DK14: 606622367 | DL14: 2f514c1d-cd44-4fa8-a95c-6022bf1d2d4e | DM14: 45976.672 | DP14: submitted_via_web | DR14: vCJgLk2yV8oivMfbcbCpCF | DT14: Stanbic Bank Incubator | DU14: Suma Mobile Money Services | DV14: 606622367 | DW14: 1 | DX14: 1 | DY14: Yes | EL14: Kyengera | ES14: 1364 | ET14: 10X Digital Economy Expression of interest Form | EU14: 708 | EV14: 606622367 | EW14: 2f514c1d-cd44-4fa8-a95c-6022bf1d2d4e | EX14: 45976.672 | FA14: submitted_via_web | FC14: vCJgLk2yV8oivMfbcbCpCF | GK14: Unique | GL14: 22 | GM14: 22
A15: 0.0058657407 | B15: 45977 | C15: Stanbic Bank Incubator | D15: Sharifah Enterprises Ltd | E15: We deal in charcoal and grocery, providing basics to the community making life more easier | F15: No | H15: No | J15: IMG-20251113-WA0034-2_17_40.jpg | K15: https://kf.kobotoolbox.org/api/v2/assets/a9dTHTe72X7zPceKxVtSxV/data/606771268/attachments/attQdoZHKuXsjEJk3PeyjJSx/ | L15: No | N15: Central | O15: Wakiso | P15: Nsangi | Q15: Kasenge ward | R15: trade and services | T15: 1 | U15: 1 | V15: 1 | W15: 0 | X15: We deal in charcoal selling and grocery | Y15: Insufficient capital | Z15: 1 | AA15: 1 | AB15: 606771268 | AC15: Dealers in charcoal selling and grocery, I make money through buying charcoal from nearby villages and get some little profits due to little capital, get groceries from the market and have 5% as profits. I sell the products at a low price due to the place am in. | AD15: 0 | AE15: No | AG15: Yes | AH15: I learnt basics on how to manage personal and business finances and Mr. Bernard was the teacher | AI15: 3000000 | AJ15: Expansion of my business | AK15: Because am working and I want to expand my business | AL15: Yes | AM15: After expanding my business, I want to also support other youth to get employed by giving them jobs | AN15: Yes | AO15: Teacher | AP15: Yes | AQ15: Business expert | AR15: No | AT15: I want to learn how to succeed in my business | AU15: From Howard Muhwezi | AV15: 4 - Easy | AW15: All the questions where about me and my business that 8 understood more | AX15: Yes | AZ15: Thanks for the program | BT15: 606771268 | BU15: 469f176e-2d69-435c-a015-7095f1229719 | BV15: 45976.983 | BY15: submitted_via_web | CA15: vCJgLk2yV8oivMfbcbCpCF | CC15: 718 | CF15: Stanbic Bank Incubator | CG15: Sharifah Enterprises Ltd | CH15: 606771268 | CI15: 1 | CJ15: Nabaata | CK15: Sharifah | CL15: 33691 | CN15: Female | CO15: 90 | CP15: Ugandan | CQ15: No | CV15: Ugandan | CX15: Wakiso | CY15: Nsangi | CZ15: Kasenge ward | DA15: Kazinga | DB15: 709734971 | DC15: nabattas80@gmail.com | DD15: Yes | DE15: 300000 | DF15: IMG-20251113-WA0034-2_21_55.jpg | DG15: https://kf.kobotoolbox.org/api/v2/assets/a9dTHTe72X7zPceKxVtSxV/data/606771268/attachments/attVnmHs97retdqm7Wny5qyE/ | DH15: 846 | DI15: 10X Digital Economy Expression of interest Form | DJ15: 718 | DK15: 606771268 | DL15: 469f176e-2d69-435c-a015-7095f1229719 | DM15: 45976.983 | DP15: submitted_via_web | DR15: vCJgLk2yV8oivMfbcbCpCF | DT15: Stanbic Bank Incubator | DU15: Sharifah Enterprises Ltd | DV15: 606771268 | DW15: 1 | DX15: Nabaata | DY15: Yes | EL15: Kazinga | ES15: 1375 | ET15: 10X Digital Economy Expression of interest Form | EU15: 718 | EV15: 606771268 | EW15: 469f176e-2d69-435c-a015-7095f1229719 | EX15: 45976.983 | FA15: submitted_via_web | FC15: vCJgLk2yV8oivMfbcbCpCF | GK15: Unique | GL15: 33 | GM15: 33
A16: 0.024893519 | B16: 45977 | C16: Stanbic Bank Incubator | D16: Sadress Poultry Farmers | E16: Dealers in Poultry of all kinds, like broilers, croilers, layers and eggs suppliers | F16: No | H16: No | J16: IMG-20251115-WA0005-2_52_22.jpg | K16: https://kf.kobotoolbox.org/api/v2/assets/a9dTHTe72X7zPceKxVtSxV/data/606777477/attachments/attWUL8HR7tj63GKQ4qxeUpN/ | L16: No | N16: Central | O16: Wakiso | P16: Nsangi | Q16: Kasenge ward | R16: Agriculture | T16: 1 | U16: 1 | V16: 1 | W16: 0 | X16: Dealers in all kinds of Poultry, broilers, croilers,layers and eggs supplies | Y16: Small scale of land and insufficient funds | Z16: 1 | AA16: 1 | AB16: 606777477 | AC16: We deal supply of broilers, croilers and eggs supply. I supply retail shop and earn income | AD16: 0 | AE16: No | AG16: Yes | AH16: I was all about business skills for success and I learnt more about business growth | AI16: 5000000 | AJ16: Giving out jobs to others and teaching them what I learnt in 10x that led to my success | AK16: Because it's the backbone of Uganda | AL16: Yes | AM16: My business promotes health and improves on people's lives | AN16: Yes | AO16: Teacher | AP16: Yes | AQ16: Business expert | AR16: No | AT16: I wanted to expand my business | AU16: Through Amodo Doreen | AV16: 4 - Easy | AW16: Because it was all about business | AX16: Yes | AZ16: Thanks | BT16: 606777477 | BU16: a00b5db3-c1d2-4c8b-a179-ffd717547062 | BV16: 45977.012 | BY16: submitted_via_web | CA16: vCJgLk2yV8oivMfbcbCpCF | CC16: 719 | CF16: Stanbic Bank Incubator | CG16: Sadress Poultry Farmers | CH16: 606777477 | CI16: 1 | CJ16: Kyabiere | CK16: Sadress | CL16: 34030 | CN16: Female | CO16: 80 | CP16: Ugandan | CQ16: No | CV16: Ugandan | CX16: Wakiso | CY16: Nsangi | CZ16: Kasenge ward | DA16: Kazinga | DB16: 776816316 | DC16: sadresskyabiere@gmail.com | DD16: Yes | DE16: 100000 | DF16: IMG-20251115-WA0005-2_52_22-2_57_20.jpg | DG16: https://kf.kobotoolbox.org/api/v2/assets/a9dTHTe72X7zPceKxVtSxV/data/606777477/attachments/att3WZM7pQPv2Vws2huHVEE9/ | DH16: 847 | DI16: 10X Digital Economy Expression of interest Form | DJ16: 719 | DK16: 606777477 | DL16: a00b5db3-c1d2-4c8b-a179-ffd717547062 | DM16: 45977.012 | DP16: submitted_via_web | DR16: vCJgLk2yV8oivMfbcbCpCF | DT16: Stanbic Bank Incubator | DU16: Sadress Poultry Farmers | DV16: 606777477 | DW16: 1 | DX16: Kyabiere | DY16: Yes | EL16: Kazinga | ES16: 1376 | ET16: 10X Digital Economy Expression of interest Form | EU16: 719 | EV16: 606777477 | EW16: a00b5db3-c1d2-4c8b-a179-ffd717547062 | EX16: 45977.012 | FA16: submitted_via_web | FC16: vCJgLk2yV8oivMfbcbCpCF | GK16: Unique | GL16: 32 | GM16: 32
A17: 0.018630787 | B17: 45978 | C17: Stanbic Bank Incubator | D17: Carol Retail shop | E17: We deal in all kinds mostly common use basics like soap, sugar, dry food Vaselines etc | F17: No | H17: No | L17: No | N17: Central | O17: Wakiso | P17: Nsangi | Q17: Kasenge ward | R17: trade and services | T17: 1 | U17: 1 | V17: 1 | W17: 0 | X17: We offer basic needs to the community nearer including sugar, dry food, soap etc | Y17: Insufficient capital | Z17: 1 | AA17: 1 | AB17: 607266161 | AC17: I buy and sell products have some profits and contine running my business | AD17: 0 | AE17: No | AG17: Yes | AH17: I learnt more about business skills and I can now generate new ideas | AI17: 3000000 | AJ17: I want to keep my business grow and developing mu country by giving revenue | AK17: Because am in a still growing community | AL17: Yes | AM17: I want to register my business and learn more about it | AN17: No | AP17: Yes | AQ17: Teacher | AR17: No | AT17: My businesses have been failling | AU17: Kayaga Patricia | AV17: 4 - Easy | AW17: All was about business | AX17: Yes | AZ17: Thank you | BT17: 607266161 | BU17: e1b17516-b9cd-4975-a9f8-6b62b3dd845e | BV17: 45978.003 | BY17: submitted_via_web | CA17: vCJgLk2yV8oivMfbcbCpCF | CC17: 736 | CF17: Stanbic Bank Incubator | CG17: Carol Retail shop | CH17: 607266161 | CI17: 1 | CJ17: Nansubuga | CK17: Carol | CL17: 37538 | CN17: Female | CO17: 90 | CP17: Ugandan | CQ17: No | CV17: Ugandan | CX17: Wakiso | CY17: Nsangi | CZ17: Kasenge ward | DA17: Kikajjo | DB17: 708040037 | DC17: nansubugacarol@gmail.com | DD17: Yes | DE17: 200000 | DF17: IMG-20251114-WA0056-2_45_30.jpg | DG17: https://kf.kobotoolbox.org/api/v2/assets/a9dTHTe72X7zPceKxVtSxV/data/607266161/attachments/attFD78cMZHgYJAtge7Es8Cu/ | DH17: 864 | DI17: 10X Digital Economy Expression of interest Form | DJ17: 736 | DK17: 607266161 | DL17: e1b17516-b9cd-4975-a9f8-6b62b3dd845e | DM17: 45978.003 | DP17: submitted_via_web | DR17: vCJgLk2yV8oivMfbcbCpCF | DT17: Stanbic Bank Incubator | DU17: Carol Retail shop | DV17: 607266161 | DW17: 1 | DX17: Nansubuga | DY17: Yes | EL17: Kikajjo | ES17: 1393 | ET17: 10X Digital Economy Expression of interest Form | EU17: 736 | EV17: 607266161 | EW17: e1b17516-b9cd-4975-a9f8-6b62b3dd845e | EX17: 45978.003 | FA17: submitted_via_web | FC17: vCJgLk2yV8oivMfbcbCpCF | GK17: Unique | GL17: 23 | GM17: 23
A18: 0.0031064815 | B18: 45978 | C18: Stanbic Bank Incubator | D18: J and J Beauty Salon | E18: We offer braids styles in all kinds | F18: No | H18: No | L18: No | N18: Central | O18: Wakiso | P18: Nsangi | Q18: Kasenge ward | R18: fashion and design | T18: 1 | U18: 1 | V18: 1 | W18: 0 | X18: We offer braid styles in all kinds. | Y18: I work from home, I want to have a place for work | Z18: 1 | AA18: 1 | AB18: 607270081 | AC18: I get customers and plait their hair, get money for profits helping in the on going of the business | AD18: 0 | AE18: No | AG18: Yes | AH18: We learnt about business ethics | AI18: 4000000 | AJ18: When my business is successful, k can also teach people my professions | AK18: Because my business supports young people which 10x is aiming at | AL18: Yes | AM18: I want to register my business | AN18: Yes | AO18: Teacher | AP18: Yes | AQ18: Teacher and student | AR18: No | AT18: I wanted to learn business growth | AU18: Amodo Doreen | AV18: 4 - Easy | AW18: Business is the topic | AX18: Yes | AZ18: Thanks | BT18: 607270081 | BU18: a80d220b-78d3-40aa-ba5e-17c2f445eb51 | BV18: 45978.017 | BY18: submitted_via_web | CA18: vCJgLk2yV8oivMfbcbCpCF | CC18: 737 | CF18: Stanbic Bank Incubator | CG18: J and J Beauty Salon | CH18: 607270081 | CI18: 1 | CJ18: Nalugwa | CK18: Juliet | CL18: 36993 | CN18: Female | CO18: 94 | CP18: Ugandan | CQ18: No | CV18: Ugandan | CX18: Wakiso | CY18: Nsangi | CZ18: Kasenge ward | DA18: Kazinga | DB18: 761316517 | DC18: julietnalugwa818@gmail.com | DD18: Yes | DE18: 200000 | DF18: IMG-20251113-WA0007-3_14_24.jpg | DG18: https://kf.kobotoolbox.org/api/v2/assets/a9dTHTe72X7zPceKxVtSxV/data/607270081/attachments/attCcsBGVcXbSkzSqaM7sCrk/ | DH18: 865 | DI18: 10X Digital Economy Expression of interest Form | DJ18: 737 | DK18: 607270081 | DL18: a80d220b-78d3-40aa-ba5e-17c2f445eb51 | DM18: 45978.017 | DP18: submitted_via_web | DR18: vCJgLk2yV8oivMfbcbCpCF | DT18: Stanbic Bank Incubator | DU18: J and J Beauty Salon | DV18: 607270081 | DW18: 1 | DX18: Nalugwa | DY18: Yes | EL18: Kazinga | ES18: 1394 | ET18: 10X Digital Economy Expression of interest Form | EU18: 737 | EV18: 607270081 | EW18: a80d220b-78d3-40aa-ba5e-17c2f445eb51 | EX18: 45978.017 | FA18: submitted_via_web | FC18: vCJgLk2yV8oivMfbcbCpCF | GK18: Unique | GL18: 24 | GM18: 24
A19: 0.025082176 | B19: 45978 | C19: Stanbic Bank Incubator | D19: Sylvia enterprise | E19: Dealing in Scholastic materials, mobile money, and tailoring | F19: No | H19: No | L19: No | N19: Central | O19: Wakiso | P19: Ndejje | Q19: Ndejje | R19: fashion and design | T19: 1 | U19: 1 | V19: 1 | W19: 0 | X19: Books, airtime,deposit and withdraw | Y19: Lack of enough capital | Z19: 1 | AA19: 1 | AB19: 607591148 | AC19: By sale of books, and repairing people's clothes | AD19: 0 | AE19: No | AG19: No | AI19: 5000000 | AJ19: I expect has business to grow by 70 percent by the end of next year if I get more capital. | AK19: Because it operates in highly populated area. | AL19: No | AN19: No | AP19: No | AR19: No | AT19: To acquire more knowledge of how to operate a business. | AU19: It's a program that provides knowledge about operating a business. | AV19: 4 - Easy | AW19: Because these are the things we move in in our day today life | AX19: Yes | AZ19: I thank the 10x program for this initiative. | BT19: 607591148 | BU19: b70d05b7-8837-4aae-98aa-a8c3f6d76b95 | BV19: 45978.426 | BY19: submitted_via_web | CA19: vCJgLk2yV8oivMfbcbCpCF | CC19: 739 | CF19: Stanbic Bank Incubator | CG19: Sylvia enterprise | CH19: 607591148 | CI19: 1 | CJ19: Sylivia | CK19: Namugambe | CL19: 32680 | CN19: Female | CO19: 100 | CP19: Ugandan | CQ19: No | CV19: Ugandan | CX19: Wakiso | CY19: Ndejje | CZ19: Ndejje | DA19: Bongole | DB19: 755910515 | DC19: sylivianamugambe497@gmail.com | DD19: Yes | DE19: 50000 | DF19: IMG_20251116_232749_013~2-12_50_51.jpg | DG19: https://kf.kobotoolbox.org/api/v2/assets/a9dTHTe72X7zPceKxVtSxV/data/607591148/attachments/attSCndjS2Mt3vtjU6N7MEyE/ | DH19: 867 | DI19: 10X Digital Economy Expression of interest Form | DJ19: 739 | DK19: 607591148 | DL19: b70d05b7-8837-4aae-98aa-a8c3f6d76b95 | DM19: 45978.426 | DP19: submitted_via_web | DR19: vCJgLk2yV8oivMfbcbCpCF | DT19: Stanbic Bank Incubator | DU19: Sylvia enterprise | DV19: 607591148 | DW19: 1 | DX19: Sylivia | DY19: Yes | EL19: Bongole | ES19: 1396 | ET19: 10X Digital Economy Expression of interest Form | EU19: 739 | EV19: 607591148 | EW19: b70d05b7-8837-4aae-98aa-a8c3f6d76b95 | EX19: 45978.426 | FA19: submitted_via_web | FC19: vCJgLk2yV8oivMfbcbCpCF | GK19: Unique | GL19: 0
A20: 0.036561343 | B20: 45978 | C20: Stanbic Bank Incubator | D20: Godhen collections | E20: A boutique | F20: No | H20: No | L20: No | N20: Central | O20: Wakiso | P20: Kajjansi | Q20: Nsaggu | R20: fashion and design | T20: 1 | U20: 1 | V20: 1 | W20: 0 | X20: We sell clothes | Y20: We give wears | Z20: 1 | AA20: 2 | AB20: 607840757 | AC20: I charge between 20k and 50k | AD20: 0 | AE20: Yes | AF20: 1 | AG20: No | AI20: 5000000 | AJ20: To make the first shop bigger and to facilitate the branch | AK20: It's in the center of the town and we advertise | AL20: Yes | AM20: I need a help to register my business | AN20: No | AP20: No | AR20: No | AT20: To get more knowledge about business | AU20: By a friend | AV20: 4 - Easy | AW20: I know the language | AX20: Yes | AZ20: Thank you | BT20: 607840757 | BU20: 93afd76a-5b28-466e-9ac7-f774579a0885 | BV20: 45978.579 | BY20: submitted_via_web | CA20: vCJgLk2yV8oivMfbcbCpCF | CC20: 745 | CF20: Stanbic Bank Incubator | CG20: Godhen collections | CH20: 607840757 | CI20: 1 | CJ20: NKWANGA | CK20: LYDIA | CL20: 31747 | CN20: Female | CO20: 100 | CP20: Ugandan | CQ20: No | CV20: Ugandan | CX20: Wakiso | CY20: Kajjansi | CZ20: Nsaggu | DA20: Nsaggu | DB20: 789538005 | DC20: zaweddelydia711@gmail.com | DD20: No | DF20: 17633856835095840836843592302337-16_21_58.jpg | DG20: https://kf.kobotoolbox.org/api/v2/assets/a9dTHTe72X7zPceKxVtSxV/data/607840757/attachments/att52FToiZfPZLMWATWuedtN/ | DH20: 874 | DI20: 10X Digital Economy Expression of interest Form | DJ20: 745 | DK20: 607840757 | DL20: 93afd76a-5b28-466e-9ac7-f774579a0885 | DM20: 45978.579 | DP20: submitted_via_web | DR20: vCJgLk2yV8oivMfbcbCpCF | DT20: Stanbic Bank Incubator | DU20: Godhen collections | DV20: 607840757 | DW20: 1 | DX20: Nkwanga Lydia | DY20: Yes | EL20: Nsaggu | ES20: 1406 | ET20: 10X Digital Economy Expression of interest Form | EU20: 745 | EV20: 607840757 | EW20: 93afd76a-5b28-466e-9ac7-f774579a0885 | EX20: 45978.579 | FA20: submitted_via_web | FC20: vCJgLk2yV8oivMfbcbCpCF | GK20: Unique | GL20: 39 | GM20: 39
A21: 0.014153935 | B21: 45978 | C21: Stanbic Bank Incubator | D21: Lydia soft drinks and shoe selling up to | E21: We selling good quality things | F21: No | H21: No | L21: No | N21: Central | O21: Wakiso | P21: Kajjansi | Q21: Nakawuka | R21: Light manufacturing | T21: 1 | U21: 1 | V21: 1 | W21: 1 | X21: We provide good juice, quality shoes | Y21: It's solves thirty from people during hot season | Z21: 1 | AA21: 2 | AB21: 608056188 | AC21: It works regularly, through selling different items,it depends on the price s in the market,it begins from 100_5000 | AD21: 140000 | AE21: No | AG21: Yes | AH21: He was mr.ssabagala,andaother two ladiesnd certifim zipora | AI21: 5000000 | AJ21: More skills | AK21: Am well trainined now | AL21: No | AN21: No | AP21: No | AR21: No | AT21: The way we were teached | AU21: It was told to by a friend | AV21: 3 - Neutral | AW21: Needs educated people | AX21: Yes | AZ21: Nothing much but thanks | BT21: 608056188 | BU21: 7ed39c93-848c-4eaf-b2db-9321491da544 | BV21: 45978.742 | BY21: submitted_via_web | CA21: vCJgLk2yV8oivMfbcbCpCF | CC21: 758 | CF21: Stanbic Bank Incubator | CG21: Lydia soft drinks and shoe selling up to | CH21: 608056188 | CI21: 1 | CJ21: Nakiganda | CK21: Lydia violet | CL21: 35371 | CN21: Female | CO21: 70 | CP21: Ugandan | CQ21: No | CV21: Ugandan | CX21: Wakiso | CY21: Kajjansi | CZ21: Nakawuka | DA21: Nakawuka/mpumudde | DB21: 751020338 | DC21: nakigandalydiav@gmail.com | DD21: Yes | DE21: 300000 | DF21: DSC_0168-17_29_27.JPG | DG21: https://kf.kobotoolbox.org/api/v2/assets/a9dTHTe72X7zPceKxVtSxV/data/608056188/attachments/attLNP68UdFTWs3ugTUzqZsK/ | DH21: 887 | DI21: 10X Digital Economy Expression of interest Form | DJ21: 758 | DK21: 608056188 | DL21: 7ed39c93-848c-4eaf-b2db-9321491da544 | DM21: 45978.742 | DP21: submitted_via_web | DR21: vCJgLk2yV8oivMfbcbCpCF | DT21: Stanbic Bank Incubator | DU21: Lydia soft drinks and shoe selling up to | DV21: 608056188 | DW21: 1 | DX21: Nalwadde Flavia | DY21: No | DZ21: Flavia | EA21: 31424 | EB21: Female | EC21: Helper | ED21: 100000 | EE21: No | EG21: Ugandan | EI21: Wakiso | EJ21: Kajjansi | EK21: Nakawuka | EL21: Nakawuka/mpumudde | EM21: 754269311 | EN21: nakigandalydiav@gmail.com | EO21: Primary level | EP21: CF820521099EVE | ES21: 1420 | ET21: 10X Digital Economy Expression of interest Form | EU21: 758 | EV21: 608056188 | EW21: 7ed39c93-848c-4eaf-b2db-9321491da544 | EX21: 45978.742 | FA21: submitted_via_web | FC21: vCJgLk2yV8oivMfbcbCpCF | FE21: Stanbic Bank Incubator | FF21: Lydia soft drinks and shoe selling up to | FG21: 608056188 | FH21: 1 | FI21: Nalubwama Lydia | FJ21: Lydia | FK21: 33239 | FL21: Female | FM21: Helper | FN21: 100000 | FO21: No | FQ21: Ugandan | FS21: Wakiso | FT21: Kajjansi | FU21: Nakawuka | FV21: Nakawuka/mpumudde | FW21: 701946290 | FX21: nakigandalydiav@gmail.com | FY21: CF9105210C79ZH | FZ21: 447 | GA21: 10X Digital Economy Expression of interest Form | GB21: 758 | GC21: 608056188 | GD21: 7ed39c93-848c-4eaf-b2db-9321491da544 | GE21: 45978.742 | GH21: submitted_via_web | GJ21: vCJgLk2yV8oivMfbcbCpCF | GK21: Unique | GL21: 29 | GM21: 29
A22: 0.040782407 | B22: 45979 | C22: Stanbic Bank Incubator | D22: Mutasubwa soft drinks no | E22: Mutasubwa soft drinks was established in 2025 it has been existing for 8 month and it sells different flavors of drinks and also detergents | F22: No | H22: No | L22: No | N22: Central | O22: Kampala | P22: Makindye division | Q22: Wasswa zone | R22: trade and services | T22: 2 | U22: 1 | V22: 1 | W22: 0 | X22: Soda and water it is for all customers either young or old | Y22: Problem of long distance and thirsty | Z22: 2 | AA22: 2 | AB22: 608476172 | AC22: It was in 24hours make money through making sells my costs 500 and 1000 | AD22: 600000 | AE22: No | AG22: Yes | AH22: Tinny he was training on how to save and how to grow your business | AI22: 2000000 | AJ22: My growth target is 500000 | AK22: Yes | AL22: No | AN22: No | AP22: No | AR22: Yes | AS22: Kabuwo Jennifer | AT22: To grow the business and knowing how to run business through media | AU22: Through college called Nakandi penninah | AV22: 3 - Neutral | AW22: Some questions are hard to answer | AX22: Yes | AZ22: Good | BT22: 608476172 | BU22: 0ae9a82f-608c-4964-ad0b-869a94880485 | BV22: 45979.376 | BY22: submitted_via_web | CA22: vCJgLk2yV8oivMfbcbCpCF | CC22: 781 | CF22: Stanbic Bank Incubator | CG22: Mutasubwa soft drinks no | CH22: 608476172 | CI22: 1 | CJ22: Kabuwo | CK22: Jennifer Bumali | CL22: 35068 | CN22: Female | CO22: 60 | CP22: Ugandan | CQ22: Yes | CR22: Visual disability Physical Disability | CS22: 1 | CT22: 0 | CV22: Ugandan | CX22: Kampala | CY22: Wasswa zone | CZ22: Nsambya parish | DA22: Wasswa zone | DB22: 780889032 | DC22: jenniferkabuwo@gmail.com | DD22: Yes | DE22: 200000 | DF22: Screenshot_20251118-112840-11_31_19.png | DG22: https://kf.kobotoolbox.org/api/v2/assets/a9dTHTe72X7zPceKxVtSxV/data/608476172/attachments/attwxGbjAEbcfLhiuKB4qoJ6/ | DH22: 911 | DI22: 10X Digital Economy Expression of interest Form | DJ22: 781 | DK22: 608476172 | DL22: 0ae9a82f-608c-4964-ad0b-869a94880485 | DM22: 45979.376 | DP22: submitted_via_web | DR22: vCJgLk2yV8oivMfbcbCpCF | DT22: Stanbic Bank Incubator | DU22: Mutasubwa soft drinks no | DV22: 608476172 | DW22: 1 | DX22: Kabuwo | DY22: Yes | EL22: Wasswa zone | ES22: 1444 | ET22: 10X Digital Economy Expression of interest Form | EU22: 781 | EV22: 608476172 | EW22: 0ae9a82f-608c-4964-ad0b-869a94880485 | EX22: 45979.376 | FA22: submitted_via_web | FC22: vCJgLk2yV8oivMfbcbCpCF | GK22: Unique | GL22: 30 | GM22: 30
A23: 0.029201389 | B23: 45979 | C23: Stanbic Bank Incubator | D23: Poultry | E23: Deals in birds keeping | F23: No | H23: No | L23: No | N23: Central | O23: Wakiso | P23: Wakiso subcouty | Q23: Bukasa parish | R23: Agriculture | T23: 1 | U23: 1 | V23: 1 | W23: 1 | X23: Eggs, chicken and also sales of the birds | Y23: Household income | Z23: 3 | AA23: 3 | AB23: 608533256 | AC23: Poultry | AD23: 500000 | AE23: No | AG23: Yes | AH23: I was running the project it was offering eggs and birds to the community igot prfitabd this changed my household income | AI23: 1000000 | AJ23: Abigger farm of birds and more sales | AK23: Because I have got enough training from the 10 x program on business management and record keeping | AL23: Yes | AM23: My enterprise welcomes other persons with disability to come and we work to improve our household income | AN23: Yes | AO23: She is a fellow person with disability | AP23: Yes | AQ23: She is a person with disability just like me | AR23: Yes | AS23: Penninah | AT23: The training they offer on digital economy | AU23: Through a friend from the disability flatanity | AV23: 2 - Difficult | AW23: Due to my disability my sight has not been easy being a person with albinism and has law sight | AX23: Yes | AZ23: The tool has been so useful for business persons with disability | BT23: 608533256 | BU23: 3350e8e5-0fc9-4384-8ad6-e884f92defc0 | BV23: 45979.415 | BY23: submitted_via_web | CA23: vCJgLk2yV8oivMfbcbCpCF | CC23: 785 | CF23: Stanbic Bank Incubator | CG23: Poultry | CH23: 608533256 | CI23: 1 | CJ23: Kasagga | CK23: Faith | CL23: 29171 | CN23: Female | CO23: 80 | CP23: Ugandan | CQ23: Yes | CR23: Others | CS23: 0 | CT23: 0 | CU23: Albinism | CV23: Ugandan | CX23: Wakiso | CY23: Wakiso subcouty | CZ23: Bukasa | DA23: Muyomba | DB23: 704744329 | DC23: bwanikafaith2016@gmail.com | DD23: Yes | DE23: 50000 | DF23: IMG_20251112_090304_484-9_47_41.jpg | DG23: https://kf.kobotoolbox.org/api/v2/assets/a9dTHTe72X7zPceKxVtSxV/data/608533256/attachments/attW8m8DnFUv6NBPod4dj5yE/ | DH23: 916 | DI23: 10X Digital Economy Expression of interest Form | DJ23: 785 | DK23: 608533256 | DL23: 3350e8e5-0fc9-4384-8ad6-e884f92defc0 | DM23: 45979.415 | DP23: submitted_via_web | DR23: vCJgLk2yV8oivMfbcbCpCF | DT23: Stanbic Bank Incubator | DU23: Poultry | DV23: 608533256 | DW23: 1 | DX23: Kasagga | DY23: No | DZ23: Faith | EA23: 29173 | EB23: Female | EC23: Looking after the birds | ED23: 50000 | EE23: Yes | EF23: Albinism | EG23: Ugandan | EI23: Wakiso | EJ23: Wakiso subcouty | EK23: Bukasa | EL23: Muyomba | EM23: 704744329 | EN23: bwanikafaith2016@gmail.com | EO23: Diploma | EP23: Cf790521081cll | ES23: 1448 | ET23: 10X Digital Economy Expression of interest Form | EU23: 785 | EV23: 608533256 | EW23: 3350e8e5-0fc9-4384-8ad6-e884f92defc0 | EX23: 45979.415 | FA23: submitted_via_web | FC23: vCJgLk2yV8oivMfbcbCpCF | FE23: Stanbic Bank Incubator | FF23: Poultry | FG23: 608533256 | FH23: 1 | FI23: Kasagga | FJ23: Faith | FK23: 29020 | FL23: Female | FM23: To take care of the nirds | FN23: 50000 | FO23: Yes | FP23: Albinism | FQ23: Ugandan | FS23: Wakiso | FT23: Wakiso subcouty | FU23: Bukasa | FV23: Muyomba | FW23: 704744329 | FX23: bwanikafaith2016@gmail.com | FY23: Cf790521081cll | FZ23: 488 | GA23: 10X Digital Economy Expression of interest Form | GB23: 785 | GC23: 608533256 | GD23: 3350e8e5-0fc9-4384-8ad6-e884f92defc0 | GE23: 45979.415 | GH23: submitted_via_web | GJ23: vCJgLk2yV8oivMfbcbCpCF | GK23: Unique | GL23: 46 | GM23: 46
A24: 0.040560185 | B24: 45979 | C24: Stanbic Bank Incubator | D24: Amanya Aronda poultry farm | E24: Eggs | F24: No | H24: No | J24: IMG-20251118-WA0000-15_1_30.jpg | K24: https://kf.kobotoolbox.org/api/v2/assets/a9dTHTe72X7zPceKxVtSxV/data/608696642/attachments/attJKSKw7HR6RhsvtQqQUYk7/ | L24: No | N24: Central | O24: Wakiso | P24: kasanje | Q24: Jungo | R24: Agriculture | T24: 1 | U24: 1 | V24: 1 | W24: 1 | X24: Selling eggs | Y24: Lack of employment in the area | Z24: 3 | AA24: 20 | AB24: 608696642 | AC24: To grow up the farm | AD24: 0 | AE24: Yes | AF24: 1 | AG24: No | AI24: 5000000 | AJ24: Boost my business | AK24: Because am sure of what am doing | AL24: No | AN24: No | AP24: No | AR24: No | AT24: To grow my business | AU24: I was taught about it | AV24: 3 - Neutral | AW24: I had full hope | AX24: Yes | BT24: 608696642 | BU24: 58b9960e-2a91-40e3-8057-f5582dd85a4b | BV24: 45979.526 | BY24: submitted_via_web | CA24: vCJgLk2yV8oivMfbcbCpCF | CC24: 795 | CF24: Stanbic Bank Incubator | CG24: Amanya Aronda poultry farm | CH24: 608696642 | CI24: 1 | CJ24: Tukwasibwe | CK24: Jalia | CL24: 28471 | CN24: Female | CO24: 100 | CP24: Ugandan | CQ24: No | CV24: Ugandan | CX24: Wakiso | CY24: Kasanje | CZ24: Jungo | DA24: Buvii | DB24: 702595555 | DC24: arindajalia@gmail.com | DD24: Yes | DE24: 300000 | DF24: IMG-20251118-WA0000-15_7_9.jpg | DG24: https://kf.kobotoolbox.org/api/v2/assets/a9dTHTe72X7zPceKxVtSxV/data/608696642/attachments/att6RQN3KJhxyXaSD5CZXNqH/ | DH24: 931 | DI24: 10X Digital Economy Expression of interest Form | DJ24: 795 | DK24: 608696642 | DL24: 58b9960e-2a91-40e3-8057-f5582dd85a4b | DM24: 45979.526 | DP24: submitted_via_web | DR24: vCJgLk2yV8oivMfbcbCpCF | DT24: Stanbic Bank Incubator | DU24: Amanya Aronda poultry farm | DV24: 608696642 | DW24: 1 | DX24: Tukwasibwe | DY24: Yes | EL24: Buvii | ES24: 1463 | ET24: 10X Digital Economy Expression of interest Form | EU24: 795 | EV24: 608696642 | EW24: 58b9960e-2a91-40e3-8057-f5582dd85a4b | EX24: 45979.526 | FA24: submitted_via_web | FC24: vCJgLk2yV8oivMfbcbCpCF | FE24: Stanbic Bank Incubator | FF24: Amanya Aronda poultry farm | FG24: 608696642 | FH24: 1 | FI24: Tukwasibwe | FJ24: Jalia | FK24: 28471 | FL24: Female | FM24: To look after chicken | FN24: 300000 | FO24: No | FQ24: Ugandan | FS24: Wakiso | FT24: Kasanje | FU24: Jungo | FV24: Buvii | FW24: 702595555 | FX24: arindajalia@gmail.com | FY24: CF770091057EAC | FZ24: 497 | GA24: 10X Digital Economy Expression of interest Form | GB24: 795 | GC24: 608696642 | GD24: 58b9960e-2a91-40e3-8057-f5582dd85a4b | GE24: 45979.526 | GH24: submitted_via_web | GJ24: vCJgLk2yV8oivMfbcbCpCF | GK24: Unique | GL24: 48 | GM24: 48
A25: 0.0094918981 | B25: 45979 | C25: Stanbic Bank Incubator | D25: Maama Jovias Saloon | E25: We sell braids, weaves,crochets, threads,wool,we do weaving, bridal,shampooing and hair styling | F25: Yes | G25: Town council | H25: Yes | I25: 2250010000000 | J25: IMG_20251118_094752_016-9_53_58.jpg | K25: https://kf.kobotoolbox.org/api/v2/assets/a9dTHTe72X7zPceKxVtSxV/data/608807304/attachments/attHVyESxGqhzU9sJEXTVwKG/ | L25: No | N25: Central | O25: Wakiso | P25: Kajjansi | Q25: Nakawuka | R25: fashion and design | T25: 1 | U25: 1 | V25: 1 | W25: 0 | X25: Products; oil for damagedhair,braids, weaves, crochets, Jerry, earrings, bridal and styling pins, puff holders,relaxers,tinti, among others.servises;we do braiding,weaving,crocheting,shampoo and blow-drying, relaxing and setting ,bridal styling and make-up,traininghairdressing | Y25: For damaged hair,we have oil 3000&5000we are known for that | Z25: 2 | AA25: 4 | AB25: 608807304 | AC25: Selling hair products and hair styling .charging depends on negotiations with the customer. ie.natural spring 25000,30000 or 40000, braiding depends on the braids used if it's zanzi,aluba,all extra long braids we charge from 30'000 , retouch we start with 25000 | AD25: 4800000 | AE25: No | AG25: No | AI25: 2000000 | AJ25: Advertising our business on watsapp profile and social media like TikTok, employing more women | AK25: It's registered,we are situated in town and well experienced | AL25: No | AN25: No | AP25: No | AR25: No | AT25: financial business support | AU25: Mdm Dorothy announced on the local radio | AV25: 4 - Easy | AW25: If at all you are literate,you have a business and everything you are saying is present and real ,the form becomes easy | AX25: Yes | BT25: 608807304 | BU25: 2451f63e-a5e8-40ac-a3e1-4d7b1f678633 | BV25: 45979.599 | BY25: submitted_via_web | CA25: vCJgLk2yV8oivMfbcbCpCF | CC25: 801 | CF25: Stanbic Bank Incubator | CG25: Maama Jovias Saloon | CH25: 608807304 | CI25: 1 | CJ25: Nabukeera | CK25: Benah | CL25: 31825 | CN25: Female | CO25: 98 | CP25: Uganda | CQ25: No | CV25: Ugandan | CX25: Wakiso | CY25: Kajjansi | CZ25: Nakawuka | DA25: Nakawuka | DB25: 753149070 | DC25: nabukeerabenah@gmail.com | DD25: Yes | DE25: 200000 | DF25: IMG_20250523_101124_108-16_7_59.jpg | DG25: https://kf.kobotoolbox.org/api/v2/assets/a9dTHTe72X7zPceKxVtSxV/data/608807304/attachments/attfSaji2SoiDCf9egkPJu9d/ | DH25: 937 | DI25: 10X Digital Economy Expression of interest Form | DJ25: 801 | DK25: 608807304 | DL25: 2451f63e-a5e8-40ac-a3e1-4d7b1f678633 | DM25: 45979.599 | DP25: submitted_via_web | DR25: vCJgLk2yV8oivMfbcbCpCF | DT25: Stanbic Bank Incubator | DU25: Maama Jovias Saloon | DV25: 608807304 | DW25: 1 | DX25: Kirabo | DY25: No | DZ25: Dorothy Hellen | EA25: 31932 | EB25: Female | EC25: Braiding | ED25: 50000 | EE25: No | EG25: Ugandan | EI25: Wakiso | EJ25: Kajjansi | EK25: Nakawuka | EL25: Nakawuka | EM25: 789133839 | EN25: doreenkirabo44@gmail.com | EO25: Diploma | EP25: CF87052103MW9A | ES25: 1469 | ET25: 10X Digital Economy Expression of interest Form | EU25: 801 | EV25: 608807304 | EW25: 2451f63e-a5e8-40ac-a3e1-4d7b1f678633 | EX25: 45979.599 | FA25: submitted_via_web | FC25: vCJgLk2yV8oivMfbcbCpCF | GK25: Unique | GL25: 0 | GM25: 39
A26: 0.040085648 | B26: 45979 | C26: Stanbic Bank Incubator | D26: Fermented milk | E26: It's a soft drink | F26: No | H26: No | L26: No | N26: Central | O26: Kampala | P26: Makindye | Q26: Kibuye I | R26: trade and services | T26: 1 | U26: 2 | V26: 3 | W26: 2 | X26: Per now I just focused on fermented milk | Y26: Capital | Z26: 10 | AA26: 15 | AB26: 608933971 | AC26: It costs 1000per glass | AD26: 100000 | AE26: No | AG26: Yes | AH26: It was a business interprenuareship | AI26: 2000000 | AJ26: To expand my business through the knowledge I got from the business tips I got from that program | AK26: The knowledge I got from the business and 10x programs we learned and the skills I know I will make it to grow | AL26: No | AN26: No | AP26: Yes | AQ26: They are the one who helped us with the teaching of these courses | AR26: No | AT26: I wanted to know more and the skills of the business since I hard just started my business and I didn't not have any experience in it | AU26: Friend | AV26: 2 - Difficult | AW26: I thought I would not to it | AX26: Yes | AZ26: Thanks for the supporting us in such program it really helps us a lot to open our minds and to know more about to start and how to expand our businesses please put more courses like these for more knowledge | BT26: 608933971 | BU26: 0c6f7da5-169f-446a-aad6-2546328fcde6 | BV26: 45979.695 | BY26: submitted_via_web | CA26: vCJgLk2yV8oivMfbcbCpCF | CC26: 802 | CF26: Stanbic Bank Incubator | CG26: Fermented milk | CH26: 608933971 | CI26: 1 | CJ26: Basuuta | CK26: Flavia | CL26: 35431 | CN26: Female | CO26: 100 | CP26: Uganda | CQ26: Yes | CR26: Physical Disability | CS26: 0 | CT26: 0 | CV26: Ugandan | CX26: Kampala | CY26: Makindye | CZ26: Kibuye I | DA26: Makindye | DB26: 757646938 | DC26: basuutaflavia2022@gmail.com | DD26: Yes | DE26: 10000 | DF26: IMG-20250624-WA0028-23_20_51.jpg | DG26: https://kf.kobotoolbox.org/api/v2/assets/a9dTHTe72X7zPceKxVtSxV/data/608933971/attachments/att4NcASURBLgT82jiBrnSuv/ | DH26: 938 | DI26: 10X Digital Economy Expression of interest Form | DJ26: 802 | DK26: 608933971 | DL26: 0c6f7da5-169f-446a-aad6-2546328fcde6 | DM26: 45979.695 | DP26: submitted_via_web | DR26: vCJgLk2yV8oivMfbcbCpCF | DT26: Stanbic Bank Incubator | DU26: Fermented milk | DV26: 608933971 | DW26: 3 | DX26: Basuuta Flavia | DY26: Yes | EL26: Makindye | ES26: 1472 | ET26: 10X Digital Economy Expression of interest Form | EU26: 802 | EV26: 608933971 | EW26: 0c6f7da5-169f-446a-aad6-2546328fcde6 | EX26: 45979.695 | FA26: submitted_via_web | FC26: vCJgLk2yV8oivMfbcbCpCF | FE26: Stanbic Bank Incubator | FF26: Fermented milk | FG26: 608933971 | FH26: 2 | FI26: Basuuta | FJ26: Flavia | FK26: 35431 | FL26: Female | FM26: Founder | FN26: 50000 | FO26: Yes | FQ26: Ugandan | FS26: Kampala | FT26: Makindye | FU26: Kibuye I | FV26: Makindye | FW26: 757646938 | FX26: basuutaflavia2022@gmail.com | FY26: CF970101217TFJ | FZ26: 499 | GA26: 10X Digital Economy Expression of interest Form | GB26: 802 | GC26: 608933971 | GD26: 0c6f7da5-169f-446a-aad6-2546328fcde6 | GE26: 45979.695 | GH26: submitted_via_web | GJ26: vCJgLk2yV8oivMfbcbCpCF | GK26: Unique | GL26: 29 | GM26: 29
A27: 0.012758102 | B27: 45979 | C27: Stanbic Bank Incubator | D27: Christine boutique, fashion and design | E27: Mainly deals in female clothes | F27: No | H27: No | L27: No | N27: West | O27: Wakiso | P27: Kajjansi Town Council | Q27: Nakawuka | R27: fashion and design | T27: 1 | U27: 1 | V27: 1 | W27: 0 | X27: First class clothes, second hand dresses, T-shirts for both men and women, ebitengi, belts | Y27: Solves the dressing code of some people | Z27: 4 | AA27: 3 | AB27: 609037086 | AC27: Somehow better, displaying well,not too high, affordable | AD27: 0 | AE27: No | AG27: No | AI27: 1000000 | AJ27: Adding more products, shoes mobile money etc | AK27: Few competiters, strategically located | AL27: No | AN27: No | AP27: No | AR27: No | AT27: Advise and support from it | AU27: I heard the announcement from our k fm | AV27: 3 - Neutral | AW27: Some words were difficult to understand like affiliate | AX27: Yes | AZ27: I will be greatful when am I succeed, thanks | BT27: 609037086 | BU27: eaaa6dfe-8c52-4c0a-9c7f-edff396a0617 | BV27: 45979.803 | BY27: submitted_via_web | CA27: vCJgLk2yV8oivMfbcbCpCF | CC27: 804 | CF27: Stanbic Bank Incubator | CG27: Christine boutique, fashion and design | CH27: 609037086 | CI27: 1 | CJ27: Namata | CK27: Christine | CL27: 37004 | CN27: Female | CO27: 100 | CP27: Uganda | CQ27: No | CV27: Ugandan | CX27: Wakiso | CY27: KajjansiTown Council | CZ27: Nakawuka | DA27: Katwe | DB27: 704830249 | DC27: nampijjachrisviola@gmail.com | DD27: Yes | DE27: 10000 | DF27: IMG_20241002_152513_979-21_34_48.jpg | DG27: https://kf.kobotoolbox.org/api/v2/assets/a9dTHTe72X7zPceKxVtSxV/data/609037086/attachments/attzaTo5KiA2ivD3tP6mYf9x/ | DH27: 940 | DI27: 10X Digital Economy Expression of interest Form | DJ27: 804 | DK27: 609037086 | DL27: eaaa6dfe-8c52-4c0a-9c7f-edff396a0617 | DM27: 45979.803 | DP27: submitted_via_web | DR27: vCJgLk2yV8oivMfbcbCpCF | DT27: Stanbic Bank Incubator | DU27: Christine boutique, fashion and design | DV27: 609037086 | DW27: 1 | DX27: Namata | DY27: No | DZ27: Christine | EA27: 37004 | EB27: Female | EC27: Owner | ED27: 10000 | EE27: No | EG27: Ugandan | EI27: Wakiso | EJ27: Kajjansi Town Council | EK27: Nakawuka | EL27: Katwe | EM27: 769266841 | EO27: Certificate in high school | EP27: CF0105210YRTPC | ES27: 1474 | ET27: 10X Digital Economy Expression of interest Form | EU27: 804 | EV27: 609037086 | EW27: eaaa6dfe-8c52-4c0a-9c7f-edff396a0617 | EX27: 45979.803 | FA27: submitted_via_web | FC27: vCJgLk2yV8oivMfbcbCpCF | GK27: Unique | GL27: 24 | GM27: 24
A28: 0.036115741 | B28: 45980 | C28: Stanbic Bank Incubator | D28: SHOE STORE | E28: Shoes for kids,ladies and gentlemen. | F28: No | H28: No | L28: No | N28: Central | O28: Kampala | P28: Lubaga | Q28: Mutundwe | R28: fashion and design | T28: 1 | U28: 1 | V28: 1 | W28: 0 | X28: Shoes for kids, ladies and gentlemen in all sizes | Y28: Market | Z28: 1 | AA28: 1 | AB28: 630080264 | AC28: If I get a shoe on 7k ,I sell it on 10k-12k | AD28: 350000 | AE28: No | AG28: No | AI28: 6000000 | AJ28: Making my own shoe company | AK28: Because shoes don't expire | AL28: No | AN28: No | AP28: Yes | AQ28: Friend | AR28: No | AT28: My friend | AU28: It was more betterðŸ™ | AV28: 4 - Easy | AW28: Because I was expressing my self | AX28: Yes | AZ28: 10X is good because it has brought hope in me,thank you ðŸ™ | BT28: 630080264 | BU28: 0becafcf-e34d-4e43-98b8-fe8524194b8d | BV28: 46006.231 | BY28: submitted_via_web | CA28: vCJgLk2yV8oivMfbcbCpCF | CC28: 1788 | CF28: Stanbic Bank Incubator | CG28: SHOE STORE | CH28: 630080264 | CI28: 1 | CJ28: NANONNO | CK28: WINNIE PEACE | CL28: 38313 | CN28: Female | CO28: 80 | CP28: Ugandan | CQ28: No | CV28: Ugandan | CX28: Kampala | CY28: Lubaga | CZ28: Mutundwe | DA28: Mutundwe | DB28: 703095965 | DC28: nwinniepeace@gmail.com | DD28: Yes | DE28: 300000 | DF28: IMG_20251119_075755-8_1_58.jpg | DG28: https://kf.kobotoolbox.org/api/v2/assets/a9dTHTe72X7zPceKxVtSxV/data/630080264/attachments/att2ZwcUyRjAY7rcpU8BA2LK/ | DH28: 1987 | DI28: 10X Digital Economy Expression of interest Form | DJ28: 1788 | DK28: 630080264 | DL28: 0becafcf-e34d-4e43-98b8-fe8524194b8d | DM28: 46006.231 | DP28: submitted_via_web | DR28: vCJgLk2yV8oivMfbcbCpCF | DT28: Stanbic Bank Incubator | DU28: SHOE STORE | DV28: 630080264 | DW28: 1 | DX28: NANONNO WINNIE PEACE | DY28: Yes | EL28: Mutundwe | ES28: 2631 | ET28: 10X Digital Economy Expression of interest Form | EU28: 1788 | EV28: 630080264 | EW28: 0becafcf-e34d-4e43-98b8-fe8524194b8d | EX28: 46006.231 | FA28: submitted_via_web | FC28: vCJgLk2yV8oivMfbcbCpCF | GK28: Unique | GL28: 20 | GM28: 20
A29: 0.039068287 | B29: 45980 | C29: Stanbic Bank Incubator | D29: Bettina Cleaning company | E29: Cleaning services | F29: No | H29: No | L29: No | N29: North | O29: Wakiso | P29: Katabi | Q29: Entebbe division A | R29: Health | T29: 1 | U29: 1 | V29: 4 | W29: 0 | X29: House cleaning | Y29: Poverty | Z29: 2 | AA29: 5 | AB29: 609480286 | AC29: Agreement | AD29: 200000 | AE29: No | AG29: No | AI29: 2000000 | AJ29: Higher outputs | AK29: Demand of services | AL29: No | AN29: No | AP29: No | AR29: No | AT29: Good program | AU29: Friend | AV29: 2 - Difficult | AW29: Brief | AX29: Yes | AZ29: Consider me | BT29: 609480286 | BU29: 4a453db0-e690-4477-9358-0c07eb060a94 | BV29: 45980.421 | BY29: submitted_via_web | CA29: vCJgLk2yV8oivMfbcbCpCF | CC29: 814 | CF29: Stanbic Bank Incubator | CG29: Bettina Cleaning company | CH29: 609480286 | CI29: 1 | CJ29: Lunkuse | CK29: Betty | CL29: 36398 | CN29: Female | CO29: 10 | CP29: Ugandan | CQ29: Yes | CR29: Visual disability Intellectual disability Others | CS29: 1 | CT29: 0 | CU29: Sight | CV29: Ugandan | CX29: Wakiso | CY29: Katabi | CZ29: Katabi | DA29: Runyo | DB29: 758778592 | DC29: bettylunkuse66@gmail.com | DD29: Yes | DE29: 300000 | DF29: IMG_20250908_230753_635-12_18_38.jpg | DG29: https://kf.kobotoolbox.org/api/v2/assets/a9dTHTe72X7zPceKxVtSxV/data/609480286/attachments/attFcSpGVVpkUD5cyxEXGtEj/ | DH29: 950 | DI29: 10X Digital Economy Expression of interest Form | DJ29: 814 | DK29: 609480286 | DL29: 4a453db0-e690-4477-9358-0c07eb060a94 | DM29: 45980.421 | DP29: submitted_via_web | DR29: vCJgLk2yV8oivMfbcbCpCF | DT29: Stanbic Bank Incubator | DU29: Bettina Cleaning company | DV29: 609480286 | DW29: 4 | DX29: .Habiyaremye | DY29: No | DZ29: Michael | EA29: 28565 | EB29: Male | EC29: Accountant | ED29: 500000 | EE29: No | EG29: Ugandan | EI29: Kagadi | EJ29: Bwikara | EK29: Nyakarongo | EL29: Mabaale A | EM29: 759692379 | EO29: Bachelor | EP29: CM780181084MAE | ES29: 1487 | ET29: 10X Digital Economy Expression of interest Form | EU29: 814 | EV29: 609480286 | EW29: 4a453db0-e690-4477-9358-0c07eb060a94 | EX29: 45980.421 | FA29: submitted_via_web | FC29: vCJgLk2yV8oivMfbcbCpCF | GK29: Unique | GL29: 26 | GM29: 26
A30: 0.022724537 | B30: 45980 | C30: Stanbic Bank Incubator | D30: Ebenezer no no | E30: Meat | F30: No | H30: No | L30: No | N30: Central | O30: Wakiso | P30: Kasanje | Q30: Jungo | R30: Agriculture | T30: 1 | U30: 1 | V30: 1 | W30: 0 | X30: Sells piglets to those who need them and sells for consumption as well | Y30: Lacking money especially for those who have to pay school fees and other accesories | Z30: 2 | AA30: 4 | AB30: 609618679 | AC30: By selling off male piglets at 6 months so they don't take up space,at 1 month a piglet goes for 100,000 or 150000 | AD30: 0 | AE30: No | AG30: No | AI30: 2000000 | AJ30: To expand the house,so I can have more animals and employ more people so they can support themselves and their families | AK30: The population is high | AL30: No | AN30: No | AP30: No | AR30: No | AT30: To learn more about business | AU30: From friends and encourage me to attend | AV30: 2 - Difficult | AW30: Some questions were usually the ones asked in day today life while others needed thinking | AX30: Yes | AZ30: Thanks for thinking about us, the women and for encouraging us to be active | BT30: 609618679 | BU30: 9d52decd-0043-4aec-a307-c238d7e946a6 | BV30: 45980.517 | BY30: submitted_via_web | CA30: vCJgLk2yV8oivMfbcbCpCF | CC30: 819 | CF30: Stanbic Bank Incubator | CG30: Ebenezer no no | CH30: 609618679 | CI30: 1 | CJ30: Theopista | CK30: Kategano | CL30: 23324 | CN30: Female | CO30: 100 | CP30: Ugandan | CQ30: No | CV30: Ugandan | CX30: Wakiso | CY30: Kasanje | CZ30: Jungo | DA30: Sakabusolo | DB30: 700385612 | DC30: theopistakategano@gmail.com | DD30: Yes | DE30: 200000 | DF30: 1000021248-20_5_1.mp4 | DG30: https://kf.kobotoolbox.org/api/v2/assets/a9dTHTe72X7zPceKxVtSxV/data/609618679/attachments/attAtNpMMoskpgS8KewZZE8Q/ | DH30: 955 | DI30: 10X Digital Economy Expression of interest Form | DJ30: 819 | DK30: 609618679 | DL30: 9d52decd-0043-4aec-a307-c238d7e946a6 | DM30: 45980.517 | DP30: submitted_via_web | DR30: vCJgLk2yV8oivMfbcbCpCF | DT30: Stanbic Bank Incubator | DU30: Ebenezer no no | DV30: 609618679 | DW30: 1 | DX30: Elizabeth | DY30: No | DZ30: Nabuwufu | EA30: 32727 | EB30: Female | EC30: Marketier | ED30: 150000 | EE30: No | EG30: Ugandan | EI30: Wakiso | EJ30: Kasanje | EK30: Jungo | EL30: Sakabusolo | EM30: 787672202 | EN30: enabuwufu@gmail.com | EO30: University | EP30: CF890521021ZDG | ES30: 1492 | ET30: 10X Digital Economy Expression of interest Form | EU30: 819 | EV30: 609618679 | EW30: 9d52decd-0043-4aec-a307-c238d7e946a6 | EX30: 45980.517 | FA30: submitted_via_web | FC30: vCJgLk2yV8oivMfbcbCpCF | GK30: Unique | GL30: 0 | GM30: 62
A31: 0.038270833 | B31: 45981 | C31: Stanbic Bank Incubator | D31: Fresh squeeze juice | E31: I blend fresh,natural and organic juice from my home and do deliveries to customers | F31: No | H31: No | L31: No | N31: Central | O31: Kampala | P31: Kira Sub county | Q31: Bweyogerere | R31: Health | T31: 1 | U31: 1 | V31: 1 | W31: 0 | X31: Fresh, natural and organic juice from fresh fruits | Y31: Dehydration | Z31: 2 | AA31: 3 | AB31: 610021715 | AC31: I sell from my church mostly and I charge 10k per liter of juice | AD31: 0 | AE31: No | AG31: No | AI31: 26450000 | AJ31: Get dispensers, set up tables, platform where to place tables in case of a function, shop for my juice, workers to assist me, rent for the shop, packing and branding | AK31: Because it's promising since I get get customers more especially on Sunday and I can make over 200k on Sundays | AL31: No | AN31: No | AP31: No | AR31: No | AT31: Seeking for support for my business and I believe they can support me | AU31: From a friend who also applied | AV31: 5 - Very easy | AW31: I have a friend who benefited from this which made it easy for me to apply | AX31: Yes | AZ31: I love this experience. | BT31: 610021715 | BU31: 4076c394-eddf-4736-9e62-5d08caf91b8f | BV31: 45980.887 | BY31: submitted_via_web | CA31: vCJgLk2yV8oivMfbcbCpCF | CC31: 830 | CF31: Stanbic Bank Incubator | CG31: Fresh squeeze juice | CH31: 610021715 | CI31: 1 | CJ31: Tebahwura | CK31: Vanessa | CL31: 35838 | CN31: Female | CO31: 10 | CP31: Ugandan | CQ31: No | CV31: Ugandan | CX31: Kampala | CY31: Kira Sub county | CZ31: Bweyogerere | DA31: Ntebete | DB31: 706208325 | DC31: tebahwurav@gmail.com | DD31: Yes | DE31: 100000 | DH31: 968 | DI31: 10X Digital Economy Expression of interest Form | DJ31: 830 | DK31: 610021715 | DL31: 4076c394-eddf-4736-9e62-5d08caf91b8f | DM31: 45980.887 | DP31: submitted_via_web | DR31: vCJgLk2yV8oivMfbcbCpCF | DT31: Stanbic Bank Incubator | DU31: Fresh squeeze juice | DV31: 610021715 | DW31: 1 | DX31: Tebahwura | DY31: Yes | EL31: Ntebete | ES31: 1507 | ET31: 10X Digital Economy Expression of interest Form | EU31: 830 | EV31: 610021715 | EW31: 4076c394-eddf-4736-9e62-5d08caf91b8f | EX31: 45980.887 | FA31: submitted_via_web | FC31: vCJgLk2yV8oivMfbcbCpCF | GK31: Unique | GL31: 28 | GM31: 28
A32: 0.017074074 | B32: 45982 | C32: Stanbic Bank Incubator | D32: The grocery spot | E32: We deal in fruits sales and supplies with fresh food or local foods inclusive | F32: No | H32: No | L32: No | N32: Central | O32: Kampala | P32: Makindye | Q32: Salaama | R32: trade and services | T32: 1 | U32: 1 | V32: 1 | W32: 0 | X32: We deal in fresh fruits and fresh local food | Y32: Insufficient capital and registration of the business | Z32: 1 | AA32: 1 | AB32: 611008492 | AC32: I buy fruits from the market or from nearby villages and sell them on a cheaper price and have some profits to work again the next day | AD32: 0 | AE32: No | AG32: Yes | AH32: It was teaching about business skills and financial literacy that taught me more about business | AI32: 5000000 | AJ32: Business growth | AK32: Because am in places where the population is high and I have learnt about business registration that am going to put in practice | AL32: Yes | AM32: I want to also give out jobs to young people because I have learnt more in 10x | AN32: Yes | AO32: Teacher and student | AP32: Yes | AQ32: Teacher | AR32: No | AT32: Business support in growth | AU32: Kayaga Patricia | AV32: 5 - Very easy | AW32: Because they are all about business | AX32: Yes | AZ32: Easy, thanks | BT32: 611008492 | BU32: 8de4874e-57d3-4757-95c8-7d41d33c1406 | BV32: 45981.951 | BY32: submitted_via_web | CA32: vxMcj6EwHzj8L2STtGezta | CC32: 854 | CF32: Stanbic Bank Incubator | CG32: The grocery spot | CH32: 611008492 | CI32: 1 | CJ32: Namulindwa | CK32: Immaculate | CL32: 37219 | CN32: Female | CO32: 90 | CP32: Ugandan | CQ32: No | CV32: Ugandan | CX32: Kampala | CY32: Makindye | CZ32: Salaama | DA32: Kosovo | DB32: 755327667 | DC32: limdawazm@gmail.com | DD32: Yes | DE32: 200000 | DF32: IMG-20251114-WA0067-1_26_52.jpg | DG32: https://kf.kobotoolbox.org/api/v2/assets/a9dTHTe72X7zPceKxVtSxV/data/611008492/attachments/attiKzEFSS9d3xQjGN5hrD2N/ | DH32: 998 | DI32: 10X Digital Economy Expression of interest Form | DJ32: 854 | DK32: 611008492 | DL32: 8de4874e-57d3-4757-95c8-7d41d33c1406 | DM32: 45981.951 | DP32: submitted_via_web | DR32: vxMcj6EwHzj8L2STtGezta | DT32: Stanbic Bank Incubator | DU32: The grocery spot | DV32: 611008492 | DW32: 1 | DX32: Namulindwa | DY32: Yes | EL32: Kosovo | ES32: 1557 | ET32: 10X Digital Economy Expression of interest Form | EU32: 854 | EV32: 611008492 | EW32: 8de4874e-57d3-4757-95c8-7d41d33c1406 | EX32: 45981.951 | FA32: submitted_via_web | FC32: vxMcj6EwHzj8L2STtGezta | GK32: Unique | GL32: 24 | GM32: 24
A33: 0.034988426 | B33: 45982 | C33: Stanbic Bank Incubator | D33: Edith Fashions and Designs | E33: We make clothes designs of all types | F33: No | H33: No | L33: No | N33: Central | O33: Wakiso | P33: Nsangi | Q33: Kasenge ward | R33: fashion and design | T33: 1 | U33: 1 | V33: 1 | W33: 0 | X33: We deal in making designs of all types including cultural wear | Y33: Little capital and analogue machines | Z33: 1 | AA33: 1 | AB33: 611024565 | AC33: I get clothes from clients and repair them, also buy new cloth materials (bitengi ) and make clothes that attract customers to order for more. I get some limited profits and work is somehow difficult since I don't have good machines | AD33: 0 | AE33: No | AG33: Yes | AH33: I learnt business skills, Baguma Amos was our teacher | AI33: 3000000 | AJ33: Business growth | AK33: Because am good to register my business and expand it if I get financial support | AL33: Yes | AM33: I need financial assistance in my business to grow | AN33: Yes | AO33: Teacher to student | AP33: Yes | AQ33: Teacher | AR33: No | AT33: I wanted to know more on growing a business | AU33: Amodo Doreen | AV33: 4 - Easy | AW33: Business issues | AX33: Yes | AZ33: Easy | BT33: 611024565 | BU33: 1fb3b923-aa97-42e9-a91c-96b6a7242652 | BV33: 45981.992 | BY33: submitted_via_web | CA33: vxMcj6EwHzj8L2STtGezta | CC33: 855 | CF33: Stanbic Bank Incubator | CG33: Edith Fashions and Designs | CH33: 611024565 | CI33: 1 | CJ33: Muhoza | CK33: Edith | CL33: 33239 | CN33: Female | CO33: 95 | CP33: Ugandan | CQ33: No | CV33: Ugandan | CX33: Wakiso | CY33: Nsangi | CZ33: Kasenge | DA33: Kazinga | DB33: 755300295 | DC33: najembaritah8@gmail.com | DD33: Yes | DE33: 100000 | DF33: IMG-20251113-WA0061-2_38_34.jpg | DG33: https://kf.kobotoolbox.org/api/v2/assets/a9dTHTe72X7zPceKxVtSxV/data/611024565/attachments/attyRzrbwKMr8zSAPfCZmSzp/ | DH33: 999 | DI33: 10X Digital Economy Expression of interest Form | DJ33: 855 | DK33: 611024565 | DL33: 1fb3b923-aa97-42e9-a91c-96b6a7242652 | DM33: 45981.992 | DP33: submitted_via_web | DR33: vxMcj6EwHzj8L2STtGezta | DT33: Stanbic Bank Incubator | DU33: Edith Fashions and Designs | DV33: 611024565 | DW33: 1 | DX33: Muhoza | DY33: Yes | EL33: Kazinga | ES33: 1558 | ET33: 10X Digital Economy Expression of interest Form | EU33: 855 | EV33: 611024565 | EW33: 1fb3b923-aa97-42e9-a91c-96b6a7242652 | EX33: 45981.992 | FA33: submitted_via_web | FC33: vxMcj6EwHzj8L2STtGezta | GK33: Unique | GL33: 35 | GM33: 35
A34: 0.033730324 | B34: 45982 | C34: Stanbic Bank Incubator | D34: Madarakah Eats Bakery | E34: We produce all bakery products | F34: No | H34: Yes | L34: No | N34: Central | O34: Wakiso | P34: Nsangi | Q34: Kasenge ward | R34: Others | S34: Bakery | T34: 1 | U34: 1 | V34: 1 | W34: 0 | X34: We produce and provide cakes, daddies, Cookies bread and many bakery products | Y34: Working from home | Z34: 1 | AA34: 1 | AB34: 611031550 | AC34: I bake and fry snacks and earn income, and my costs are determined by the price of the materials I bought | AD34: 0 | AE34: No | AG34: Yes | AH34: I was taught by Mr. Bernard Muwanga | AI34: 3000000 | AJ34: Business success | AK34: Because I have learnt more about business in the 10x program | AL34: Yes | AM34: I want to register my business | AN34: No | AP34: Yes | AQ34: Teacher | AR34: No | AT34: I wanted to learn more about digital marketing skills | AU34: Amodo Doreen | AV34: 5 - Very easy | AW34: It was all about business issues | AX34: Yes | AZ34: Easy, thanks | BT34: 611031550 | BU34: 080350b7-2ffd-449c-badf-f4889e257cce | BV34: 45982.01 | BY34: submitted_via_web | CA34: vxMcj6EwHzj8L2STtGezta | CC34: 856 | CF34: Stanbic Bank Incubator | CG34: Madarakah Eats Bakery | CH34: 611031550 | CI34: 1 | CJ34: Namayanja | CK34: Jameo | CL34: 37391 | CN34: Female | CO34: 98 | CP34: Ugandan | CQ34: No | CV34: Ugandan | CX34: Wakiso | CY34: Nsangi | CZ34: Kasenge ward | DA34: Mugongo | DB34: 751477721 | DC34: jameoqariimmadarakah@gmail.com | DD34: Yes | DE34: 200000 | DH34: 1000 | DI34: 10X Digital Economy Expression of interest Form | DJ34: 856 | DK34: 611031550 | DL34: 080350b7-2ffd-449c-badf-f4889e257cce | DM34: 45982.01 | DP34: submitted_via_web | DR34: vxMcj6EwHzj8L2STtGezta | DT34: Stanbic Bank Incubator | DU34: Madarakah Eats Bakery | DV34: 611031550 | DW34: 1 | DX34: Namayanja | DY34: Yes | EL34: Mugongo | ES34: 1559 | ET34: 10X Digital Economy Expression of interest Form | EU34: 856 | EV34: 611031550 | EW34: 080350b7-2ffd-449c-badf-f4889e257cce | EX34: 45982.01 | FA34: submitted_via_web | FC34: vxMcj6EwHzj8L2STtGezta | GK34: Unique | GL34: 23 | GM34: 23
A35: 0.017400463 | B35: 45982 | C35: Stanbic Bank Incubator | D35: Psalms medical center | E35: Provides medical Care to patients | F35: No | H35: No | L35: No | N35: Central | O35: Wakiso | P35: Nsangi sub county | Q35: Kikajjo ward | R35: Health | T35: 1 | U35: 1 | V35: 1 | W35: 0 | X35: ,bed side nursing , simple lab test , medications | Y35: Improve on laboratory,add more drugs | Z35: 1 | AA35: 0 | AB35: 611228780 | AC35: It will work since it's a new business,sell drugs and treat patient inorder to get money,low costs | AD35: 0 | AE35: No | AG35: Yes | AH35: Mr.Baguuma Amos was running it, what I got I learnt to keep business record,to separate business money from my money,to use technology like my phone to market my business | AI35: 3000000 | AJ35: I want a microscope,I want to register my business,I want to add more drugs,to renovate my beds a | AK35: Yes I do | AL35: No | AN35: Yes | AO35: Teacher | AP35: Yes | AQ35: Teacher | AR35: No | AT35: Business development | AU35: Amodo Doreen | AV35: 4 - Easy | AW35: Easy because they wanted person information and what we learnt in the 10x program | AX35: Yes | AZ35: Good | BT35: 611228780 | BU35: 248d1c5b-d215-4613-878d-5ae991408113 | BV35: 45982.328 | BY35: submitted_via_web | CA35: vxMcj6EwHzj8L2STtGezta | CC35: 857 | CF35: Stanbic Bank Incubator | CG35: Psalms medical center | CH35: 611228780 | CI35: 1 | CJ35: Betty | CK35: Nabayemba | CL35: 36889 | CN35: Female | CO35: 50 | CP35: Ugandan | CQ35: No | CV35: Ugandan | CX35: Wakiso | CY35: Nsangi | CZ35: Kikajjo ward | DA35: Kasenge | DB35: 709551927 | DC35: musanyusabetty@gmail.com | DD35: Yes | DE35: 10000 | DF35: IMG_20250203_181620_063-15_12_57.jpg | DG35: https://kf.kobotoolbox.org/api/v2/assets/a9dTHTe72X7zPceKxVtSxV/data/611228780/attachments/attGHTUUctayWocfjPc2vYeL/ | DH35: 1001 | DI35: 10X Digital Economy Expression of interest Form | DJ35: 857 | DK35: 611228780 | DL35: 248d1c5b-d215-4613-878d-5ae991408113 | DM35: 45982.328 | DP35: submitted_via_web | DR35: vxMcj6EwHzj8L2STtGezta | DT35: Stanbic Bank Incubator | DU35: Psalms medical center | DV35: 611228780 | DW35: 1 | DX35: joan | DY35: No | DZ35: Ndibogeza | EA35: 36879 | EB35: Female | EC35: Lab technician | ED35: 150000 | EE35: No | EG35: Ugandan | EI35: Wakiso | EJ35: Nsangi | EK35: Kikajjo ward | EL35: Kaziga | EM35: 756299254 | EO35: Institute | ES35: 1560 | ET35: 10X Digital Economy Expression of interest Form | EU35: 857 | EV35: 611228780 | EW35: 248d1c5b-d215-4613-878d-5ae991408113 | EX35: 45982.328 | FA35: submitted_via_web | FC35: vxMcj6EwHzj8L2STtGezta | GK35: Unique | GL35: 0 | GM35: 25
A36: 0.010113426 | B36: 45982 | C36: Stanbic Bank Incubator | D36: Vicky Fashions and Beauty | E36: We deal in all cloth Fashions and makeup inclusive | F36: No | H36: No | L36: No | N36: Central | O36: Wakiso | P36: Nsangi | Q36: Kasenge ward | R36: fashion and design | T36: 1 | U36: 1 | V36: 1 | W36: 0 | X36: We deal in tailoring, making Fashions in all types plus makeup aside | Y36: Working from home | Z36: 1 | AA36: 1 | AB36: 611310436 | AC36: I have few customers since i work from home get little profits to push my business forward | AD36: 0 | AE36: No | AG36: Yes | AH36: It was about offering and teaching business skills that I learnt most and Baguma Amos was the teacher | AI36: 5000000 | AJ36: Business growth | AK36: Because am going to register my business such that I don't get difficulties in advertising to more customers | AL36: Yes | AM36: I want to register my business and also get financial support | AN36: No | AP36: Yes | AQ36: Teacher | AR36: No | AT36: I wanted to gain business knowledge and skills | AU36: Howard Muhwezi | AV36: 5 - Very easy | AW36: Because it was reflected on my business | AX36: Yes | AZ36: Easy | BT36: 611310436 | BU36: 8cb4642d-e84b-4789-8e47-368fd0570e6b | BV36: 45982.393 | BY36: submitted_via_web | CA36: vxMcj6EwHzj8L2STtGezta | CC36: 859 | CF36: Stanbic Bank Incubator | CG36: Vicky Fashions and Beauty | CH36: 611310436 | CI36: 1 | CJ36: Kagga | CK36: Vicky | CL36: 39324 | CN36: Female | CO36: 98 | CP36: Ugandan | CQ36: No | CV36: Ugandan | CX36: Wakiso | CY36: Nsangi | CZ36: Kasenge ward | DA36: Mugongo | DB36: 700581000 | DC36: vickykagga@gmail.com | DD36: Yes | DE36: 100000 | DH36: 1003 | DI36: 10X Digital Economy Expression of interest Form | DJ36: 859 | DK36: 611310436 | DL36: 8cb4642d-e84b-4789-8e47-368fd0570e6b | DM36: 45982.393 | DP36: submitted_via_web | DR36: vxMcj6EwHzj8L2STtGezta | DT36: Stanbic Bank Incubator | DU36: Vicky Fashions and Beauty | DV36: 611310436 | DW36: 1 | DX36: Kagga | DY36: Yes | EL36: Mugongo | ES36: 1562 | ET36: 10X Digital Economy Expression of interest Form | EU36: 859 | EV36: 611310436 | EW36: 8cb4642d-e84b-4789-8e47-368fd0570e6b | EX36: 45982.393 | FA36: submitted_via_web | FC36: vxMcj6EwHzj8L2STtGezta | GK36: Unique | GL36: 18 | GM36: 18
A37: 0.032302083 | B37: 45982 | C37: Stanbic Bank Incubator | D37: Rauyah cake bakery hi | E37: Provides cakes, cookies, cupcakes etc | F37: No | H37: No | L37: No | N37: Central | O37: Wakiso | P37: Kyengera town council | Q37: Kasenge ward | R37: trade and services | T37: 1 | U37: 1 | V37: 1 | W37: 1 | X37: Cakes, cupcakes, daddies, cookies etc | Y37: Getting materials like oven, stand mixer and rent | Z37: 1 | AA37: 0 | AB37: 611373694 | AC37: Work on orders and supply cupcakes and daddies on shops, I charge according to someone's order and choice and how much I put in for that product I supply on shops | AD37: 0 | AE37: No | AG37: No | AI37: 2000000 | AJ37: Operating a big bakery employing peaple | AK37: I advertise and I make good products | AL37: Yes | AM37: So far I'm working from home but I would like to rent a shop make a clear display | AN37: No | AP37: No | AR37: No | AT37: They taught about entrepreneurship skills that in business growth and that inspired me to join | AU37: Through announcement at chairman's places | AV37: 3 - Neutral | AW37: Some questions were difficult to answer | AX37: Yes | AZ37: Thank you so much | BT37: 611373694 | BU37: b25bee19-2e17-4e36-b3b6-493befd473c0 | BV37: 45982.443 | BY37: submitted_via_web | CA37: vxMcj6EwHzj8L2STtGezta | CC37: 860 | CF37: Stanbic Bank Incubator | CG37: Rauyah cake bakery hi | CH37: 611373694 | CI37: 1 | CJ37: Nakanwagi | CK37: Rauyah | CL37: 37544 | CN37: Female | CO37: 60 | CP37: Ugandan | CQ37: No | CV37: Ugandan | CX37: Wakiso | CY37: Kyengera town council | CZ37: Kasenge ward | DA37: Kinaawa | DB37: 743861721 | DC37: rauyahisa5@gmail.com | DD37: No | DF37: IMG_20251003_073303-12_15_29.jpg | DG37: https://kf.kobotoolbox.org/api/v2/assets/a9dTHTe72X7zPceKxVtSxV/data/611373694/attachments/attWKNmepeunbHzy7t7KgLdH/ | DH37: 1004 | DI37: 10X Digital Economy Expression of interest Form | DJ37: 860 | DK37: 611373694 | DL37: b25bee19-2e17-4e36-b3b6-493befd473c0 | DM37: 45982.443 | DP37: submitted_via_web | DR37: vxMcj6EwHzj8L2STtGezta | DT37: Stanbic Bank Incubator | DU37: Rauyah cake bakery hi | DV37: 611373694 | DW37: 1 | DX37: Nakanwagi Rauyah | DY37: Yes | EL37: Kinaawa | ES37: 1563 | ET37: 10X Digital Economy Expression of interest Form | EU37: 860 | EV37: 611373694 | EW37: b25bee19-2e17-4e36-b3b6-493befd473c0 | EX37: 45982.443 | FA37: submitted_via_web | FC37: vxMcj6EwHzj8L2STtGezta | FE37: Stanbic Bank Incubator | FF37: Rauyah cake bakery hi | FG37: 611373694 | FH37: 1 | FI37: Nakanwagi | FJ37: Rauyah | FK37: 37544 | FL37: Female | FM37: Baking | FN37: 50000 | FO37: No | FQ37: Ugandan | FS37: Wakiso | FT37: Kyengera town council | FU37: Kasenge | FV37: Kinaawa | FW37: 743861721 | FX37: rauyahisa5@gmail.com | FY37: CF02045105VX7G | FZ37: 522 | GA37: 10X Digital Economy Expression of interest Form | GB37: 860 | GC37: 611373694 | GD37: b25bee19-2e17-4e36-b3b6-493befd473c0 | GE37: 45982.443 | GH37: submitted_via_web | GJ37: vxMcj6EwHzj8L2STtGezta | GK37: Unique | GL37: 23 | GM37: 23
A38: 0.018265046 | B38: 45982 | C38: Stanbic Bank Incubator | D38: Rise Bakery | E38: We dealing cakes and all the color products | F38: No | H38: No | L38: No | N38: Central | O38: Wakiso | P38: Nsangi | Q38: Kasenge | R38: Others | S38: Bakery | T38: 1 | U38: 1 | V38: 1 | W38: 0 | X38: We doing cakes that is cookies bread and buns and so many other products | Y38: I want to have a place of work away from home | Z38: 1 | AA38: 1 | AB38: 611434707 | AC38: I bake and fry snacks put them on retail shop and earn income | AD38: 0 | AE38: No | AG38: Yes | AH38: It was all about business skills and financial literacy | AI38: 5000000 | AJ38: Business growth and success | AK38: Because am in an area where my products are on a higher demand | AL38: Yes | AM38: I want to register my business and also expand it | AN38: No | AP38: Yes | AQ38: Teacher | AR38: No | AT38: I wanted to learn more about digital marketing | AU38: Nakiryowa Esther | AV38: 5 - Very easy | AW38: Business issues | AX38: Yes | AZ38: Easy | BT38: 611434707 | BU38: 233f3a48-7d25-489c-abf0-b57e872418a6 | BV38: 45982.489 | BY38: submitted_via_web | CA38: vxMcj6EwHzj8L2STtGezta | CC38: 861 | CF38: Stanbic Bank Incubator | CG38: Rise Bakery | CH38: 611434707 | CI38: 1 | CJ38: Najjuko | CK38: Aisha | CL38: 37847 | CN38: Female | CO38: 98 | CP38: Ugandan | CQ38: No | CV38: Ugandan | CX38: Wakiso | CY38: Nsangi | CZ38: Kasenge ward | DA38: Kasenge ward | DB38: 771465046 | DC38: aishanajjuko09@gmail.com | DD38: Yes | DE38: 100000 | DH38: 1005 | DI38: 10X Digital Economy Expression of interest Form | DJ38: 861 | DK38: 611434707 | DL38: 233f3a48-7d25-489c-abf0-b57e872418a6 | DM38: 45982.489 | DP38: submitted_via_web | DR38: vxMcj6EwHzj8L2STtGezta | DT38: Stanbic Bank Incubator | DU38: Rise Bakery | DV38: 611434707 | DW38: 1 | DX38: Najjuko | DY38: Yes | EL38: Nabaziza | ES38: 1564 | ET38: 10X Digital Economy Expression of interest Form | EU38: 861 | EV38: 611434707 | EW38: 233f3a48-7d25-489c-abf0-b57e872418a6 | EX38: 45982.489 | FA38: submitted_via_web | FC38: vxMcj6EwHzj8L2STtGezta | GK38: Unique | GL38: 22 | GM38: 22
A39: 0.039627315 | B39: 45983 | C39: Stanbic Bank Incubator | D39: Fashion en design | E39: Fashion | F39: No | H39: No | L39: No | N39: Central | O39: Wakiso | P39: Nsangi | Q39: Kikkajjo | R39: fashion and design | T39: 1 | U39: 1 | V39: 2 | W39: 1 | X39: Hair dressings | Y39: Buaty | Z39: 2 | AA39: 4 | AB39: 612264356 | AC39: I axchange my skills | AD39: 50000 | AE39: Yes | AF39: 1 | AG39: No | AI39: 1000000 | AJ39: Business woman | AK39: Couse am confident | AL39: No | AN39: No | AP39: No | AR39: No | AT39: I wanted to try my chances | AU39: Friend | AV39: 4 - Easy | AW39: Couse there under business | AX39: Yes | AZ39: I will be happy if u help me with my business to be successful | BT39: 612264356 | BU39: 78425186-fba5-456e-9d49-c455203befe8 | BV39: 45983.519 | BY39: submitted_via_web | CA39: vxMcj6EwHzj8L2STtGezta | CC39: 881 | CF39: Stanbic Bank Incubator | CG39: Fashion en design | CH39: 612264356 | CI39: 1 | CJ39: Nalukenge | CK39: Gladys | CL39: 38835 | CN39: Female | CO39: 100 | CP39: Ugandan | CQ39: No | CV39: Ugandan | CX39: Wakiso | CY39: Nsangi | CZ39: Kikkajjo | DA39: Katale | DB39: 747715389 | DC39: nalukengegladys42@gmail.com | DD39: Yes | DE39: 500000 | DH39: 1027 | DI39: 10X Digital Economy Expression of interest Form | DJ39: 881 | DK39: 612264356 | DL39: 78425186-fba5-456e-9d49-c455203befe8 | DM39: 45983.519 | DP39: submitted_via_web | DR39: vxMcj6EwHzj8L2STtGezta | DT39: Stanbic Bank Incubator | DU39: Fashion en design | DV39: 612264356 | DW39: 2 | DX39: Nalukenge | DY39: Yes | EL39: Katale | ES39: 1590 | ET39: 10X Digital Economy Expression of interest Form | EU39: 881 | EV39: 612264356 | EW39: 78425186-fba5-456e-9d49-c455203befe8 | EX39: 45983.519 | FA39: submitted_via_web | FC39: vxMcj6EwHzj8L2STtGezta | FE39: Stanbic Bank Incubator | FF39: Fashion en design | FG39: 612264356 | FH39: 1 | FI39: Silivia | FJ39: Nabawanuka | FK39: 38958 | FL39: Female | FM39: Employee | FN39: 150000 | FO39: No | FQ39: Ugandan | FS39: Wakiso | FT39: Nsangi | FU39: Kikkajjo | FV39: Katale | FW39: 702424633 | FX39: nalukengegladys42@gmail.com | FZ39: 530 | GA39: 10X Digital Economy Expression of interest Form | GB39: 881 | GC39: 612264356 | GD39: 78425186-fba5-456e-9d49-c455203befe8 | GE39: 45983.519 | GH39: submitted_via_web | GJ39: vxMcj6EwHzj8L2STtGezta | GK39: Unique | GL39: 19 | GM39: 19
A40: 0.01843287 | B40: 45985 | C40: Stanbic Bank Incubator | D40: Tailoring | E40: School uniforms | F40: No | H40: No | L40: No | N40: Central | O40: Wakiso | P40: Kyengera | Q40: Kasenge | R40: trade and services | T40: 1 | U40: 1 | V40: 1 | W40: 0 | X40: Mainly school uniforms and repairs rarely | Y40: Enough Capital | Z40: 1 | AA40: 1 | AB40: 613133711 | AC40: I make school uniforms, it is the school to provide material, I charge 5k for each wether a shirt, dress, or short | AD40: 120000 | AE40: No | AG40: No | AI40: 1000000 | AJ40: Hiring the first employee and buying my own material | AK40: Good products and good time management | AL40: No | AN40: No | AP40: No | AR40: No | AT40: Ii had hope that I would be assisted to make my business grow better | AU40: From a friend that we had done the same course of tailoring | AV40: 3 - Neutral | AW40: I am always looking forward to something that would make my business stand out so I don't take negativity as an option but still I don't hope so much because anything is possible | AX40: Yes | AZ40: It has been a great pleasure to express myself on this tool and I hope for better from this programme. Thank you prog | BT40: 613133711 | BU40: ecf08a45-2966-406e-8685-bf842d91e7cc | BV40: 45984.935 | BY40: submitted_via_web | CA40: vxMcj6EwHzj8L2STtGezta | CC40: 890 | CF40: Stanbic Bank Incubator | CG40: Tailoring | CH40: 613133711 | CI40: 1 | CJ40: Sharon | CK40: Zalwango | CL40: 38904 | CN40: Female | CO40: 100 | CP40: Ugandan | CQ40: No | CV40: Ugandan | CX40: Wakiso | CY40: Kyengera | CZ40: Kasenge | DA40: Bandwe | DB40: 702376193 | DC40: shamimaddie@gmail.com | DD40: Yes | DE40: 100000 | DF40: 20251115_162851-0_32_15.jpg | DG40: https://kf.kobotoolbox.org/api/v2/assets/a9dTHTe72X7zPceKxVtSxV/data/613133711/attachments/attpw8JQVtRxAZmX3RQTvkNr/ | DH40: 1039 | DI40: 10X Digital Economy Expression of interest Form | DJ40: 890 | DK40: 613133711 | DL40: ecf08a45-2966-406e-8685-bf842d91e7cc | DM40: 45984.935 | DP40: submitted_via_web | DR40: vxMcj6EwHzj8L2STtGezta | DT40: Stanbic Bank Incubator | DU40: Tailoring | DV40: 613133711 | DW40: 1 | DX40: Sharon | DY40: Yes | EL40: Bandwe | ES40: 1613 | ET40: 10X Digital Economy Expression of interest Form | EU40: 890 | EV40: 613133711 | EW40: ecf08a45-2966-406e-8685-bf842d91e7cc | EX40: 45984.935 | FA40: submitted_via_web | FC40: vxMcj6EwHzj8L2STtGezta | GK40: Unique | GL40: 19 | GM40: 19
A41: 0.0013402778 | B41: 45985 | C41: Stanbic Bank Incubator | D41: Mobile money | E41: Money | F41: No | H41: No | L41: No | N41: Central | O41: Kampala | P41: Kampala | Q41: Rubaga | R41: trade and services | T41: 1 | U41: 1 | V41: 2 | W41: 2 | X41: Money airtime | Y41: Lack of capital and customers | Z41: 10 | AA41: 1 | AB41: 613577292 | AC41: By sending money to them | AD41: 100000 | AE41: No | AG41: Yes | AH41: It helped us in business training | AI41: 1000000 | AJ41: More customers and increase in the business | AK41: I have learnt alot from Stanbic business incubator alot which will help me to continue my business | AL41: No | AN41: No | AP41: Yes | AQ41: Our business tutors | AR41: Yes | AT41: I want to learn how to manage a business we're by i hard no experience | AU41: Nakandi peninah | AV41: 4 - Easy | AW41: Some who tricky | AX41: Yes | AZ41: The formal wasn't very easy | BT41: 613577292 | BU41: dfe8ff98-26aa-441f-a1d3-d64b0e82eb23 | BV41: 45985.467 | BY41: submitted_via_web | CA41: vxMcj6EwHzj8L2STtGezta | CC41: 899 | CF41: Stanbic Bank Incubator | CG41: Mobile money | CH41: 613577292 | CI41: 1 | CJ41: Bwabale | CK41: Joshua | CL41: 34335 | CN41: Male | CO41: 100 | CP41: Ugandan | CQ41: No | CV41: Ugandan | CX41: Kampala | CY41: Kampala | CZ41: Rubaga | DA41: Rubaga | DB41: 753673736 | DC41: safinahnagawa56@gmail.com | DD41: Yes | DE41: 100000 | DH41: 1048 | DI41: 10X Digital Economy Expression of interest Form | DJ41: 899 | DK41: 613577292 | DL41: dfe8ff98-26aa-441f-a1d3-d64b0e82eb23 | DM41: 45985.467 | DP41: submitted_via_web | DR41: vxMcj6EwHzj8L2STtGezta | DT41: Stanbic Bank Incubator | DU41: Mobile money | DV41: 613577292 | DW41: 1 | DX41: NAGAWA SAFINAH | DY41: No | DZ41: Safinah | EA41: 37036 | EB41: Female | EC41: Staff | ED41: 100000 | EE41: No | EG41: Ugandan | EI41: Kampala | EJ41: Kampala | EK41: Rubaga | EL41: Rubaga | EM41: 753673736 | EN41: safinahnagawa56@gmail.com | EO41: Degree | EP41: CF01012107M6XH | ES41: 1634 | ET41: 10X Digital Economy Expression of interest Form | EU41: 899 | EV41: 613577292 | EW41: dfe8ff98-26aa-441f-a1d3-d64b0e82eb23 | EX41: 45985.467 | FA41: submitted_via_web | FC41: vxMcj6EwHzj8L2STtGezta | FE41: Stanbic Bank Incubator | FF41: Mobile money | FG41: 613577292 | FH41: 1 | FI41: NAGAWA | FJ41: Safinah | FK41: 37036 | FL41: Female | FM41: Staff | FN41: 100000 | FO41: No | FQ41: Ugandan | FS41: Kampala | FT41: Kampala | FU41: Rubaga | FV41: Rubaga | FW41: 753673736 | FX41: safinahnagawa56@gmail.com | FY41: CF01012107M6XH | FZ41: 541 | GA41: 10X Digital Economy Expression of interest Form | GB41: 899 | GC41: 613577292 | GD41: dfe8ff98-26aa-441f-a1d3-d64b0e82eb23 | GE41: 45985.467 | GH41: submitted_via_web | GJ41: vxMcj6EwHzj8L2STtGezta | GK41: Unique | GL41: 24 | GM41: 24
A42: 0.0013402778 | B42: 45985 | C42: Stanbic Bank Incubator | D42: Mobile money | E42: Money | F42: No | H42: No | L42: No | N42: Central | O42: Kampala | P42: Kampala | Q42: Rubaga | R42: trade and services | T42: 1 | U42: 1 | V42: 2 | W42: 2 | X42: Money airtime | Y42: Lack of capital and customers | Z42: 10 | AA42: 1 | AB42: 613577292 | AC42: By sending money to them | AD42: 100000 | AE42: No | AG42: Yes | AH42: It helped us in business training | AI42: 1000000 | AJ42: More customers and increase in the business | AK42: I have learnt alot from Stanbic business incubator alot which will help me to continue my business | AL42: No | AN42: No | AP42: Yes | AQ42: Our business tutors | AR42: Yes | AT42: I want to learn how to manage a business we're by i hard no experience | AU42: Nakandi peninah | AV42: 4 - Easy | AW42: Some who tricky | AX42: Yes | AZ42: The formal wasn't very easy | BT42: 613577292 | BU42: dfe8ff98-26aa-441f-a1d3-d64b0e82eb23 | BV42: 45985.467 | BY42: submitted_via_web | CA42: vxMcj6EwHzj8L2STtGezta | CC42: 899 | CF42: Stanbic Bank Incubator | CG42: Mobile money | CH42: 613577292 | CI42: 1 | CJ42: Bwabale | CK42: Joshua | CL42: 34335 | CN42: Male | CO42: 100 | CP42: Ugandan | CQ42: No | CV42: Ugandan | CX42: Kampala | CY42: Kampala | CZ42: Rubaga | DA42: Rubaga | DB42: 753673736 | DC42: safinahnagawa56@gmail.com | DD42: Yes | DE42: 100000 | DH42: 1048 | DI42: 10X Digital Economy Expression of interest Form | DJ42: 899 | DK42: 613577292 | DL42: dfe8ff98-26aa-441f-a1d3-d64b0e82eb23 | DM42: 45985.467 | DP42: submitted_via_web | DR42: vxMcj6EwHzj8L2STtGezta | DT42: Stanbic Bank Incubator | DU42: Mobile money | DV42: 613577292 | DW42: 1 | DX42: NAGAWA SAFINAH | DY42: No | DZ42: Safinah | EA42: 37036 | EB42: Female | EC42: Staff | ED42: 100000 | EE42: No | EG42: Ugandan | EI42: Kampala | EJ42: Kampala | EK42: Rubaga | EL42: Rubaga | EM42: 753673736 | EN42: safinahnagawa56@gmail.com | EO42: Degree | EP42: CF01012107M6XH | ES42: 1634 | ET42: 10X Digital Economy Expression of interest Form | EU42: 899 | EV42: 613577292 | EW42: dfe8ff98-26aa-441f-a1d3-d64b0e82eb23 | EX42: 45985.467 | FA42: submitted_via_web | FC42: vxMcj6EwHzj8L2STtGezta | FE42: Stanbic Bank Incubator | FF42: Mobile money | FG42: 613577292 | FH42: 2 | FI42: NAGAWA | FJ42: Safinah | FK42: 37036 | FL42: Female | FM42: Staff | FN42: 100000 | FO42: No | FQ42: Ugandan | FS42: Kampala | FT42: Kampala | FU42: Rubaga | FV42: Rubaga | FW42: 753673736 | FX42: safinahnagawa56@gmail.com | FY42: CF01012107M6XH | FZ42: 542 | GA42: 10X Digital Economy Expression of interest Form | GB42: 899 | GC42: 613577292 | GD42: dfe8ff98-26aa-441f-a1d3-d64b0e82eb23 | GE42: 45985.467 | GH42: submitted_via_web | GJ42: vxMcj6EwHzj8L2STtGezta | GK42: Unique | GL42: 24 | GM42: 24
A43: 0.0013402778 | B43: 45985 | C43: Stanbic Bank Incubator | D43: Mobile money | E43: Money | F43: No | H43: No | L43: No | N43: Central | O43: Kampala | P43: Kampala | Q43: Rubaga | R43: trade and services | T43: 1 | U43: 1 | V43: 2 | W43: 2 | X43: Money airtime | Y43: Lack of capital and customers | Z43: 10 | AA43: 1 | AB43: 613577292 | AC43: By sending money to them | AD43: 100000 | AE43: No | AG43: Yes | AH43: It helped us in business training | AI43: 1000000 | AJ43: More customers and increase in the business | AK43: I have learnt alot from Stanbic business incubator alot which will help me to continue my business | AL43: No | AN43: No | AP43: Yes | AQ43: Our business tutors | AR43: Yes | AT43: I want to learn how to manage a business we're by i hard no experience | AU43: Nakandi peninah | AV43: 4 - Easy | AW43: Some who tricky | AX43: Yes | AZ43: The formal wasn't very easy | BT43: 613577292 | BU43: dfe8ff98-26aa-441f-a1d3-d64b0e82eb23 | BV43: 45985.467 | BY43: submitted_via_web | CA43: vxMcj6EwHzj8L2STtGezta | CC43: 899 | CF43: Stanbic Bank Incubator | CG43: Mobile money | CH43: 613577292 | CI43: 1 | CJ43: Bwabale | CK43: Joshua | CL43: 34335 | CN43: Male | CO43: 100 | CP43: Ugandan | CQ43: No | CV43: Ugandan | CX43: Kampala | CY43: Kampala | CZ43: Rubaga | DA43: Rubaga | DB43: 753673736 | DC43: safinahnagawa56@gmail.com | DD43: Yes | DE43: 100000 | DH43: 1048 | DI43: 10X Digital Economy Expression of interest Form | DJ43: 899 | DK43: 613577292 | DL43: dfe8ff98-26aa-441f-a1d3-d64b0e82eb23 | DM43: 45985.467 | DP43: submitted_via_web | DR43: vxMcj6EwHzj8L2STtGezta | DT43: Stanbic Bank Incubator | DU43: Mobile money | DV43: 613577292 | DW43: 2 | DX43: NAGAWA SAFINAH | DY43: No | DZ43: Safinah | EA43: 37036 | EB43: Female | EC43: Staff | ED43: 100000 | EE43: No | EG43: Ugandan | EI43: Kampala | EJ43: Kampala | EK43: Rubaga | EL43: Rubaga | EM43: 753673736 | EN43: safinahnagawa56@gmail.com | EO43: Degree | EP43: CF01012107M6XH | ES43: 1635 | ET43: 10X Digital Economy Expression of interest Form | EU43: 899 | EV43: 613577292 | EW43: dfe8ff98-26aa-441f-a1d3-d64b0e82eb23 | EX43: 45985.467 | FA43: submitted_via_web | FC43: vxMcj6EwHzj8L2STtGezta | FE43: Stanbic Bank Incubator | FF43: Mobile money | FG43: 613577292 | FH43: 1 | FI43: NAGAWA | FJ43: Safinah | FK43: 37036 | FL43: Female | FM43: Staff | FN43: 100000 | FO43: No | FQ43: Ugandan | FS43: Kampala | FT43: Kampala | FU43: Rubaga | FV43: Rubaga | FW43: 753673736 | FX43: safinahnagawa56@gmail.com | FY43: CF01012107M6XH | FZ43: 541 | GA43: 10X Digital Economy Expression of interest Form | GB43: 899 | GC43: 613577292 | GD43: dfe8ff98-26aa-441f-a1d3-d64b0e82eb23 | GE43: 45985.467 | GH43: submitted_via_web | GJ43: vxMcj6EwHzj8L2STtGezta | GK43: Unique | GL43: 24 | GM43: 24
A44: 0.0013402778 | B44: 45985 | C44: Stanbic Bank Incubator | D44: Mobile money | E44: Money | F44: No | H44: No | L44: No | N44: Central | O44: Kampala | P44: Kampala | Q44: Rubaga | R44: trade and services | T44: 1 | U44: 1 | V44: 2 | W44: 2 | X44: Money airtime | Y44: Lack of capital and customers | Z44: 10 | AA44: 1 | AB44: 613577292 | AC44: By sending money to them | AD44: 100000 | AE44: No | AG44: Yes | AH44: It helped us in business training | AI44: 1000000 | AJ44: More customers and increase in the business | AK44: I have learnt alot from Stanbic business incubator alot which will help me to continue my business | AL44: No | AN44: No | AP44: Yes | AQ44: Our business tutors | AR44: Yes | AT44: I want to learn how to manage a business we're by i hard no experience | AU44: Nakandi peninah | AV44: 4 - Easy | AW44: Some who tricky | AX44: Yes | AZ44: The formal wasn't very easy | BT44: 613577292 | BU44: dfe8ff98-26aa-441f-a1d3-d64b0e82eb23 | BV44: 45985.467 | BY44: submitted_via_web | CA44: vxMcj6EwHzj8L2STtGezta | CC44: 899 | CF44: Stanbic Bank Incubator | CG44: Mobile money | CH44: 613577292 | CI44: 1 | CJ44: Bwabale | CK44: Joshua | CL44: 34335 | CN44: Male | CO44: 100 | CP44: Ugandan | CQ44: No | CV44: Ugandan | CX44: Kampala | CY44: Kampala | CZ44: Rubaga | DA44: Rubaga | DB44: 753673736 | DC44: safinahnagawa56@gmail.com | DD44: Yes | DE44: 100000 | DH44: 1048 | DI44: 10X Digital Economy Expression of interest Form | DJ44: 899 | DK44: 613577292 | DL44: dfe8ff98-26aa-441f-a1d3-d64b0e82eb23 | DM44: 45985.467 | DP44: submitted_via_web | DR44: vxMcj6EwHzj8L2STtGezta | DT44: Stanbic Bank Incubator | DU44: Mobile money | DV44: 613577292 | DW44: 2 | DX44: NAGAWA SAFINAH | DY44: No | DZ44: Safinah | EA44: 37036 | EB44: Female | EC44: Staff | ED44: 100000 | EE44: No | EG44: Ugandan | EI44: Kampala | EJ44: Kampala | EK44: Rubaga | EL44: Rubaga | EM44: 753673736 | EN44: safinahnagawa56@gmail.com | EO44: Degree | EP44: CF01012107M6XH | ES44: 1635 | ET44: 10X Digital Economy Expression of interest Form | EU44: 899 | EV44: 613577292 | EW44: dfe8ff98-26aa-441f-a1d3-d64b0e82eb23 | EX44: 45985.467 | FA44: submitted_via_web | FC44: vxMcj6EwHzj8L2STtGezta | FE44: Stanbic Bank Incubator | FF44: Mobile money | FG44: 613577292 | FH44: 2 | FI44: NAGAWA | FJ44: Safinah | FK44: 37036 | FL44: Female | FM44: Staff | FN44: 100000 | FO44: No | FQ44: Ugandan | FS44: Kampala | FT44: Kampala | FU44: Rubaga | FV44: Rubaga | FW44: 753673736 | FX44: safinahnagawa56@gmail.com | FY44: CF01012107M6XH | FZ44: 542 | GA44: 10X Digital Economy Expression of interest Form | GB44: 899 | GC44: 613577292 | GD44: dfe8ff98-26aa-441f-a1d3-d64b0e82eb23 | GE44: 45985.467 | GH44: submitted_via_web | GJ44: vxMcj6EwHzj8L2STtGezta | GK44: Unique | GL44: 24 | GM44: 24
A45: 0.0090439815 | B45: 45985 | C45: Stanbic Bank Incubator | D45: Dei-gratia Fashions | E45: Ladies' clothes like skirts, blouses, trousers | F45: No | H45: No | L45: Yes | N45: Central | O45: Wakiso | P45: Division A | Q45: Central | R45: fashion and design | T45: 1 | U45: 1 | V45: 1 | W45: 0 | X45: Ladies' skirts, blouses, trousers | Y45: Unemployment | Z45: 3 | AA45: 3 | AB45: 613993912 | AC45: Pricing abit higher than the original price I bought | AD45: 0 | AE45: No | AG45: No | AI45: 5000000 | AJ45: Opening up other branches | AK45: I have received knowledge needed from the 10x program | AL45: No | AN45: No | AP45: No | AR45: No | AT45: More knowledge of expanding and employing more people | AU45: From Nakandi Peninah | AV45: 5 - Very easy | AW45: Information is plainly provided and aligns with my business ideas | AX45: Yes | AZ45: Thank you so much for the opportunity | BT45: 613993912 | BU45: 2fd3f244-1f78-4eb9-9896-9c7b74108231 | BV45: 45985.793 | BY45: submitted_via_web | CA45: vxMcj6EwHzj8L2STtGezta | CC45: 907 | CF45: Stanbic Bank Incubator | CG45: Dei-gratia Fashions | CH45: 613993912 | CI45: 1 | CJ45: Esther Catherine | CK45: Kemigisa | CL45: 35171 | CN45: Female | CO45: 100 | CP45: Ugandan | CQ45: Yes | CR45: Visual disability | CS45: 1 | CT45: 0 | CV45: Ugandan | CX45: Wakiso | CY45: Division A | CZ45: Central | DA45: Post Office | DB45: 704379339 | DC45: kemigisaesther8@gmail.com | DD45: Yes | DE45: 150000 | DF45: IMG-20250726-WA0000-21_43_41.jpeg | DG45: https://kf.kobotoolbox.org/api/v2/assets/a9dTHTe72X7zPceKxVtSxV/data/613993912/attachments/attkNzRetMK3yqKdB3HR4JLm/ | DH45: 1057 | DI45: 10X Digital Economy Expression of interest Form | DJ45: 907 | DK45: 613993912 | DL45: 2fd3f244-1f78-4eb9-9896-9c7b74108231 | DM45: 45985.793 | DP45: submitted_via_web | DR45: vxMcj6EwHzj8L2STtGezta | DT45: Stanbic Bank Incubator | DU45: Dei-gratia Fashions | DV45: 613993912 | DW45: 1 | DX45: Dorothy | DY45: No | DZ45: Birungi | EA45: 35639 | EB45: Female | EC45: Member | ED45: 100000 | EE45: Yes | EG45: Ugandan | EI45: Wakiso | EJ45: Division A | EK45: Central | EL45: Post Office | EM45: 782501242 | EN45: dorothybirungi7@gmail.com | EO45: UCE certificate | EP45: CF970481077QUH | ES45: 1644 | ET45: 10X Digital Economy Expression of interest Form | EU45: 907 | EV45: 613993912 | EW45: 2fd3f244-1f78-4eb9-9896-9c7b74108231 | EX45: 45985.793 | FA45: submitted_via_web | FC45: vxMcj6EwHzj8L2STtGezta | GK45: Unique | GL45: 29 | GM45: 29
A46: 0.024759259 | B46: 45986 | C46: Stanbic Bank Incubator | D46: Ming Ming cakes and pastries | E46: We provide fast foods and bakery products | F46: No | H46: No | L46: No | N46: Central | O46: Wakiso | P46: Busiro East | Q46: Sumbwe | R46: Others | S46: Bakery | T46: 1 | U46: 1 | V46: 1 | W46: 0 | X46: We deal in all kinds of pastries and bakery products eg bread, cakes, daddies, Cookies and many others | Y46: Insufficient capital | Z46: 1 | AA46: 1 | AB46: 614105945 | AC46: I bake fast foods and bakery products where by I sell them on orders and make profits | AD46: 0 | AE46: No | AG46: Yes | AH46: I was about business knowledge and skills for success and Baguma Amos was the teacher that made a great impact in my business | AI46: 3000000 | AJ46: Business growth | AK46: Because am in an area that is still growing and has a high demand for my products | AL46: Yes | AM46: I need modern or digital machines to run my business smoothly and profitable | AN46: No | AP46: Yes | AQ46: Teacher and student | AR46: No | AT46: I want to know about business skills and financial knowledge in the digital system | AU46: Amodo Doreen | AV46: 4 - Easy | AW46: It was all about business skills and financial literacy | AX46: Yes | AZ46: Easy | BT46: 614105945 | BU46: dd99c847-91df-411c-b804-744f164c493f | BV46: 45985.983 | BY46: submitted_via_web | CA46: vxMcj6EwHzj8L2STtGezta | CC46: 909 | CF46: Stanbic Bank Incubator | CG46: Ming Ming cakes and pastries | CH46: 614105945 | CI46: 1 | CJ46: Nagannya | CK46: Resty | CL46: 36671 | CN46: Female | CO46: 90 | CP46: Ugandan | CQ46: No | CV46: Ugandan | CX46: Wakiso | CY46: Busiro East | CZ46: Sumbwe | DA46: Bulenga | DB46: 706101943 | DC46: kasoziresty006@gmail.com | DD46: Yes | DE46: 200000 | DH46: 1060 | DI46: 10X Digital Economy Expression of interest Form | DJ46: 909 | DK46: 614105945 | DL46: dd99c847-91df-411c-b804-744f164c493f | DM46: 45985.983 | DP46: submitted_via_web | DR46: vxMcj6EwHzj8L2STtGezta | DT46: Stanbic Bank Incubator | DU46: Ming Ming cakes and pastries | DV46: 614105945 | DW46: 1 | DX46: Nagannya | DY46: Yes | EL46: Bulenga | ES46: 1646 | ET46: 10X Digital Economy Expression of interest Form | EU46: 909 | EV46: 614105945 | EW46: dd99c847-91df-411c-b804-744f164c493f | EX46: 45985.983 | FA46: submitted_via_web | FC46: vxMcj6EwHzj8L2STtGezta | GK46: Unique | GL46: 25 | GM46: 25
A47: 0.025334491 | B47: 45986 | C47: Stanbic Bank Incubator | D47: The Tea Spot | E47: We provide tea in all types | F47: Yes | G47: License | H47: No | L47: No | N47: Central | O47: Wakiso | P47: Nsangi | Q47: Kasenge ward | R47: Others | S47: Tea supply | T47: 1 | U47: 1 | V47: 1 | W47: 0 | X47: We deal in all kinds of tea which coffee inclusive | Y47: Limited working place | Z47: 1 | AA47: 1 | AB47: 614109637 | AC47: I cook tea and put spices on to brand my business and make profits | AD47: 500000 | AE47: No | AG47: Yes | AH47: It was all about business skills and financial skills and taught by Baguma Amos which made a great impact in my business | AI47: 3000000 | AJ47: Business uplift | AK47: Because am in a place where my business and products are on a higher demand | AL47: Yes | AM47: I want to register my business | AN47: No | AP47: Yes | AQ47: Teacher and student | AR47: No | AT47: I Wanted to be helped in business like knowledge | AU47: Howard Muhwezi | AV47: 5 - Very easy | AW47: It was all about business | AX47: Yes | AZ47: Easy | BT47: 614109637 | BU47: 66d26e81-4fba-4c3e-86bd-5f919a2cf186 | BV47: 45985.995 | BY47: submitted_via_web | CA47: vxMcj6EwHzj8L2STtGezta | CC47: 910 | CF47: Stanbic Bank Incubator | CG47: The Tea Spot | CH47: 614109637 | CI47: 1 | CJ47: Nabukenya | CK47: Shiba | CL47: 34641 | CN47: Female | CO47: 98 | CP47: Ugandan | CQ47: No | CV47: Ugandan | CX47: Wakiso | CY47: Nsangi | CZ47: Kasenge ward | DA47: Kikajjo | DB47: 782037866 | DC47: dembeamiri226@gmail.com | DD47: Yes | DE47: 300000 | DH47: 1061 | DI47: 10X Digital Economy Expression of interest Form | DJ47: 910 | DK47: 614109637 | DL47: 66d26e81-4fba-4c3e-86bd-5f919a2cf186 | DM47: 45985.995 | DP47: submitted_via_web | DR47: vxMcj6EwHzj8L2STtGezta | DT47: Stanbic Bank Incubator | DU47: The Tea Spot | DV47: 614109637 | DW47: 1 | DX47: Nabukenya | DY47: Yes | EL47: Kikajjo | ES47: 1647 | ET47: 10X Digital Economy Expression of interest Form | EU47: 910 | EV47: 614109637 | EW47: 66d26e81-4fba-4c3e-86bd-5f919a2cf186 | EX47: 45985.995 | FA47: submitted_via_web | FC47: vxMcj6EwHzj8L2STtGezta | GK47: Unique | GL47: 31 | GM47: 31
A48: 0.027454861 | B48: 45986 | C48: Stanbic Bank Incubator | D48: Sharifah fashions | E48: We deal in making all kinds of fashions | F48: No | H48: No | L48: No | N48: Central | O48: Wakiso | P48: Nsangi | Q48: Kasenge ward | R48: fashion and design | T48: 1 | U48: 1 | V48: 1 | W48: 0 | X48: We deal in all kinds of fashion designs | Y48: Working from home | Z48: 1 | AA48: 1 | AB48: 614740113 | AC48: I get materials of cloth and tailoring equipments from town and make beautiful designs of clothes. I get random customers that supports me with profits to keep standing in business | AD48: 0 | AE48: No | AG48: Yes | AH48: It was about business knowledge and financial skills taught by Baguma Amos . I can now grow my business | AI48: 3000000 | AJ48: Financial growth | AK48: Because I have inserted all the knowledge from 10x to my business that I believe is for growth | AL48: Yes | AM48: I want to register my business | AN48: No | AP48: Yes | AQ48: Teacher and student in 10x | AR48: No | AT48: I wanted to grow my business | AU48: Howard Muhwezi | AV48: 4 - Easy | AW48: It was all about business | AX48: Yes | AZ48: Easy | BT48: 614740113 | BU48: 391b1482-07f5-4e11-a2e2-69bb2447b2b8 | BV48: 45986.653 | BY48: submitted_via_web | CA48: vxMcj6EwHzj8L2STtGezta | CC48: 922 | CF48: Stanbic Bank Incubator | CG48: Sharifah fashions | CH48: 614740113 | CI48: 1 | CJ48: Babirye | CK48: Sharifah | CL48: 36521 | CN48: Female | CO48: 98 | CP48: Ugandan | CQ48: No | CV48: Ugandan | CX48: Wakiso | CY48: Nsangi | CZ48: Kasenge ward | DA48: Nkokonjeru | DB48: 751916377 | DC48: bsharifah993@gmail.com | DD48: Yes | DE48: 100000 | DH48: 1073 | DI48: 10X Digital Economy Expression of interest Form | DJ48: 922 | DK48: 614740113 | DL48: 391b1482-07f5-4e11-a2e2-69bb2447b2b8 | DM48: 45986.653 | DP48: submitted_via_web | DR48: vxMcj6EwHzj8L2STtGezta | DT48: Stanbic Bank Incubator | DU48: Sharifah fashions | DV48: 614740113 | DW48: 1 | DX48: Babirye | DY48: Yes | EL48: Nkokonjeru | ES48: 1659 | ET48: 10X Digital Economy Expression of interest Form | EU48: 922 | EV48: 614740113 | EW48: 391b1482-07f5-4e11-a2e2-69bb2447b2b8 | EX48: 45986.653 | FA48: submitted_via_web | FC48: vxMcj6EwHzj8L2STtGezta | GK48: Unique | GL48: 26 | GM48: 26
A49: 0.028116898 | B49: 45986 | C49: Stanbic Bank Incubator | D49: Hope shine beauty salon | E49: We deal in all types and hair styles loll | F49: No | H49: No | L49: No | N49: Central | O49: Wakiso | P49: Nsangi | Q49: Kasenge ward | R49: fashion and design | T49: 1 | U49: 1 | V49: 1 | W49: 0 | X49: We deal in all kinds and hair styles | Y49: Insufficient capital | Z49: 1 | AA49: 1 | AB49: 614802384 | AC49: I get random customers and plait their hair where I get profits to run my business | AD49: 0 | AE49: No | AG49: Yes | AH49: It was all about business knowledge and financial skills taught by Baguma Amos and I learnt more about business | AI49: 3000000 | AJ49: I want to have my own business and also e | AK49: I want to have my own business and also register it | AL49: Yes | AM49: It was all about business knowledge and financial skills taught by Baguma Amos and I learnt more about business | AN49: No | AP49: Yes | AQ49: Teacher and student | AR49: No | AT49: I wanted to get advise on how to have an outstanding business | AU49: Nakiryowa Esther | AV49: 4 - Easy | AW49: Because it was all about business knowledge | AX49: Yes | AZ49: Easy | BT49: 614802384 | BU49: d3a2b3a3-d961-42f2-b1dd-f7e30074b304 | BV49: 45986.7 | BY49: submitted_via_web | CA49: vxMcj6EwHzj8L2STtGezta | CC49: 925 | CF49: Stanbic Bank Incubator | CG49: Hope shine beauty salon | CH49: 614802384 | CI49: 1 | CJ49: Bakita | CK49: Hope | CL49: 37708 | CN49: Female | CO49: 98 | CP49: Ugandan | CQ49: No | CV49: Ugandan | CX49: Wakiso | CY49: Nsangi | CZ49: Kasenge ward | DA49: Kyengera | DB49: 786234810 | DC49: bakitahope3@gmail.com | DD49: Yes | DE49: 200000 | DH49: 1076 | DI49: 10X Digital Economy Expression of interest Form | DJ49: 925 | DK49: 614802384 | DL49: d3a2b3a3-d961-42f2-b1dd-f7e30074b304 | DM49: 45986.7 | DP49: submitted_via_web | DR49: vxMcj6EwHzj8L2STtGezta | DT49: Stanbic Bank Incubator | DU49: Hope shine beauty salon | DV49: 614802384 | DW49: 1 | DX49: Bakita | DY49: Yes | EL49: Kyengera | ES49: 1662 | ET49: 10X Digital Economy Expression of interest Form | EU49: 925 | EV49: 614802384 | EW49: d3a2b3a3-d961-42f2-b1dd-f7e30074b304 | EX49: 45986.7 | FA49: submitted_via_web | FC49: vxMcj6EwHzj8L2STtGezta | GK49: Unique | GL49: 22 | GM49: 22
A50: 0.033784722 | B50: 45986 | C50: Stanbic Bank Incubator | D50: Swafua chips and takeaway | E50: We provide chips and other snacks | F50: No | H50: No | L50: No | N50: Central | O50: Wakiso | Q50: Nsangi | R50: Others | S50: Fast foods | T50: 1 | U50: 1 | V50: 1 | W50: 0 | X50: We deal in chips, takeaway and snacks | Y50: Insufficient capital | Z50: 1 | AA50: 1 | AB50: 614823437 | AC50: I buy Irish, charcoal, cooking oil, flour and other ingredients. Fry them and serve my customers where I get some profits to push me work again the next day | AD50: 0 | AE50: No | AG50: Yes | AH50: It was all about business knowledge and financial skills taught by Baguma Amos | AI50: 3000000 | AJ50: I want to have a business working place for n a business town to eatlrn more money and also develop my current job | AK50: Because I have learnt 10x program courses and am putting them to work that I believe that they will lead me to success | AL50: Yes | AM50: My business isn't registered and I want to register it | AN50: Yes | AO50: Teacher and student | AP50: Yes | AQ50: Teacher and student in 10x | AR50: No | AT50: Teachings for business knowledge | AU50: Nakiryowa Esther | AV50: 5 - Very easy | AW50: Mostly about business | AX50: Yes | AZ50: Easy | BT50: 614823437 | BU50: 4b64c6ee-2b06-440b-89dc-7f4e9c656dea | BV50: 45986.719 | BY50: submitted_via_web | CA50: vxMcj6EwHzj8L2STtGezta | CC50: 926 | CF50: Stanbic Bank Incubator | CG50: Swafua chips and takeaway | CH50: 614823437 | CI50: 1 | CJ50: Namombe | CK50: Swafua | CL50: 37361 | CN50: Female | CO50: 98 | CP50: Ugandan | CQ50: No | CV50: Ugandan | CX50: Wakiso | CY50: Nsangi | CZ50: Kasenge ward | DA50: Kyengera | DB50: 767623319 | DC50: bigronaldkalyesubula@gmail.com | DD50: Yes | DE50: 200000 | DH50: 1077 | DI50: 10X Digital Economy Expression of interest Form | DJ50: 926 | DK50: 614823437 | DL50: 4b64c6ee-2b06-440b-89dc-7f4e9c656dea | DM50: 45986.719 | DP50: submitted_via_web | DR50: vxMcj6EwHzj8L2STtGezta | DT50: Stanbic Bank Incubator | DU50: Swafua chips and takeaway | DV50: 614823437 | DW50: 1 | DX50: Namombe | DY50: Yes | EL50: Kyengera | ES50: 1663 | ET50: 10X Digital Economy Expression of interest Form | EU50: 926 | EV50: 614823437 | EW50: 4b64c6ee-2b06-440b-89dc-7f4e9c656dea | EX50: 45986.719 | FA50: submitted_via_web | FC50: vxMcj6EwHzj8L2STtGezta | GK50: Unique | GL50: 23 | GM50: 23
A51: 0.011327546 | B51: 45986 | C51: Stanbic Bank Incubator | D51: Olivia Beauty salon | E51: We deal for n all kinds of hair fashions | F51: No | H51: No | L51: No | N51: Central | O51: Wakiso | P51: Nsangi | Q51: Nsangi | R51: fashion and design | T51: 1 | U51: 1 | V51: 1 | W51: 0 | X51: We offer all hair styles and fashions | Y51: Working place away from home | Z51: 1 | AA51: 1 | AB51: 614849372 | AC51: I plait customers and earn money | AD51: 0 | AE51: No | AG51: Yes | AH51: It was all about business knowledge and financial skills taught by Baguma Amos and I learnt more about business | AI51: 2000000 | AJ51: Business expansion and financial growth | AK51: Because am going to register it so that I don't get disturbances from the authorities | AL51: Yes | AM51: I want to expand my business and also register it | AN51: Yes | AO51: Teacher and student | AP51: Yes | AQ51: Teacher and student | AR51: No | AT51: I wanted to get business knowledge | AU51: Howard Muhwezi | AV51: 5 - Very easy | AW51: Because it was about business knowledge | AX51: Yes | AZ51: Easy | BT51: 614849372 | BU51: d3e5d22a-a4f9-4832-b740-3d7e96ed7e14 | BV51: 45986.743 | BY51: submitted_via_web | CA51: vxMcj6EwHzj8L2STtGezta | CC51: 927 | CF51: Stanbic Bank Incubator | CG51: Olivia Beauty salon | CH51: 614849372 | CI51: 1 | CJ51: Nakayiwa | CK51: Olivia | CL51: 35001 | CN51: Female | CO51: 98 | CP51: Ugandan | CQ51: No | CV51: Ugandan | CX51: Wakiso | CY51: Nsangi | CZ51: Kasenge ward | DA51: Kikajjo | DB51: 769425321 | DC51: kayiwaolivia90@gmail.com | DD51: Yes | DE51: 200000 | DH51: 1078 | DI51: 10X Digital Economy Expression of interest Form | DJ51: 927 | DK51: 614849372 | DL51: d3e5d22a-a4f9-4832-b740-3d7e96ed7e14 | DM51: 45986.743 | DP51: submitted_via_web | DR51: vxMcj6EwHzj8L2STtGezta | DT51: Stanbic Bank Incubator | DU51: Olivia Beauty salon | DV51: 614849372 | DW51: 1 | DX51: Nakayiwa | DY51: Yes | EL51: Kikajjo | ES51: 1664 | ET51: 10X Digital Economy Expression of interest Form | EU51: 927 | EV51: 614849372 | EW51: d3e5d22a-a4f9-4832-b740-3d7e96ed7e14 | EX51: 45986.743 | FA51: submitted_via_web | FC51: vxMcj6EwHzj8L2STtGezta | GK51: Unique | GL51: 0 | GM51: 30
A52: 0.0049710648 | B52: 45986 | C52: Stanbic Bank Incubator | D52: Breezy fashions | E52: It provides services like makeup,selling clothes,cosmetics and women braids | F52: No | H52: Yes | L52: No | N52: Central | O52: Wakiso | P52: Kajjansi | Q52: Nakawuka | R52: fashion and design | T52: 1 | U52: 1 | V52: 1 | W52: 1 | X52: Makeup,clothes,cosmetics and women's hair | Y52: Marketing and increasing capital | Z52: 6 | AA52: 40 | AB52: 614853719 | AC52: Selling clothes,doing makeup on people,selling cosmetics and women's hair | AD52: 5000000 | AE52: No | AG52: No | AI52: 5000000 | AJ52: Executing a new marketing strategy,growing my brand,getting new skills I don't have | AK52: I have a strategic business location and they are constructing roads | AL52: No | AN52: No | AP52: Yes | AQ52: A friend.Nkoyoyo Gorret | AR52: No | AT52: It's genuine and helps many young ladies to grow in business,becoming financially stable,getting to know more about business language and online marketing strategies | AU52: From a friend | AV52: 5 - Very easy | AW52: It was very good | AX52: Yes | AZ52: It was great to know this program. It's an amazing program | BT52: 614853719 | BU52: 77e35040-642f-4e5e-ba7c-b66ad95ee738 | BV52: 45986.749 | BY52: submitted_via_web | CA52: vxMcj6EwHzj8L2STtGezta | CC52: 928 | CF52: Stanbic Bank Incubator | CG52: Breezy fashions | CH52: 614853719 | CI52: 1 | CJ52: Gloria | CK52: Namatovu | CL52: 37398 | CN52: Female | CO52: 100 | CP52: Ugandan | CQ52: No | CV52: Ugandan | CX52: Wakiso | CY52: Kajjansi | CZ52: Nakawuka | DA52: Nakawuka | DB52: 708411988 | DC52: namatovugloria71@gmail.com | DD52: Yes | DE52: 600000 | DF52: IMG_20251125_202312_881-20_24_53.jpg | DG52: https://kf.kobotoolbox.org/api/v2/assets/a9dTHTe72X7zPceKxVtSxV/data/614853719/attachments/attU6wnWPWKKGXREpW5RjYj8/ | DH52: 1079 | DI52: 10X Digital Economy Expression of interest Form | DJ52: 928 | DK52: 614853719 | DL52: 77e35040-642f-4e5e-ba7c-b66ad95ee738 | DM52: 45986.749 | DP52: submitted_via_web | DR52: vxMcj6EwHzj8L2STtGezta | DT52: Stanbic Bank Incubator | DU52: Breezy fashions | DV52: 614853719 | DW52: 1 | DX52: Gloria | DY52: Yes | EL52: Nakawuka | ES52: 1665 | ET52: 10X Digital Economy Expression of interest Form | EU52: 928 | EV52: 614853719 | EW52: 77e35040-642f-4e5e-ba7c-b66ad95ee738 | EX52: 45986.749 | FA52: submitted_via_web | FC52: vxMcj6EwHzj8L2STtGezta | FE52: Stanbic Bank Incubator | FF52: Breezy fashions | FG52: 614853719 | FH52: 1 | FI52: Gloria | FJ52: Namatovu | FK52: 37398 | FL52: Female | FM52: Chief Executive officer | FN52: 600000 | FO52: No | FQ52: Ugandan | FS52: Wakiso | FT52: Kajjansi | FU52: Nakawuka | FV52: Nakawuka | FW52: 708411988 | FX52: namatovugloria71@gmail.com | FY52: CF0210010ARUCF | FZ52: 573 | GA52: 10X Digital Economy Expression of interest Form | GB52: 928 | GC52: 614853719 | GD52: 77e35040-642f-4e5e-ba7c-b66ad95ee738 | GE52: 45986.749 | GH52: submitted_via_web | GJ52: vxMcj6EwHzj8L2STtGezta | GK52: Unique | GL52: 23 | GM52: 23
A53: 0.0076238426 | B53: 45986 | C53: Stanbic Bank Incubator | D53: Phiona's Bakery | E53: I deal in cakes and cookies | F53: No | H53: No | L53: No | N53: Central | O53: Wakiso | P53: DIVISION A | Q53: KATABI | R53: trade and services | T53: 1 | U53: 1 | V53: 1 | W53: 1 | X53: Cookies, cakes, doughnuts and Daddies | Y53: Capital | Z53: 1 | AA53: 2 | AB53: 614891201 | AC53: I make money through orders and I cost accordingly | AD53: 0 | AE53: No | AG53: No | AI53: 2000000 | AJ53: I will be able to have more equipments | AK53: By advertising my business through social medias | AL53: No | AN53: No | AP53: No | AR53: No | AT53: It is teaching us how to handle our businesses through technology | AU53: They taught us | AV53: 3 - Neutral | AW53: It is because some questions where hard while others where simple | AX53: Yes | BT53: 614891201 | BU53: 975d2934-89ca-47ca-b939-a80096241f79 | BV53: 45986.79 | BY53: submitted_via_web | CA53: vxMcj6EwHzj8L2STtGezta | CC53: 930 | CF53: Stanbic Bank Incubator | CG53: Phiona's Bakery | CH53: 614891201 | CI53: 1 | CJ53: Nassaazi | CK53: Phiona | CL53: 36576 | CN53: Female | CO53: 100 | CP53: Ugandan | CQ53: Yes | CR53: Physical Disability | CS53: 0 | CT53: 0 | CV53: Ugandan | CX53: Wakiso | CY53: Division A | CZ53: Katabi | DA53: Katabi Busambaga | DB53: 760954629 | DC53: nassaaziphiona5@gmail.com | DD53: Yes | DE53: 150000 | DH53: 1081 | DI53: 10X Digital Economy Expression of interest Form | DJ53: 930 | DK53: 614891201 | DL53: 975d2934-89ca-47ca-b939-a80096241f79 | DM53: 45986.79 | DP53: submitted_via_web | DR53: vxMcj6EwHzj8L2STtGezta | DT53: Stanbic Bank Incubator | DU53: Phiona's Bakery | DV53: 614891201 | DW53: 1 | DX53: Ssekyanzi | DY53: No | DZ53: Innocent | EA53: 38764 | EB53: Male | EC53: Helper | ED53: 50000 | EE53: No | EG53: Ugandan | EI53: Wakiso | EJ53: Division A | EK53: Katabi | EL53: Katabi Busanbaga | EM53: 707994629 | EO53: A'level | ES53: 1667 | ET53: 10X Digital Economy Expression of interest Form | EU53: 930 | EV53: 614891201 | EW53: 975d2934-89ca-47ca-b939-a80096241f79 | EX53: 45986.79 | FA53: submitted_via_web | FC53: vxMcj6EwHzj8L2STtGezta | FE53: Stanbic Bank Incubator | FF53: Phiona's Bakery | FG53: 614891201 | FH53: 1 | FI53: MULOWOZA | FJ53: GRACE | FK53: 34078 | FL53: Male | FM53: Part-time employee | FN53: 20000 | FO53: No | FQ53: Ugandan | FS53: Wakiso | FT53: Nsangi | FU53: Kyengera | FV53: Wakimese | FW53: 705620491 | FX53: mulowozagrace@gmail.com | FY53: CM930081066LJE | FZ53: 578 | GA53: 10X Digital Economy Expression of interest Form | GB53: 930 | GC53: 614891201 | GD53: 975d2934-89ca-47ca-b939-a80096241f79 | GE53: 45986.79 | GH53: submitted_via_web | GJ53: vxMcj6EwHzj8L2STtGezta | GK53: Unique | GL53: 25 | GM53: 25
A54: 0.037438657 | B54: 45987 | C54: Stanbic Bank Incubator | D54: Phionah Beauty Salon | E54: We deal in all kinds of hair styles and fashions | F54: No | H54: No | L54: No | N54: Central | O54: Wakiso | P54: Nsangi | Q54: Kasenge ward | R54: fashion and design | T54: 1 | U54: 1 | V54: 1 | W54: 0 | X54: We deal in all kinds of hair styles and fashions | Y54: Limited capital | Z54: 1 | AA54: 1 | AB54: 614996658 | AC54: I buy braids getting ready for customers, plait their hair and get money | AD54: 0 | AE54: No | AG54: Yes | AH54: It was all about business skills and financial literacy that I have been putting to work in my business that has made a great impact | AI54: 3000000 | AJ54: Business growth | AK54: Because I have learnt more about business in 10x foundation course | AL54: Yes | AM54: My business is not yet registered | AN54: Yes | AO54: Teacher and student | AP54: Yes | AQ54: Teacher and student in 10x | AR54: No | AT54: Business growth lessons | AU54: Kayaga Patricia | AV54: 5 - Very easy | AW54: Because it was all about business | AX54: Yes | AZ54: Easy | BT54: 614996658 | BU54: bfa6d189-1407-4417-853e-354428198b31 | BV54: 45986.937 | BY54: submitted_via_web | CA54: vxMcj6EwHzj8L2STtGezta | CC54: 931 | CF54: Stanbic Bank Incubator | CG54: Phionah Beauty Salon | CH54: 614996658 | CI54: 1 | CJ54: Nakanyike | CK54: Phionah | CL54: 36583 | CN54: Female | CO54: 98 | CP54: Ugandan | CQ54: No | CV54: Ugandan | CX54: Wakiso | CY54: Nsangi | CZ54: Kasenge ward | DA54: Kazinga | DB54: 744524687 | DC54: nakanyikephionah854@gmail.com | DD54: Yes | DE54: 200000 | DH54: 1082 | DI54: 10X Digital Economy Expression of interest Form | DJ54: 931 | DK54: 614996658 | DL54: bfa6d189-1407-4417-853e-354428198b31 | DM54: 45986.937 | DP54: submitted_via_web | DR54: vxMcj6EwHzj8L2STtGezta | DT54: Stanbic Bank Incubator | DU54: Phionah Beauty Salon | DV54: 614996658 | DW54: 1 | DX54: Nakanyike | DY54: Yes | EL54: Kazinga | ES54: 1668 | ET54: 10X Digital Economy Expression of interest Form | EU54: 931 | EV54: 614996658 | EW54: bfa6d189-1407-4417-853e-354428198b31 | EX54: 45986.937 | FA54: submitted_via_web | FC54: vxMcj6EwHzj8L2STtGezta | GK54: Unique | GL54: 25 | GM54: 25
A55: 0.026756944 | B55: 45987 | C55: Stanbic Bank Incubator | D55: FifizTABLE LTD | E55: FifizTABLE Ltd is a premier bakery and catering company, celebrated for our delicious event cakes, pastries, and nutritious meals. We believe in the power of food to bring people together, fuelling both joyful celebrations and meaningful social change through skills training for underprivileged individuals. | F55: No | H55: No | L55: No | N55: Central | O55: Wakiso | P55: Makindye Ssabagabo | Q55: Sseguku | R55: Light manufacturing | T55: 1 | U55: 1 | V55: 1 | W55: 2 | X55: FifizTABLE Ltd is a premier bakery and catering company, celebrated for our delicious event cakes, pastries, and nutritious meals. We believe in the power of food to bring people together, fuelling both joyful celebrations and meaningful social change through skills training for underprivileged individuals. | Y55: The need for high-quality, delicious, and celebratory bakery and catering services for events. They solve the problem for customers who want exceptional food to bring people together and create a joyful experience. | Z55: 5 | AA55: 200 | AB55: 615578022 | AC55: FifizTABLE Ltd works by transforming purchased ingredients into premium baked goods and meals, which we sell directly to customers. We make money through a tiered pricing model that reflects the value and cost of our products. Our costs are primarily the ingredients and labour, with a significant portion of our operational focus (and cost) dedicated to our social mission of training underprivileged individuals, which is core to our identity. | AD55: 48000000 | AE55: No | AG55: Yes | AH55: I have participated in key leadership and digital skills programmes that strengthened my entrepreneurial capacity. As a YALI Fellow at Kenyatta University, I gained practical training in business, leadership, and financial management, which improved how I run and grow my enterprise. Through the TEFâ€“GIZ ICT Boot Camp, I learned how to use digital tools to enhance communication, data management, and online business operations. The Andela Women Tech Leadership Program equipped me with basic programming and strong communication skills. Altogether, these programmes gave me an entrepreneurial mindset and the digital competence I apply daily in my work. | AI55: 35000000 | AJ55: With support from the 10X Digital Economy program, I aim to digitize our core operations, expand our services to more communities across the nation, and increase the number of clients we serve by at least 40%. I also plan to strengthen our revenue through digital platforms, improve staff capacity in digital tools, and establish a strong system for real-time impact tracking. Overall, this support will help us scale efficiently, improve customer experience, and position the enterprise for future investment. | AK55: My business is well positioned to grow because we offer clean, healthy foods that meet strong demand from events, households, daily consumers, and corporate clients. Our products are trusted for quality, produced efficiently, and supported by a committed team. With improved distribution and digital reach, we can scale quickly and serve more customers. | AL55: No | AN55: No | AP55: No | AR55: No | AT55: I find 10X Digital Economy Program unique from other programs I have attended in the past because it offers practical skills | AU55: Social Media (LinkedIn) | AV55: 2 - Difficult | AW55: There are very many questions and some are related (Repeated) | AX55: Yes | BT55: 615578022 | BU55: 3bdee1cb-6401-48d0-8cdb-2d5676af5b09 | BV55: 45987.592 | BY55: submitted_via_web | CA55: vxMcj6EwHzj8L2STtGezta | CC55: 941 | CF55: Stanbic Bank Incubator | CG55: FifizTABLE LTD | CH55: 615578022 | CI55: 1 | CJ55: Phiona | CK55: Namutebi | CL55: 32904 | CN55: Female | CO55: 100 | CP55: Ugandan | CQ55: No | CV55: Ugandan | CX55: Wakiso | CY55: Makindye | CZ55: Segguku | DA55: Katale | DB55: 751255370 | DC55: fifinam@gmail.com | DD55: Yes | DE55: 600000 | DH55: 1092 | DI55: 10X Digital Economy Expression of interest Form | DJ55: 941 | DK55: 615578022 | DL55: 3bdee1cb-6401-48d0-8cdb-2d5676af5b09 | DM55: 45987.592 | DP55: submitted_via_web | DR55: vxMcj6EwHzj8L2STtGezta | DT55: Stanbic Bank Incubator | DU55: FifizTABLE LTD | DV55: 615578022 | DW55: 1 | DX55: Phiona Namutebi | DY55: Yes | EL55: Katale, Sseguku | ES55: 1678 | ET55: 10X Digital Economy Expression of interest Form | EU55: 941 | EV55: 615578022 | EW55: 3bdee1cb-6401-48d0-8cdb-2d5676af5b09 | EX55: 45987.592 | FA55: submitted_via_web | FC55: vxMcj6EwHzj8L2STtGezta | FE55: Stanbic Bank Incubator | FF55: FifizTABLE LTD | FG55: 615578022 | FH55: 2 | FI55: Hilda | FJ55: Nakisanja | FK55: 33314 | FL55: Female | FM55: Production | FN55: 600000 | FO55: Yes | FQ55: Ugandan | FS55: Buikwe | FT55: Lugazi | FU55: Kawolo | FV55: Bulyantete | FW55: 708118344 | FX55: hilvic1000@gmail.com | FY55: CF91082103HFNK | FZ55: 580 | GA55: 10X Digital Economy Expression of interest Form | GB55: 941 | GC55: 615578022 | GD55: 3bdee1cb-6401-48d0-8cdb-2d5676af5b09 | GE55: 45987.592 | GH55: submitted_via_web | GJ55: vxMcj6EwHzj8L2STtGezta | GK55: Unique | GL55: 37 | GM55: 37
A56: 0.01930787 | B56: 45987 | C56: Stanbic Bank Incubator | D56: Restys restaurant | E56: For financial | F56: No | H56: No | L56: No | N56: Central | O56: Wakiso | P56: Sisa | Q56: Nakawuka | R56: Others | S56: Restaurant management | T56: 1 | U56: 1 | V56: 1 | W56: 0 | X56: Foodstuff banana,rice,meat | Y56: Poverty | Z56: 30 | AA56: 0 | AB56: 615616872 | AC56: Good,by selling food,aplate at 2000 | AD56: 2400000 | AE56: No | AG56: No | AI56: 5000000 | AJ56: I want to construct a bigger business | AK56: Because it's near the road and every one reaches there | AL56: No | AN56: No | AP56: No | AR56: No | AT56: Employment | AU56: By church group | AV56: 3 - Neutral | AW56: Because we have learned | AX56: Yes | AZ56: Finance development | BT56: 615616872 | BU56: f6f553b2-64df-4e35-9a04-7e08df18d9e0 | BV56: 45987.622 | BY56: submitted_via_web | CA56: vxMcj6EwHzj8L2STtGezta | CC56: 942 | CF56: Stanbic Bank Incubator | CG56: Restys restaurant | CH56: 615616872 | CI56: 1 | CJ56: Ndagire | CK56: Resty | CL56: 35200 | CN56: Female | CO56: 5 | CP56: Ugandan | CQ56: No | CV56: Ugandan | CX56: Wakiso | CY56: Sisa | CZ56: Nakawuka | DA56: Nakawuka | DB56: 765671208 | DC56: ndagireresty@gmail.com | DD56: Yes | DE56: 100000 | DH56: 1093 | DI56: 10X Digital Economy Expression of interest Form | DJ56: 942 | DK56: 615616872 | DL56: f6f553b2-64df-4e35-9a04-7e08df18d9e0 | DM56: 45987.622 | DP56: submitted_via_web | DR56: vxMcj6EwHzj8L2STtGezta | DT56: Stanbic Bank Incubator | DU56: Restys restaurant | DV56: 615616872 | DW56: 1 | DX56: Ndagire | DY56: Yes | EL56: Nakawuka | ES56: 1679 | ET56: 10X Digital Economy Expression of interest Form | EU56: 942 | EV56: 615616872 | EW56: f6f553b2-64df-4e35-9a04-7e08df18d9e0 | EX56: 45987.622 | FA56: submitted_via_web | FC56: vxMcj6EwHzj8L2STtGezta | GK56: Unique | GL56: 29 | GM56: 29
A57: 0.034568287 | B57: 45988 | C57: Stanbic Bank Incubator | D57: Nekesa Delicious chips | E57: We offer chips and other simple foods | F57: No | H57: No | L57: No | N57: Central | O57: Wakiso | P57: Nsangi | Q57: Kasenge ward | R57: Others | S57: Fast foods | T57: 1 | U57: 1 | V57: 1 | W57: 0 | X57: We provide chips and fast foods to the community such that we make ready made food easier to find | Y57: A business working place | Z57: 1 | AA57: 1 | AB57: 615897982 | AC57: I buy Irish potatoes from the market Plus cooking oil charcoal and other vegetables and fry them every evening where I Get Money to stand up tomorrow again in my business after getting profits from my daily customers | AD57: 0 | AE57: No | AG57: Yes | AH57: It was all about business skills and financial literacy taught by Baguma Amos and I learnt more about business growth | AI57: 5000000 | AJ57: I want to have another business aside such that I increase on my earning | AK57: Because of lunch more in the 10x program about business growth and financially dressing that I believe that it will help me and growing my business | AL57: Yes | AM57: I want to register my business | AN57: Yes | AO57: Teacher and student | AP57: Yes | AQ57: Teacher and student | AR57: No | AT57: I have been starting businesses and in the end they fail so I want to have an outstanding business with backup | AU57: Barbra Ruth Magena | AV57: 5 - Very easy | AW57: Because it was all about business skills | AX57: Yes | AZ57: Easy | BT57: 615897982 | BU57: 5e7c6d2a-56bc-46f8-a9af-f7dbf6d6e2cb | BV57: 45987.981 | BY57: submitted_via_web | CA57: vxMcj6EwHzj8L2STtGezta | CC57: 950 | CF57: Stanbic Bank Incubator | CG57: Nekesa Delicious chips | CH57: 615897982 | CI57: 1 | CJ57: Nekesa | CK57: Annet | CL57: 34328 | CN57: Female | CO57: 98 | CP57: Ugandan | CQ57: No | CV57: Ugandan | CX57: Wakiso | CY57: Nsangi | CZ57: Kasenge ward | DA57: Kazinga | DB57: 760769083 | DC57: nekesaannet269@gmail.com | DD57: Yes | DE57: 3000000 | DF57: IMG-20251113-WA0037-2_21_59.jpg | DG57: https://kf.kobotoolbox.org/api/v2/assets/a9dTHTe72X7zPceKxVtSxV/data/615897982/attachments/attx8UDSYbv3LMRGVNeZPBxR/ | DH57: 1101 | DI57: 10X Digital Economy Expression of interest Form | DJ57: 950 | DK57: 615897982 | DL57: 5e7c6d2a-56bc-46f8-a9af-f7dbf6d6e2cb | DM57: 45987.981 | DP57: submitted_via_web | DR57: vxMcj6EwHzj8L2STtGezta | DT57: Stanbic Bank Incubator | DU57: Nekesa Delicious chips | DV57: 615897982 | DW57: 1 | DX57: Nekesa | DY57: Yes | EL57: Kazinga | ES57: 1688 | ET57: 10X Digital Economy Expression of interest Form | EU57: 950 | EV57: 615897982 | EW57: 5e7c6d2a-56bc-46f8-a9af-f7dbf6d6e2cb | EX57: 45987.981 | FA57: submitted_via_web | FC57: vxMcj6EwHzj8L2STtGezta | GK57: Unique | GL57: 32 | GM57: 32
A58: 0.022407407 | B58: 45988 | C58: Stanbic Bank Incubator | D58: Fast soft drinks | E58: We offer soft drinks in all kinds | F58: No | H58: No | L58: No | N58: Central | O58: Wakiso | P58: Nsangi | Q58: Kasenge ward | R58: Others | S58: Soft drinks | T58: 1 | U58: 1 | V58: 1 | W58: 0 | X58: We offer soft, drinks like soda juice in all kinds, mineral water in all types etc | Y58: I want to buy a new refrigerator and expand my business | Z58: 1 | AA58: 1 | AB58: 615902767 | AC58: I buy fruit and blend them, make juice and make money. Also buy soda and mineral water to make supplements | AD58: 0 | AE58: No | AG58: Yes | AH58: It was all about business skills and financial literacy that I have been doing in my business hence improving it. Baguma Amos was the teacher | AI58: 2000000 | AJ58: Business expansion | AK58: Because I am in a business place | AL58: Yes | AM58: I want to register my business | AN58: Yes | AO58: Teacher and student | AP58: Yes | AQ58: Teacher and student | AR58: No | AT58: I wanted to learn more about digital marketing | AU58: Barbra Ruth Magena | AV58: 5 - Very easy | AW58: Business issues | AX58: Yes | AZ58: Easy | BT58: 615902767 | BU58: 2510bbe9-dcea-4243-a964-3010b8a7710a | BV58: 45987.995 | BY58: submitted_via_web | CA58: vxMcj6EwHzj8L2STtGezta | CC58: 951 | CF58: Stanbic Bank Incubator | CG58: Fast soft drinks | CH58: 615902767 | CI58: 1 | CJ58: Namatovu | CK58: Aijera | CL58: 35198 | CN58: Female | CO58: 95 | CP58: Ugandan | CQ58: No | CV58: Ugandan | CX58: Wakiso | CY58: Nsangi | CZ58: Kasenge ward | DA58: Kasenge | DB58: 741691494 | DC58: namatovuaijera998@gmail.com | DD58: Yes | DE58: 200000 | DF58: IMG-20251122-WA0007-2_43_30.jpg | DG58: https://kf.kobotoolbox.org/api/v2/assets/a9dTHTe72X7zPceKxVtSxV/data/615902767/attachments/attCn2DLfEBPCGYmvFzjGK8J/ | DH58: 1102 | DI58: 10X Digital Economy Expression of interest Form | DJ58: 951 | DK58: 615902767 | DL58: 2510bbe9-dcea-4243-a964-3010b8a7710a | DM58: 45987.995 | DP58: submitted_via_web | DR58: vxMcj6EwHzj8L2STtGezta | DT58: Stanbic Bank Incubator | DU58: Fast soft drinks | DV58: 615902767 | DW58: 1 | DX58: Namatovu | DY58: Yes | EL58: Kasenge | ES58: 1689 | ET58: 10X Digital Economy Expression of interest Form | EU58: 951 | EV58: 615902767 | EW58: 2510bbe9-dcea-4243-a964-3010b8a7710a | EX58: 45987.995 | FA58: submitted_via_web | FC58: vxMcj6EwHzj8L2STtGezta | GK58: Unique | GL58: 29 | GM58: 29
A59: 0.037126157 | B59: 45988 | C59: Stanbic Bank Incubator | D59: Sarah's Restaurant | E59: We offer local foods in all types | F59: No | H59: No | L59: No | N59: Central | O59: Wakiso | P59: Nsangi | Q59: Kasenge ward | R59: Others | S59: Restaurant | T59: 1 | U59: 1 | V59: 1 | W59: 0 | X59: We offer and serve ready food most especially local foods | Y59: I want to set up a modern restaurant away from the current one | Z59: 1 | AA59: 1 | AB59: 615907338 | AC59: I buy food and cook it make it ready for customers where I wait for customers come and be served ready food where I get Money and some of your profits that push me to work the next day | AD59: 0 | AE59: No | AG59: Yes | AH59: It was all about business skills and financial literacy for business growth where I learned how to manage business with my personal life | AI59: 2000000 | AJ59: Business expansion and modernisation | AK59: I wanted to learn how to work in a business for a long period of time or my own without feeling | AL59: Yes | AM59: I want to legalise my business | AN59: Yes | AO59: Teacher and student | AP59: Yes | AQ59: Teacher and student | AR59: No | AT59: I wanted to learn how to have a profitable business | AU59: Barbra Ruth Magena | AV59: 5 - Very easy | AW59: Because this was about business issues | AX59: Yes | AZ59: Easy | BT59: 615907338 | BU59: 3d9e251f-8840-4ddd-bd91-53dfb6016b97 | BV59: 45988.01 | BY59: submitted_via_web | CA59: vxMcj6EwHzj8L2STtGezta | CC59: 952 | CF59: Stanbic Bank Incubator | CG59: Sarah's Restaurant | CH59: 615907338 | CI59: 1 | CJ59: Nakaye | CK59: Sarah | CL59: 36558 | CN59: Female | CO59: 98 | CP59: Ugandan | CQ59: No | CV59: Ugandan | CX59: Wakiso | CY59: Nsangi | CZ59: Kasenge ward | DA59: Kasenge | DB59: 709656808 | DC59: nakaye842@gmail.com | DD59: Yes | DE59: 200000 | DH59: 1103 | DI59: 10X Digital Economy Expression of interest Form | DJ59: 952 | DK59: 615907338 | DL59: 3d9e251f-8840-4ddd-bd91-53dfb6016b97 | DM59: 45988.01 | DP59: submitted_via_web | DR59: vxMcj6EwHzj8L2STtGezta | DT59: Stanbic Bank Incubator | DU59: Sarah's Restaurant | DV59: 615907338 | DW59: 1 | DX59: Nakaye | DY59: Yes | EL59: Kasenge | ES59: 1690 | ET59: 10X Digital Economy Expression of interest Form | EU59: 952 | EV59: 615907338 | EW59: 3d9e251f-8840-4ddd-bd91-53dfb6016b97 | EX59: 45988.01 | FA59: submitted_via_web | FC59: vxMcj6EwHzj8L2STtGezta | GK59: Unique | GL59: 24 | GM59: 24
A60: 0.038814815 | B60: 45988 | C60: Stanbic Bank Incubator | D60: Julie Enterprises | E60: I have a retail shop, that has mobile money, liquid soap as I do poultry also | F60: No | H60: No | L60: No | N60: Central | O60: Wakiso | P60: Nansana Municipality | Q60: Nansana Westward | R60: trade and services | T60: 1 | U60: 1 | V60: 1 | W60: 1 | X60: I own a retail shop where I add other products like baked cakes, half cakes, chapati and do liquid soap, shower gel as well as the mobile money business and put them all in the same shop | Y60: My business solves a problem of my clients not to go far for the products I make sure I bring the products closer to them | Z60: 3 | AA60: 5 | AB60: 615975173 | AC60: My business is a cash on delivery mode and I charge normal prices | AD60: 0 | AE60: No | AG60: No | AI60: 50000000 | AJ60: I want to expand my business , make it wholesale because wholesale shops are far from us and also create more employment opportunities to other because when it's expanded I can't maintain it alone | AK60: My business is on the main road so when I expand it can grow and reach to more clients instead of going to other Wholesalers who are far they can all shift and buy from me | AL60: No | AN60: No | AP60: No | AR60: No | AT60: I need to learn more business ideas and business growth as well because I believe that with 10X Digital program I will achieve both Economically, socially and expand | AU60: From a Friend | AV60: 4 - Easy | AW60: Because it asks for the real personal experience and information on my personal business which I know well and can explain well | AX60: Yes | AZ60: After filling this form am willing and waiting to learn more business skills and ideas in a digital way and ready to be mentored | BT60: 615975173 | BU60: 942e3be9-3bfb-4cda-a484-220ff15a1d10 | BV60: 45988.201 | BY60: submitted_via_web | CA60: vxMcj6EwHzj8L2STtGezta | CC60: 953 | CF60: Stanbic Bank Incubator | CG60: Julie Enterprises | CH60: 615975173 | CI60: 1 | CJ60: Juliet | CK60: Nakazzi Sseguya | CL60: 30493 | CN60: Female | CO60: 100 | CP60: Ugandan | CQ60: No | CV60: Ugandan | CX60: Wakiso | CY60: Nansana Municipality | CZ60: Nansana Westward | DA60: Nansana West 1B | DB60: 704273802 | DC60: sseguyajulie1983@gmail.com | DD60: Yes | DE60: 900000 | DF60: Screenshot_2025-11-24-09-13-49-623_com.google.android.apps.photos-9_14_51.jpg | DG60: https://kf.kobotoolbox.org/api/v2/assets/a9dTHTe72X7zPceKxVtSxV/data/615975173/attachments/attSgQFpc3z7RPXnHmdVbUYV/ | DH60: 1104 | DI60: 10X Digital Economy Expression of interest Form | DJ60: 953 | DK60: 615975173 | DL60: 942e3be9-3bfb-4cda-a484-220ff15a1d10 | DM60: 45988.201 | DP60: submitted_via_web | DR60: vxMcj6EwHzj8L2STtGezta | DT60: Stanbic Bank Incubator | DU60: Julie Enterprises | DV60: 615975173 | DW60: 1 | DX60: Juliet | DY60: Yes | EL60: Nansana West. 1 B | ES60: 1691 | ET60: 10X Digital Economy Expression of interest Form | EU60: 953 | EV60: 615975173 | EW60: 942e3be9-3bfb-4cda-a484-220ff15a1d10 | EX60: 45988.201 | FA60: submitted_via_web | FC60: vxMcj6EwHzj8L2STtGezta | FE60: Stanbic Bank Incubator | FF60: Julie Enterprises | FG60: 615975173 | FH60: 1 | FI60: Richard | FJ60: Seguya | FK60: 29739 | FL60: Male | FM60: Consultations and Deliveries | FN60: 300000 | FO60: No | FQ60: Ugandan | FS60: Wakiso | FT60: Nansana Municipality | FU60: Nansana Westward | FV60: Nansana West 1B | FW60: 754056919 | FX60: richardseguya@gmail.com | FY60: CM8105210GTUTL | FZ60: 581 | GA60: 10X Digital Economy Expression of interest Form | GB60: 953 | GC60: 615975173 | GD60: 942e3be9-3bfb-4cda-a484-220ff15a1d10 | GE60: 45988.201 | GH60: submitted_via_web | GJ60: vxMcj6EwHzj8L2STtGezta | GK60: Unique | GL60: 42 | GM60: 42
A61: 0.035181713 | B61: 45988 | C61: Stanbic Bank Incubator | D61: Reins Beauty Pub | E61: We work on beauty we do manicure, pedicure, massage parlour | F61: No | H61: No | L61: No | N61: Central | O61: Wakiso | P61: Nansana Municipality | Q61: Nansana West Ward | R61: trade and services | T61: 1 | U61: 1 | V61: 1 | W61: 0 | X61: Makeup , nails,facial | Y61: It lacks capital | Z61: 2 | AA61: 2 | AB61: 616159459 | AC61: It has got machines that we use to work on clients | AD61: 300000 | AE61: No | AG61: No | AI61: 10000000 | AJ61: Buy more machines | AK61: I have got the best location | AL61: No | AN61: No | AP61: No | AR61: No | AT61: I looked into it and I trusted in it | AU61: From a friend | AV61: 3 - Neutral | AW61: The Question had simplified english | AX61: Yes | AZ61: It has helped me to learn more about the business | BT61: 616159459 | BU61: c73271b0-41e3-4079-8fe5-916d5a8fc9f6 | BV61: 45988.38 | BY61: submitted_via_web | CA61: vxMcj6EwHzj8L2STtGezta | CC61: 954 | CF61: Stanbic Bank Incubator | CG61: Reins Beauty Pub | CH61: 616159459 | CI61: 1 | CJ61: Irene | CK61: Mununuzi | CL61: 36269 | CN61: Female | CO61: 90 | CP61: Ugandan | CQ61: No | CV61: Ugandan | CX61: Wakiso | CY61: Nansana Municipality | CZ61: Nansana Westward | DA61: Nansana West 1B | DB61: 783082228 | DC61: mununuziiryn1999@gmail.com | DD61: Yes | DE61: 800000 | DF61: IMG-20251127-WA0067-11_43_38.jpg | DG61: https://kf.kobotoolbox.org/api/v2/assets/a9dTHTe72X7zPceKxVtSxV/data/616159459/attachments/attyaUPnDWNkFJZNCR3rMK34/ | DH61: 1105 | DI61: 10X Digital Economy Expression of interest Form | DJ61: 954 | DK61: 616159459 | DL61: c73271b0-41e3-4079-8fe5-916d5a8fc9f6 | DM61: 45988.38 | DP61: submitted_via_web | DR61: vxMcj6EwHzj8L2STtGezta | DT61: Stanbic Bank Incubator | DU61: Reins Beauty Pub | DV61: 616159459 | DW61: 1 | DX61: Namirembe | DY61: No | DZ61: Vivian | EA61: 36126 | EB61: Female | EC61: Worker | ED61: 300000 | EE61: No | EG61: Ugandan | EI61: Wakiso | EJ61: Nansana Municipality | EK61: Nansana divison | EL61: Nansana westward | EM61: 707914620 | EO61: S.6 | ES61: 1692 | ET61: 10X Digital Economy Expression of interest Form | EU61: 954 | EV61: 616159459 | EW61: c73271b0-41e3-4079-8fe5-916d5a8fc9f6 | EX61: 45988.38 | FA61: submitted_via_web | FC61: vxMcj6EwHzj8L2STtGezta | GK61: Unique | GL61: 27 | GM61: 27
A62: 0.030024306 | B62: 45988 | C62: Stanbic Bank Incubator | D62: Hair dressing | E62: It provides 20k profits per months | F62: No | H62: No | L62: No | N62: Central | O62: Wakiso | P62: Nakuwadde | Q62: Nakabugo | R62: fashion and design | T62: 2 | U62: 2 | V62: 1 | W62: 0 | X62: We do all women's hairstyles | Y62: The problem of jobs and poverty | Z62: 1 | AA62: 4 | AB62: 619439876 | AC62: We do cornrows for 10000 | AD62: 500000 | AE62: No | AG62: No | AI62: 1000000 | AJ62: Opening other branches in all parts of Uganda | AK62: All our customers love what we do | AL62: No | AN62: No | AP62: No | AR62: No | AT62: I need support in my business | AU62: From men and women from Stanbic bank | AV62: 4 - Easy | AW62: English is a bit hard for me | AX62: Yes | AZ62: This program can help my community | BT62: 619439876 | BU62: e9740440-60bf-467f-a4e3-3baa226357a2 | BV62: 45992.649 | BY62: submitted_via_web | CA62: vCJgLk2yV8oivMfbcbCpCF | CC62: 1037 | CF62: Stanbic Bank Incubator | CG62: Hair dressing | CH62: 619439876 | CI62: 2 | CJ62: Agnes | CK62: Nabukenya | CL62: 38241 | CN62: Female | CO62: 50 | CP62: Ugandan | CQ62: No | CV62: Ugandan | CX62: Wakiso | CY62: Nakuwadde | CZ62: Nakabugo | DA62: Nakuwadde | DB62: 744696221 | DC62: agnesnabukenya@gmail.com | DD62: Yes | DE62: 30000 | DH62: 1196 | DI62: 10X Digital Economy Expression of interest Form | DJ62: 1037 | DK62: 619439876 | DL62: e9740440-60bf-467f-a4e3-3baa226357a2 | DM62: 45992.649 | DP62: submitted_via_web | DR62: vCJgLk2yV8oivMfbcbCpCF | DT62: Stanbic Bank Incubator | DU62: Hair dressing | DV62: 619439876 | DW62: 1 | DX62: Esther | DY62: Yes | EL62: Nakuwadde | ES62: 1798 | ET62: 10X Digital Economy Expression of interest Form | EU62: 1037 | EV62: 619439876 | EW62: e9740440-60bf-467f-a4e3-3baa226357a2 | EX62: 45992.649 | FA62: submitted_via_web | FC62: vCJgLk2yV8oivMfbcbCpCF | GK62: Unique | GL62: 0 | GM62: 21
A63: 0.010768519 | B63: 45989 | C63: Stanbic Bank Incubator | D63: God cares beauty salon | E63: Hairdressing | F63: No | H63: No | L63: No | N63: Central | O63: Wakiso | P63: Kyengera Town Council | Q63: Kasenge | R63: fashion and design | T63: 2 | U63: 2 | V63: 1 | W63: 0 | X63: We plait hair in all styles | Y63: Limited working space | Z63: 1 | AA63: 1 | AB63: 617059044 | AC63: I plait customers and get money especially the random customer who are not within the place or within the community I'm working in, get services and pay more money more than those in thethe community | AD63: 0 | AE63: No | AG63: Yes | AH63: Teacher and student | AI63: 1500000 | AJ63: Business expansion and registration | AK63: Because it can give other young people jobs | AL63: Yes | AM63: I want to register my business | AN63: Yes | AO63: Teacher | AP63: Yes | AQ63: Teacher and student | AR63: No | AT63: Business growth teachings | AU63: Amodo Doreen | AV63: 5 - Very easy | AW63: Business issues | AX63: Yes | AZ63: Easy | BT63: 617059044 | BU63: 50d60c81-275f-4bf7-bde8-b2222ef4eede | BV63: 45989.408 | BY63: submitted_via_web | CA63: vxMcj6EwHzj8L2STtGezta | CC63: 969 | CF63: Stanbic Bank Incubator | CG63: God cares beauty salon | CH63: 617059044 | CI63: 1 | CJ63: Doreen | CK63: Nakigudde | CL63: 33874 | CN63: Female | CO63: 95 | CP63: Ugandan | CQ63: No | CV63: Ugandan | CX63: Wakiso | CY63: Nsangi | CZ63: Kyengera Town Council | DA63: Kazinga | DB63: 756324423 | DC63: doreenkulabako242@gmail.com | DD63: Yes | DE63: 300000 | DF63: IMG-20251128-WA0013-12_28_17.jpg | DG63: https://kf.kobotoolbox.org/api/v2/assets/a9dTHTe72X7zPceKxVtSxV/data/617059044/attachments/attHUT5cNk6mf25ivMDNUZpS/ | DH63: 1124 | DI63: 10X Digital Economy Expression of interest Form | DJ63: 969 | DK63: 617059044 | DL63: 50d60c81-275f-4bf7-bde8-b2222ef4eede | DM63: 45989.408 | DP63: submitted_via_web | DR63: vxMcj6EwHzj8L2STtGezta | DT63: Stanbic Bank Incubator | DU63: God cares beauty salon | DV63: 617059044 | DW63: 1 | DX63: Doreen | DY63: Yes | EL63: Kazinga | ES63: 1711 | ET63: 10X Digital Economy Expression of interest Form | EU63: 969 | EV63: 617059044 | EW63: 50d60c81-275f-4bf7-bde8-b2222ef4eede | EX63: 45989.408 | FA63: submitted_via_web | FC63: vxMcj6EwHzj8L2STtGezta | GK63: Unique | GL63: 29 | GM63: 29
A64: 0.032944444 | B64: 45989 | C64: Stanbic Bank Incubator | D64: Joy's retail shop | E64: Merchandise store | F64: No | H64: No | L64: No | N64: Central | O64: Wakiso | P64: Nsangi | Q64: Kasenge ward | R64: trade and services | T64: 1 | U64: 1 | V64: 1 | W64: 0 | X64: We offer all retail products | Y64: Insufficient capital | Z64: 1 | AA64: 1 | AB64: 617069078 | AC64: I buy products from Wholesale stores to my community and adding a little more money as profits to make money | AD64: 0 | AE64: No | AG64: Yes | AH64: It was all about business skills and financial literacy that I have learnt more taught by Baguma Amos | AI64: 1000000 | AJ64: Business growth | AK64: Because they are inside demand for potato products in my community | AL64: Yes | AM64: I want to register my business | AN64: Yes | AO64: Teacher | AP64: Yes | AQ64: Teacher and student | AR64: No | AT64: Business skills | AU64: Nakiryowa Esther | AV64: 5 - Very easy | AW64: Business skills | AX64: Yes | AZ64: Easy | BT64: 617069078 | BU64: e82c6a48-d4e7-45ae-9dee-6d96e8264f43 | BV64: 45989.417 | BY64: submitted_via_web | CA64: vxMcj6EwHzj8L2STtGezta | CC64: 970 | CF64: Stanbic Bank Incubator | CG64: Joy's retail shop | CH64: 617069078 | CI64: 1 | CJ64: Nalubega | CK64: Ann | CL64: 37548 | CN64: Female | CO64: 98 | CP64: Ugandan | CQ64: No | CV64: Ugandan | CX64: Wakiso | CY64: Nsangi | CZ64: Kasenge ward | DA64: Katale | DB64: 756256230 | DC64: joynalubega430@gmail.com | DD64: Yes | DE64: 200000 | DH64: 1126 | DI64: 10X Digital Economy Expression of interest Form | DJ64: 970 | DK64: 617069078 | DL64: e82c6a48-d4e7-45ae-9dee-6d96e8264f43 | DM64: 45989.417 | DP64: submitted_via_web | DR64: vxMcj6EwHzj8L2STtGezta | DT64: Stanbic Bank Incubator | DU64: Joy's retail shop | DV64: 617069078 | DW64: 1 | DX64: Nalubega | DY64: Yes | EL64: Katale | ES64: 1712 | ET64: 10X Digital Economy Expression of interest Form | EU64: 970 | EV64: 617069078 | EW64: e82c6a48-d4e7-45ae-9dee-6d96e8264f43 | EX64: 45989.417 | FA64: submitted_via_web | FC64: vxMcj6EwHzj8L2STtGezta | GK64: Unique | GL64: 24 | GM64: 24
A65: 0.005474537 | B65: 45989 | C65: Stanbic Bank Incubator | D65: Shoky enterprise s | E65: Male and female garments which includes clothes, shoes and bags | F65: No | H65: No | L65: No | N65: Central | O65: Wakiso | P65: Sissa | Q65: Namulanda | R65: trade and services | T65: 1 | U65: 1 | V65: 1 | W65: 0 | X65: The business has all male and female garments including bags and shoes | Y65: My business tries to solve a problem of in employment | Z65: 1 | AA65: 5 | AB65: 617362915 | AC65: I charge normal charges to all customers | AD65: 5000000 | AE65: No | AG65: No | AI65: 50000000 | AJ65: I seek to achieve a wholesale shop and also to go and do shipping my self | AK65: Because am determined and ready to maintain it and see it grow | AL65: No | AN65: No | AP65: No | AR65: No | AT65: To get more business growth ideas | AU65: From a friend | AV65: 4 - Easy | AW65: It asks personal business information which I know knows and am very well sure of | AX65: Yes | AZ65: Okey | BT65: 617362915 | BU65: 0be17113-7a14-470d-b12e-59aade554ddc | BV65: 45989.65 | BY65: submitted_via_web | CA65: vxMcj6EwHzj8L2STtGezta | CC65: 982 | CF65: Stanbic Bank Incubator | CG65: Shoky enterprise s | CH65: 617362915 | CI65: 1 | CJ65: Lizzie | CK65: Kashokye | CL65: 31118 | CN65: Female | CO65: 100 | CP65: Ugandan | CQ65: No | CV65: Ugandan | CX65: Wakiso | CY65: Sissa | CZ65: Namulanda | DA65: Namulanda B | DB65: 704339744 | DC65: kashokyesasha@gmail.com | DD65: Yes | DE65: 1000000 | DH65: 1139 | DI65: 10X Digital Economy Expression of interest Form | DJ65: 982 | DK65: 617362915 | DL65: 0be17113-7a14-470d-b12e-59aade554ddc | DM65: 45989.65 | DP65: submitted_via_web | DR65: vxMcj6EwHzj8L2STtGezta | DT65: Stanbic Bank Incubator | DU65: Shoky enterprise s | DV65: 617362915 | DW65: 1 | DX65: Lizzie | DY65: Yes | EL65: Namulanda B | ES65: 1733 | ET65: 10X Digital Economy Expression of interest Form | EU65: 982 | EV65: 617362915 | EW65: 0be17113-7a14-470d-b12e-59aade554ddc | EX65: 45989.65 | FA65: submitted_via_web | FC65: vxMcj6EwHzj8L2STtGezta | GK65: Unique | GL65: 40 | GM65: 40
A66: 0.00056712963 | B66: 45989 | C66: Stanbic Bank Incubator | D66: Hadytagz salon | E66: We plait hair in all kinds | F66: No | H66: No | L66: No | N66: Central | O66: Wakiso | P66: Nsangi | Q66: Kasenge ward | R66: fashion and design | T66: 1 | U66: 1 | V66: 1 | W66: 0 | X66: We offer hair styles in all kinds | Y66: Insufficient capital | Z66: 1 | AA66: 1 | AB66: 617078808 | AC66: I plait customers hair and earn money | AD66: 0 | AE66: No | AG66: Yes | AH66: It was all about business skills and financial literacy that I learnt and taught by Baguma Amos | AI66: 2000000 | AJ66: Business registration and growth | AK66: Because there is high demand for the services I offer in my community | AL66: Yes | AM66: Business registration | AN66: Yes | AO66: Teacher | AP66: Yes | AQ66: Teacher and student | AR66: No | AT66: Business support for success | AU66: Nakiryowa Esther | AV66: 4 - Easy | AW66: Business skills | AX66: Yes | AZ66: Easy | BT66: 617078808 | BU66: be439afc-5e71-4713-a68a-d98ec7955077 | BV66: 45989.424 | BY66: submitted_via_web | CA66: vxMcj6EwHzj8L2STtGezta | CC66: 971 | CF66: Stanbic Bank Incubator | CG66: Hadytagz salon | CH66: 617078808 | CI66: 1 | CJ66: Nansubuga | CK66: Hadijja | CL66: 38279 | CN66: Female | CO66: 95 | CP66: Ugandan | CQ66: No | CV66: Ugandan | CX66: Wakiso | CY66: Nsangi | CZ66: Kasenge ward | DA66: Kazinga | DB66: 743855449 | DC66: hadtagz57@gmail.com | DD66: Yes | DE66: 200000 | DH66: 1127 | DI66: 10X Digital Economy Expression of interest Form | DJ66: 971 | DK66: 617078808 | DL66: be439afc-5e71-4713-a68a-d98ec7955077 | DM66: 45989.424 | DP66: submitted_via_web | DR66: vxMcj6EwHzj8L2STtGezta | DT66: Stanbic Bank Incubator | DU66: Hadytagz salon | DV66: 617078808 | DW66: 1 | DX66: Nansubuga | DY66: Yes | EL66: Kazinga | ES66: 1713 | ET66: 10X Digital Economy Expression of interest Form | EU66: 971 | EV66: 617078808 | EW66: be439afc-5e71-4713-a68a-d98ec7955077 | EX66: 45989.424 | FA66: submitted_via_web | FC66: vxMcj6EwHzj8L2STtGezta | GK66: Unique | GL66: 21 | GM66: 21
A67: 0.0074965278 | B67: 45989 | C67: Stanbic Bank Incubator | D67: Jane Enterprises | E67: We offer charcoal and vegetables | F67: No | H67: No | L67: No | N67: Central | O67: Wakiso | P67: Nsangi | Q67: Kasenge ward | R67: trade and services | T67: 1 | U67: 1 | V67: 1 | W67: 0 | X67: We offer charcoal and vegetables in all types | Y67: Limited landscale | Z67: 1 | AA67: 1 | AB67: 617089415 | AC67: I I buy charcoal from Villages nearby and vegetables from markets and sell them to get the money | AD67: 0 | AE67: No | AG67: Yes | AH67: It was all about business skills and financially trusted taught by Baguma Amos and I have learnt more about business | AI67: 1000000 | AJ67: Business growth | AK67: Because I have been working and I know how the system is flowing through trade | AL67: Yes | AM67: I want to know about business registration | AN67: Yes | AO67: Teacher | AP67: Yes | AQ67: Teacher and student | AR67: No | AT67: Business skills for growth | AU67: Barbra Ruth Magena | AV67: 4 - Easy | AW67: Business issues | AX67: Yes | AZ67: Easy | BT67: 617089415 | BU67: 09542c08-5533-4985-b87e-e437d255a1fe | BV67: 45989.432 | BY67: submitted_via_web | CA67: vxMcj6EwHzj8L2STtGezta | CC67: 972 | CF67: Stanbic Bank Incubator | CG67: Jane Enterprises | CH67: 617089415 | CI67: 1 | CJ67: Najjuma | CK67: Jane | CL67: 37362 | CN67: Female | CO67: 95 | CP67: Ugandan | CQ67: No | CV67: Ugandan | CX67: Wakiso | CY67: Nsangi | CZ67: Kasenge ward | DA67: Kikajjo | DB67: 753770536 | DC67: najjumajane@gmail.com | DD67: Yes | DE67: 200000 | DH67: 1128 | DI67: 10X Digital Economy Expression of interest Form | DJ67: 972 | DK67: 617089415 | DL67: 09542c08-5533-4985-b87e-e437d255a1fe | DM67: 45989.432 | DP67: submitted_via_web | DR67: vxMcj6EwHzj8L2STtGezta | DT67: Stanbic Bank Incubator | DU67: Jane Enterprises | DV67: 617089415 | DW67: 1 | DX67: Najjuma | DY67: Yes | EL67: Kikajjo | ES67: 1714 | ET67: 10X Digital Economy Expression of interest Form | EU67: 972 | EV67: 617089415 | EW67: 09542c08-5533-4985-b87e-e437d255a1fe | EX67: 45989.432 | FA67: submitted_via_web | FC67: vxMcj6EwHzj8L2STtGezta | GK67: Unique | GL67: 23 | GM67: 23
A68: 0.015497685 | B68: 45989 | C68: Stanbic Bank Incubator | D68: Pauline hairdressers | E68: We offer hair styles in all types | F68: No | H68: No | L68: No | N68: Central | O68: Wakiso | P68: Nsangi | Q68: Kasenge ward | R68: fashion and design | T68: 1 | U68: 1 | V68: 1 | W68: 0 | X68: We offer hair styles in all kinds | Y68: Limited working space | Z68: 1 | AA68: 1 | AB68: 617097203 | AC68: I plait customers and get money | AD68: 0 | AE68: No | AG68: Yes | AH68: It was all about business skills and financial literacy that I learnt more of business taught by Baguma Amos | AI68: 1000000 | AJ68: Business growth and development | AK68: Because I can employ other people so that they get jobs | AL68: Yes | AM68: I want to learn how to register my business | AN68: Yes | AO68: Teacher | AP68: Yes | AQ68: Teacher and student | AR68: No | AT68: Business growth and development | AU68: Barbra Ruth Magena | AV68: 5 - Very easy | AW68: Business issues | AX68: Yes | AZ68: Easy | BT68: 617097203 | BU68: 8fa759a8-9a55-41fc-b954-39a389485534 | BV68: 45989.438 | BY68: submitted_via_web | CA68: vxMcj6EwHzj8L2STtGezta | CC68: 973 | CF68: Stanbic Bank Incubator | CG68: Pauline hairdressers | CH68: 617097203 | CI68: 1 | CJ68: Nantaba | CK68: Pauline | CL68: 37615 | CN68: Female | CO68: 98 | CP68: Ugandan | CQ68: No | CV68: Ugandan | CX68: Wakiso | CY68: Nsangi | CZ68: Kasenge ward | DA68: Bandwe | DB68: 757717294 | DC68: ssemukojoshua@gmail.com | DD68: Yes | DE68: 100000 | DH68: 1129 | DI68: 10X Digital Economy Expression of interest Form | DJ68: 973 | DK68: 617097203 | DL68: 8fa759a8-9a55-41fc-b954-39a389485534 | DM68: 45989.438 | DP68: submitted_via_web | DR68: vxMcj6EwHzj8L2STtGezta | DT68: Stanbic Bank Incubator | DU68: Pauline hairdressers | DV68: 617097203 | DW68: 1 | DX68: Nantaba | DY68: Yes | EL68: Bandwe | ES68: 1715 | ET68: 10X Digital Economy Expression of interest Form | EU68: 973 | EV68: 617097203 | EW68: 8fa759a8-9a55-41fc-b954-39a389485534 | EX68: 45989.438 | FA68: submitted_via_web | FC68: vxMcj6EwHzj8L2STtGezta | GK68: Unique | GL68: 23 | GM68: 23
A69: 0.021936343 | B69: 45989 | C69: Stanbic Bank Incubator | D69: Esther Fashions | E69: We offer all fashions in all kinds | F69: No | H69: No | L69: No | N69: Central | O69: Wakiso | P69: Nsangi | Q69: Kasenge ward | R69: fashion and design | T69: 1 | U69: 1 | V69: 1 | W69: 0 | X69: We offer all kinds of cloth Fashions | Y69: Insufficient capital | Z69: 1 | AA69: 1 | AB69: 617107058 | AC69: I buy clothes from town saw them and make different kinds of fashions | AD69: 0 | AE69: No | AG69: Yes | AH69: It was about business skills and financial literacy that I learnt more and was taught by Baguma Amos | AI69: 1000000 | AJ69: Business growth and development | AK69: Because I learnt more of my business and how to earn money after learnt the 10x program foundation course | AL69: Yes | AM69: I want to expand my knowledge to other people | AN69: Yes | AO69: Teacher and student | AP69: Yes | AQ69: Teacher and student | AR69: No | AT69: Business growth for success | AU69: Barbra Ruth Magena | AV69: 4 - Easy | AW69: Business issues | AX69: Yes | AZ69: Easy | BT69: 617107058 | BU69: fa658495-92a2-47bb-9a0e-82994e57c817 | BV69: 45989.446 | BY69: submitted_via_web | CA69: vxMcj6EwHzj8L2STtGezta | CC69: 974 | CF69: Stanbic Bank Incubator | CG69: Esther Fashions | CH69: 617107058 | CI69: 1 | CJ69: Tumushabe | CK69: Esther | CL69: 38645 | CN69: Female | CO69: 95 | CP69: Ugandan | CQ69: No | CV69: Ugandan | CX69: Wakiso | CY69: Nsangi | CZ69: Kasenge ward | DA69: Kazinga | DB69: 750525011 | DC69: tumushabe2462@gmail.com | DD69: Yes | DE69: 100000 | DH69: 1130 | DI69: 10X Digital Economy Expression of interest Form | DJ69: 974 | DK69: 617107058 | DL69: fa658495-92a2-47bb-9a0e-82994e57c817 | DM69: 45989.446 | DP69: submitted_via_web | DR69: vxMcj6EwHzj8L2STtGezta | DT69: Stanbic Bank Incubator | DU69: Esther Fashions | DV69: 617107058 | DW69: 1 | DX69: Tumushabe | DY69: Yes | EL69: Kazinga | ES69: 1716 | ET69: 10X Digital Economy Expression of interest Form | EU69: 974 | EV69: 617107058 | EW69: fa658495-92a2-47bb-9a0e-82994e57c817 | EX69: 45989.446 | FA69: submitted_via_web | FC69: vxMcj6EwHzj8L2STtGezta | GK69: Unique | GL69: 20 | GM69: 20
A70: 0.02966088 | B70: 45989 | C70: Stanbic Bank Incubator | D70: Harriet beauty parlour | E70: We offer hair styles in all kinds | F70: No | H70: No | L70: No | N70: Central | O70: Wakiso | P70: Nsangi | Q70: Kasenge ward | R70: fashion and design | T70: 1 | U70: 1 | V70: 1 | W70: 0 | X70: We offer hair styles in all kinds | Y70: Insufficient capital | Z70: 1 | AA70: 1 | AB70: 617124697 | AC70: I plait customers hair and get money | AD70: 0 | AE70: No | AG70: Yes | AH70: I was all about business skills and financial literacy that I learnt more and was taught by Baguma Amos | AI70: 2000000 | AJ70: Business development and management | AK70: I have learnt more in the 10x program about business | AL70: Yes | AM70: I want to learn how to register my business | AN70: Yes | AO70: Teacher | AP70: Yes | AQ70: Teacher and student | AR70: No | AT70: Business knowledge | AU70: Amodo Doreen | AV70: 5 - Very easy | AW70: Business issues | AX70: Yes | AZ70: Easy | BT70: 617124697 | BU70: 42d5978e-b48c-4be1-a4ad-54462527ae3a | BV70: 45989.46 | BY70: submitted_via_web | CA70: vxMcj6EwHzj8L2STtGezta | CC70: 975 | CF70: Stanbic Bank Incubator | CG70: Harriet beauty parlour | CH70: 617124697 | CI70: 1 | CJ70: Mata | CK70: Harriet | CL70: 37217 | CN70: Female | CO70: 98 | CP70: Ugandan | CQ70: No | CV70: Ugandan | CX70: Wakiso | CY70: Nsangi | CZ70: Kasenge ward | DA70: Kazinga | DB70: 754069149 | DC70: mata22430@gmail.com | DD70: Yes | DE70: 200000 | DH70: 1131 | DI70: 10X Digital Economy Expression of interest Form | DJ70: 975 | DK70: 617124697 | DL70: 42d5978e-b48c-4be1-a4ad-54462527ae3a | DM70: 45989.46 | DP70: submitted_via_web | DR70: vxMcj6EwHzj8L2STtGezta | DT70: Stanbic Bank Incubator | DU70: Harriet beauty parlour | DV70: 617124697 | DW70: 1 | DX70: Mata | DY70: Yes | EL70: Kazinga | ES70: 1717 | ET70: 10X Digital Economy Expression of interest Form | EU70: 975 | EV70: 617124697 | EW70: 42d5978e-b48c-4be1-a4ad-54462527ae3a | EX70: 45989.46 | FA70: submitted_via_web | FC70: vxMcj6EwHzj8L2STtGezta | GK70: Unique | GL70: 24 | GM70: 24
A71: 0.017800926 | B71: 45989 | C71: Stanbic Bank Incubator | D71: Sizn's Snacks | E71: I Bake and sell Daddies, Scones, Cakes, Doughnuts, Madazi 's | F71: No | H71: No | L71: No | N71: Central | O71: Wakiso | P71: Kasanje | Q71: Jungo | R71: trade and services | T71: 1 | U71: 1 | V71: 1 | W71: 1 | X71: I Bake locally eg Daddies, Scones, Cakes, Doughnuts, Rock buns, I also train in Bakery skills | Y71: Poverty or Unemployment problem in our communities/ Uganda at large | Z71: 1 | AA71: 0 | AB71: 617146572 | AC71: I Bake, pack in Kaveras or tins, I make money by supplying to shops, work places and i also get personal orders, I charge according to the order, I begin from 500,1000 per pack of silled Kaveras n tin beginning from 11000 and above | AD71: 8400000 | AE71: No | AG71: No | AI71: 19500000 | AJ71: Enlarge my business and gain more sales for Financial stability t | AK71: Depending on the customers I reach daily | AL71: No | AN71: No | AP71: No | AR71: No | AT71: When the 10x economy program Directors came to my community and oriented us on business skills | AU71: Through Mr Ssebagala Francis | AV71: 3 - Neutral | AW71: Some questions were easy some were abit difficult | AX71: Yes | AZ71: Thank you so much for coming in to help us | BT71: 617146572 | BU71: d37ecb63-79af-46d8-880c-4be1d55dc34a | BV71: 45989.477 | BY71: submitted_via_web | CA71: vxMcj6EwHzj8L2STtGezta | CC71: 976 | CE71: Duplicates | CF71: Stanbic Bank Incubator | CG71: Sizn's Snacks | CH71: 617146572 | CI71: 1 | CJ71: Asengo | CK71: Susan Florence | CL71: 32467 | CN71: Female | CO71: 99 | CP71: Uganda | CQ71: No | CV71: Ugandan | CX71: Wakiso | CY71: Kasanje | CZ71: Jungo | DA71: Sakabusolo | DB71: 700803195 | DC71: siznasen@gmail.com | DD71: Yes | DE71: 350000 | DH71: 1132 | DI71: 10X Digital Economy Expression of interest Form | DJ71: 976 | DK71: 617146572 | DL71: d37ecb63-79af-46d8-880c-4be1d55dc34a | DM71: 45989.477 | DP71: submitted_via_web | DR71: vxMcj6EwHzj8L2STtGezta | DT71: Stanbic Bank Incubator | DU71: Sizn's Snacks | DV71: 617146572 | DW71: 1 | DX71: Ejoyi | DY71: No | DZ71: Roy | EA71: 30294 | EB71: Male | EC71: Supplier | ED71: 120000 | EE71: No | EG71: Ugandan | EI71: Arua | EJ71: Manibe | EK71: Eleku | EL71: Onzoro | EM71: 703269126 | EN71: ejoyiroy@gmail.com | EO71: A level | EP71: Cm8200210d6fqg | ES71: 1718 | ET71: 10X Digital Economy Expression of interest Form | EU71: 976 | EV71: 617146572 | EW71: d37ecb63-79af-46d8-880c-4be1d55dc34a | EX71: 45989.477 | FA71: submitted_via_web | FC71: vxMcj6EwHzj8L2STtGezta | FE71: Stanbic Bank Incubator | FF71: Sizn's Snacks | FG71: 617146572 | FH71: 1 | FI71: Lenia | FJ71: Hope | FK71: 39379 | FL71: Female | FM71: Baker and packer | FN71: 100000 | FO71: No | FQ71: Ugandan | FS71: Arua | FT71: Manibe | FU71: Eleku | FV71: Onzoro | FW71: 787375001 | FX71: mambor55@gmail.com | FY71: Non | FZ71: 586 | GA71: 10X Digital Economy Expression of interest Form | GB71: 976 | GC71: 617146572 | GD71: d37ecb63-79af-46d8-880c-4be1d55dc34a | GE71: 45989.477 | GH71: submitted_via_web | GJ71: vxMcj6EwHzj8L2STtGezta | GK71: Unique | GL71: 37 | GM71: 37
A72: 0.011300926 | B72: 45989 | C72: Stanbic Bank Incubator | D72: AW craft makers | E72: Hand made shoes | F72: No | H72: No | L72: No | N72: Central | O72: Wakiso | P72: Division A | Q72: Katabi | R72: fashion and design | T72: 1 | U72: 0 | V72: 1 | W72: 0 | X72: Hand made craft shoes | Y72: Unemployment among the youth | Z72: 1 | AA72: 5 | AB72: 617262751 | AC72: Fashion and design | AD72: 500000 | AE72: No | AG72: No | AI72: 10000000 | AJ72: Expanding and employing more people | AK72: I have learnt how to manage it | AL72: No | AN72: No | AP72: No | AR72: No | AT72: Nakandi Peninah | AU72: Program champion | AV72: 4 - Easy | AW72: I was helped and the people were friendly | AX72: Yes | AZ72: Good work keep it up | BT72: 617262751 | BU72: c6786f0c-e8bc-4604-9e30-6effc873e96e | BV72: 45989.569 | BY72: submitted_via_web | CA72: vxMcj6EwHzj8L2STtGezta | CC72: 979 | CF72: Stanbic Bank Incubator | CG72: AW craft makers | CH72: 617262751 | CI72: 1 | CJ72: William | CK72: Asaba | CL72: 34126 | CN72: Male | CO72: 100 | CP72: Ugandan | CQ72: Yes | CR72: Physical Disability | CS72: 0 | CT72: 0 | CV72: Ugandan | CX72: Wakiso | CY72: Division A | CZ72: Katabi | DA72: Katabi busambaga | DB72: 757551599 | DC72: asabawilliam488@gmail.com | DD72: Yes | DE72: 100000 | DF72: IMG_20251128_162635_557-16_26_52.jpg | DG72: https://kf.kobotoolbox.org/api/v2/assets/a9dTHTe72X7zPceKxVtSxV/data/617262751/attachments/attAFQXXZmiBpEv4kWsMCT6h/ | DH72: 1136 | DI72: 10X Digital Economy Expression of interest Form | DJ72: 979 | DK72: 617262751 | DL72: c6786f0c-e8bc-4604-9e30-6effc873e96e | DM72: 45989.569 | DP72: submitted_via_web | DR72: vxMcj6EwHzj8L2STtGezta | DT72: Stanbic Bank Incubator | DU72: AW craft makers | DV72: 617262751 | DW72: 1 | DX72: Jackline | DY72: No | DZ72: Nabukenya | EA72: 38270 | EB72: Female | EC72: Sales personnel | ED72: 50000 | EE72: No | EG72: Ugandan | EI72: Wakiso | EJ72: Namayumba town council | EK72: Luguzi ward | EL72: Kasanga | EM72: 757372228 | EO72: O level | EP72: CF04052111X37K | ES72: 1730 | ET72: 10X Digital Economy Expression of interest Form | EU72: 979 | EV72: 617262751 | EW72: c6786f0c-e8bc-4604-9e30-6effc873e96e | EX72: 45989.569 | FA72: submitted_via_web | FC72: vxMcj6EwHzj8L2STtGezta | GK72: Unique | GL72: 32 | GM72: 32
A73: 0.0018240741 | B73: 45990 | C73: Stanbic Bank Incubator | D73: Shalom Bakery | E73: We offer all kinds of pastries | F73: No | H73: No | L73: No | N73: Central | O73: Wakiso | P73: Nsangi | Q73: Kasenge ward | R73: Others | S73: Bakery | T73: 1 | U73: 1 | V73: 1 | W73: 0 | X73: We offer all kinds of pastries like cakes, daddies, Cookies and many others | Y73: Insufficient capital | Z73: 1 | AA73: 1 | AB73: 618073604 | AC73: I make my products on customer orders, sell them and get money | AD73: 0 | AE73: No | AG73: Yes | AH73: It was all about business skills and financial literacy that I learnt more and was taught by Baguma Amos | AI73: 5000000 | AJ73: Business growth and life development | AK73: Because I am still energetic and hardworking | AL73: Yes | AM73: I have a certificate in my work | AN73: Yes | AO73: Teacher | AP73: Yes | AQ73: Teacher and student | AR73: No | AT73: Business skills for success | AU73: Nakiryowa Esther | AV73: 5 - Very easy | AW73: Business issues | AX73: Yes | AZ73: Easy | BT73: 618073604 | BU73: 4620d056-5cd7-4f64-a639-328b1f1aaab0 | BV73: 45990.662 | BY73: submitted_via_web | CA73: vxMcj6EwHzj8L2STtGezta | CC73: 986 | CF73: Stanbic Bank Incubator | CG73: Shalom Bakery | CH73: 618073604 | CI73: 1 | CJ73: Nakayima | CK73: Halimah | CL73: 38477 | CN73: Female | CO73: 98 | CP73: Ugandan | CQ73: No | CV73: Ugandan | CX73: Wakiso | CY73: Nsangi | CZ73: Kasenge ward | DA73: Mugongo A | DB73: 702236592 | DC73: tonnymayanja78@gmail.com | DD73: Yes | DE73: 200000 | DH73: 1143 | DI73: 10X Digital Economy Expression of interest Form | DJ73: 986 | DK73: 618073604 | DL73: 4620d056-5cd7-4f64-a639-328b1f1aaab0 | DM73: 45990.662 | DP73: submitted_via_web | DR73: vxMcj6EwHzj8L2STtGezta | DT73: Stanbic Bank Incubator | DU73: Shalom Bakery | DV73: 618073604 | DW73: 1 | DX73: Nakayima | DY73: Yes | EL73: Mugongo A | ES73: 1737 | ET73: 10X Digital Economy Expression of interest Form | EU73: 986 | EV73: 618073604 | EW73: 4620d056-5cd7-4f64-a639-328b1f1aaab0 | EX73: 45990.662 | FA73: submitted_via_web | FC73: vxMcj6EwHzj8L2STtGezta | GK73: Unique | GL73: 20 | GM73: 20
A74: 0.030258102 | B74: 45991 | C74: Stanbic Bank Incubator | D74: Patricia 's piggery rearing | E74: It provides,pork,manure, urine, | F74: No | H74: No | L74: No | N74: Central | O74: Wakiso | P74: Kajjansi | Q74: Nakawuka | R74: Agriculture | T74: 1 | U74: 1 | V74: 2 | W74: 0 | X74: Jt provides manure, pork, urine | Y74: It fertilizes the garden | Z74: 3 | AA74: 3 | AB74: 624399979 | AC74: I am rearing piggs,selling manure , urine. Atrip of manure is charged 120000. | AD74: 2400000 | AE74: Yes | AF74: 3 | AG74: Yes | AH74: Nankanja was running it. | AI74: 6000000 | AJ74: To expand my farm by adding more pigglet and adding more sty. | AK74: Because I expanded my sty,morepiglets I know more customers | AL74: No | AN74: No | AP74: Yes | AQ74: She is amobliser in stanbicincubator | AR74: No | AT74: To get financial support into my business | AU74: I had that it provides financial support to business | AV74: 5 - Very easy | AW74: Because they ask questions about your personal business | AX74: Yes | AZ74: Am waiting for your financial support | BT74: 624399979 | BU74: b1349e1e-246c-4452-88e9-88dcaa39b9c9 | BV74: 45998.668 | BY74: submitted_via_web | CA74: vxMcj6EwHzj8L2STtGezta | CC74: 1418 | CF74: Stanbic Bank Incubator | CG74: Patricia 's piggery rearing | CH74: 624399979 | CI74: 1 | CJ74: Nankanja | CK74: Patricia | CL74: 39004 | CN74: Female | CO74: 80 | CP74: Uganda | CQ74: No | CV74: Ugandan | CX74: Wakiso | CY74: Kajjansi | CZ74: Nakawuka | DA74: Mpumudde | DB74: 758289321 | DC74: nankanja@gmail.com | DD74: Yes | DE74: 100000 | DH74: 1597 | DI74: 10X Digital Economy Expression of interest Form | DJ74: 1418 | DK74: 624399979 | DL74: b1349e1e-246c-4452-88e9-88dcaa39b9c9 | DM74: 45998.668 | DP74: submitted_via_web | DR74: vxMcj6EwHzj8L2STtGezta | DT74: Stanbic Bank Incubator | DU74: Patricia 's piggery rearing | DV74: 624399979 | DW74: 1 | DX74: Batuuka harriet | DY74: No | DZ74: Harriet | EA74: 30473 | EB74: Female | EC74: Is aworker | ED74: 150000 | EE74: No | EG74: Ugandan | EI74: Wakiso | EJ74: Kajjansi | EK74: Nakawuka | EL74: Mpumudde | EM74: 758289321 | EN74: batuuka@gmail.com | EO74: Olevel | ES74: 2222 | ET74: 10X Digital Economy Expression of interest Form | EU74: 1418 | EV74: 624399979 | EW74: b1349e1e-246c-4452-88e9-88dcaa39b9c9 | EX74: 45998.668 | FA74: submitted_via_web | FC74: vxMcj6EwHzj8L2STtGezta | GK74: Unique | GL74: 19 | GM74: 21
A75: 0.030927083 | B75: 45991 | C75: Stanbic Bank Incubator | D75: Hana fashions | E75: It provides dresses, shirts, shorts and trousers for both female and male | F75: No | H75: No | L75: No | N75: Central | O75: Wakiso | P75: Kajjansi | Q75: Nakawuka | R75: fashion and design | T75: 1 | U75: 1 | V75: 2 | W75: 0 | X75: We make dresses, shirts, shorts, trousers and repair | Y75: Making clothes for people | Z75: 3 | AA75: 2 | AB75: 618737614 | AC75: We saw clothes for people at 30000 | AD75: 2400000 | AE75: Yes | AF75: 3 | AG75: Yes | AH75: Hana was running it | AI75: 5000000 | AJ75: To ged moremachines and materials | AK75: Because of the financial assistance I will be able to supply in time I be able to supply in time | AL75: No | AN75: Yes | AO75: She is amobilizer in Stanbic incubator | AP75: Yes | AQ75: She is mobiizer | AR75: No | AT75: To get financial support in my business | AU75: I had tha it gives financial support to business | AV75: 5 - Very easy | AW75: Because they ask about our personal businesses | AX75: Yes | AZ75: am waiting for fincial support | BT75: 618737614 | BU75: df1cda28-880d-4845-b287-86e18bb0c9f8 | BV75: 45991.811 | BY75: submitted_via_web | CA75: vxMcj6EwHzj8L2STtGezta | CC75: 988 | CF75: Stanbic Bank Incubator | CG75: Hana fashions | CH75: 618737614 | CI75: 1 | CJ75: Hana | CK75: Nabwire | CL75: 38828 | CN75: Female | CO75: 80 | CP75: Ugandan | CQ75: No | CV75: Ugandan | CX75: Wakiso | CY75: Kajjansi | CZ75: Nakawuka | DA75: Mpumudde | DB75: 782980819 | DC75: hanah@gmail.com | DD75: Yes | DE75: 100000 | DH75: 1145 | DI75: 10X Digital Economy Expression of interest Form | DJ75: 988 | DK75: 618737614 | DL75: df1cda28-880d-4845-b287-86e18bb0c9f8 | DM75: 45991.811 | DP75: submitted_via_web | DR75: vxMcj6EwHzj8L2STtGezta | DT75: Stanbic Bank Incubator | DU75: Hana fashions | DV75: 618737614 | DW75: 2 | DX75: Hana | DY75: Yes | EL75: Mpumudde | ES75: 1740 | ET75: 10X Digital Economy Expression of interest Form | EU75: 988 | EV75: 618737614 | EW75: df1cda28-880d-4845-b287-86e18bb0c9f8 | EX75: 45991.811 | FA75: submitted_via_web | FC75: vxMcj6EwHzj8L2STtGezta | GK75: Unique | GL75: 19 | GM75: 19
A76: 0.035559028 | B76: 45991 | C76: Stanbic Bank Incubator | D76: Namuddu's piggery | E76: Generates income through selling piglets | F76: No | H76: No | L76: No | N76: Central | O76: Wakiso | P76: Sisa | Q76: Nakawuka | R76: Agriculture | T76: 1 | U76: 1 | V76: 1 | W76: 0 | X76: We sell piglets, mature pigs for pork and manure. | Y76: Poverty | Z76: 1 | AA76: 2 | AB76: 618741035 | AC76: From the start, I bought 2 piglets, both male and female, when they matured, they gave me piglets and I sold some piglets at 80000 each. | AD76: 3000000 | AE76: No | AG76: No | AI76: 5000000 | AJ76: Am going to enlarge my sty and buy more female pigs to produce more piglets. | AK76: Because in my community people like to eat pork more and others want to start the same business by buying piglets and crop farmers want manure. | AL76: No | AN76: No | AP76: No | AR76: No | AT76: The need to grow my project. | AU76: Mobilizer from stanbic incubator | AV76: 3 - Neutral | AW76: Because I understand English | AX76: Yes | AZ76: It was understandable | BT76: 618741035 | BU76: 09f91462-e544-4fee-87e8-5889c4806128 | BV76: 45991.816 | BY76: submitted_via_web | CA76: vxMcj6EwHzj8L2STtGezta | CC76: 989 | CF76: Stanbic Bank Incubator | CG76: Namuddu's piggery | CH76: 618741035 | CI76: 1 | CJ76: Namuddu | CK76: Ruth | CL76: 34243 | CN76: Female | CO76: 80 | CP76: Ugandan | CQ76: No | CV76: Ugandan | CX76: Wakiso | CY76: Kajjansi town council | CZ76: Nakawuka | DA76: Mpumudde | DB76: 779018235 | DC76: ruthnamurr@gmail.com | DD76: Yes | DE76: 80000 | DF76: IMG_20251130_214227_002-22_6_56.jpg | DG76: https://kf.kobotoolbox.org/api/v2/assets/a9dTHTe72X7zPceKxVtSxV/data/618741035/attachments/attFt4KTVNFcsx78hqRfGswZ/ | DH76: 1146 | DI76: 10X Digital Economy Expression of interest Form | DJ76: 989 | DK76: 618741035 | DL76: 09f91462-e544-4fee-87e8-5889c4806128 | DM76: 45991.816 | DP76: submitted_via_web | DR76: vxMcj6EwHzj8L2STtGezta | DT76: Stanbic Bank Incubator | DU76: Namuddu's piggery | DV76: 618741035 | DW76: 1 | DX76: Ssali | DY76: Yes | EL76: Mpumudde | ES76: 1741 | ET76: 10X Digital Economy Expression of interest Form | EU76: 989 | EV76: 618741035 | EW76: 09f91462-e544-4fee-87e8-5889c4806128 | EX76: 45991.816 | FA76: submitted_via_web | FC76: vxMcj6EwHzj8L2STtGezta | GK76: Unique | GL76: 0 | GM76: 32
